Workbook
Name cbo_range: OFFSET(#REF!,0,3,#REF!,1)
Name cbo_range: OFFSET(#REF!,0,3,#REF!,1)
Name cbo_range: OFFSET(#REF!,0,3,#REF!,1)
Name cbo_range: OFFSET(#REF!,0,3,#REF!,1)
Name cbo_range: OFFSET(#REF!,0,3,#REF!,1)
Name cbo_range: OFFSET(#REF!,0,3,#REF!,1)
Name cbo_range: OFFSET(#REF!,0,3,#REF!,1)
Name cbo_range: OFFSET(#REF!,0,3,#REF!,1)
Name cbo_range: OFFSET(#REF!,0,3,#REF!,1)
Name cbo_range: OFFSET(#REF!,0,3,#REF!,1)
Name cbo_range: OFFSET(#REF!,0,3,#REF!,1)
Name date_range: OFFSET(#REF!,0,0,#REF!,1)
Name date_range: OFFSET(#REF!,0,0,#REF!,1)
Name date_range: OFFSET(#REF!,0,0,#REF!,1)
Name date_range: OFFSET(#REF!,0,0,#REF!,1)
Name date_range: OFFSET(#REF!,0,0,#REF!,1)
Name date_range: OFFSET(#REF!,0,0,#REF!,1)
Name date_range: OFFSET(#REF!,0,0,#REF!,1)
Name date_range: OFFSET(#REF!,0,0,#REF!,1)
Name date_range: OFFSET(#REF!,0,0,#REF!,1)
Name date_range: OFFSET(#REF!,0,0,#REF!,1)
Name date_range: OFFSET(#REF!,0,0,#REF!,1)
Name jwi_range: OFFSET(#REF!,0,2,#REF!,1)
Name jwi_range: OFFSET(#REF!,0,2,#REF!,1)
Name jwi_range: OFFSET(#REF!,0,2,#REF!,1)
Name jwi_range: OFFSET(#REF!,0,2,#REF!,1)
Name jwi_range: OFFSET(#REF!,0,2,#REF!,1)
Name jwi_range: OFFSET(#REF!,0,2,#REF!,1)
Name jwi_range: OFFSET(#REF!,0,2,#REF!,1)
Name jwi_range: OFFSET(#REF!,0,2,#REF!,1)
Name jwi_range: OFFSET(#REF!,0,2,#REF!,1)
Name jwi_range: OFFSET(#REF!,0,2,#REF!,1)
Name jwi_range: OFFSET(#REF!,0,2,#REF!,1)
Name jwu_range: OFFSET(#REF!,0,1,#REF!,1)
Name jwu_range: OFFSET(#REF!,0,1,#REF!,1)
Name jwu_range: OFFSET(#REF!,0,1,#REF!,1)
Name jwu_range: OFFSET(#REF!,0,1,#REF!,1)
Name jwu_range: OFFSET(#REF!,0,1,#REF!,1)
Name jwu_range: OFFSET(#REF!,0,1,#REF!,1)
Name jwu_range: OFFSET(#REF!,0,1,#REF!,1)
Name jwu_range: OFFSET(#REF!,0,1,#REF!,1)
Name jwu_range: OFFSET(#REF!,0,1,#REF!,1)
Name jwu_range: OFFSET(#REF!,0,1,#REF!,1)
Name jwu_range: OFFSET(#REF!,0,1,#REF!,1)
Name mst_range: OFFSET(#REF!,0,7,#REF!,1)
Name mst_range: OFFSET(#REF!,0,7,#REF!,1)
Name mst_range: OFFSET(#REF!,0,7,#REF!,1)
Name mst_range: OFFSET(#REF!,0,7,#REF!,1)
Name mst_range: OFFSET(#REF!,0,7,#REF!,1)
Name mst_range: OFFSET(#REF!,0,7,#REF!,1)
Name mst_range: OFFSET(#REF!,0,7,#REF!,1)
Name mst_range: OFFSET(#REF!,0,7,#REF!,1)
Name mst_range: OFFSET(#REF!,0,7,#REF!,1)
Name mst_range: OFFSET(#REF!,0,7,#REF!,1)
Name mst_range: OFFSET(#REF!,0,7,#REF!,1)
Name pivot_range: OFFSET(Participation!#REF!,0,0,Participation!#REF!,9)
Name pivot_range: OFFSET('Stats 2017'!$M$23,0,0,'Stats 2017'!$U$17,9)
Name pivot_range: OFFSET('Stats 2018'!$M$23,0,0,'Stats 2018'!$U$17,9)
Name pivot_range: OFFSET('Stats 2019'!$M$23,0,0,'Stats 2019'!$T$17,9)
Name pivot_range: OFFSET('Stats 2021'!$M$23,0,0,'Stats 2021'!$T$17,9)

Sheet Graphs
C1: ='Stats 2020'!O18 -> JWU | D1: ='Stats 2020'!P18 -> CBO | E1: ='Stats 2020'!Q18 -> PKN | F1: ='Stats 2020'!R18 -> YMI | G1: ='Stats 2020'!S18 -> SJU | H1: ='Stats 2020'!T18 -> MST | I1: =C1 -> JWU | J1: =D1 -> CBO | K1: =E1 -> PKN | L1: =F1 -> YMI | M1: =G1 -> SJU | N1: =H1 -> MST | Q1: =C1 -> JWU | R1: =D1 -> CBO | S1: =E1 -> PKN | T1: =F1 -> YMI | U1: =G1 -> SJU | V1: MSO | Y1: =Q1 -> JWU | Z1: =R1 -> CBO | AA1: =S1 -> PKN | AB1: =T1 -> YMI | AC1: =U1 -> SJU | AD1: =V1 -> MSO | AE1: Overall | AF1: =Y1 -> JWU | AG1: =Z1 -> CBO | AH1: =AA1 -> PKN | AI1: =AB1 -> YMI | AJ1: =AC1 -> SJU | AK1: =AD1 -> MSO | AL1: =AE1 -> Overall | AO1: Prognose-und-Estimation-Nonprofit-Institute of Safran
A2: =IF(AND((TODAY()-B2)<7,(TODAY()-B2>=0)),B2,NA()) -> #N/A | B2: 43854 | C2: =IF($B2<=TODAY(),SUMIF('Stats 2020'!$M$24:$M$1048576,"<="&Graphs!$B2,'Stats 2020'!O$24:O$1048576),NA()) -> 50 | D2: =IF($B2<=TODAY(),MAX($C2,$E2,$G2,$H2)+11,NA()) -> 61 | E2: =IF($B2<=TODAY(),SUMIF('Stats 2020'!$M$24:$M$1048576,"<="&Graphs!$B2,'Stats 2020'!Q$24:Q$1048576),NA()) -> 50 | F2: =IF($B2<=TODAY(),MAX($C2,$E2,$G2,$H2)+11,NA()) -> 61 | G2: =IF($B2<=TODAY(),SUMIF('Stats 2020'!$M$24:$M$1048576,"<="&Graphs!$B2,'Stats 2020'!S$24:S$1048576),NA()) -> 50 | H2: =IF($B2<=TODAY(),SUMIF('Stats 2020'!$M$24:$M$1048576,"<="&Graphs!$B2,'Stats 2020'!T$24:T$1048576),NA()) -> 50 | I2: =VLOOKUP($A2,$B$1:$H$59,MATCH(I$1,$B$1:$H$1,0),0) -> #N/A | J2: =VLOOKUP($A2,$B$1:$H$59,MATCH(J$1,$B$1:$H$1,0),0) -> #N/A | K2: =VLOOKUP($A2,$B$1:$H$59,MATCH(K$1,$B$1:$H$1,0),0) -> #N/A | L2: =VLOOKUP($A2,$B$1:$H$59,MATCH(L$1,$B$1:$H$1,0),0) -> #N/A | M2: =VLOOKUP($A2,$B$1:$H$59,MATCH(M$1,$B$1:$H$1,0),0) -> #N/A | N2: =VLOOKUP($A2,$B$1:$H$59,MATCH(N$1,$B$1:$H$1,0),0) -> #N/A | P2: =B2 -> 43854 | Q2: =VLOOKUP($B2,'Stats 2020'!$D$25:$J$200,MATCH(Graphs!Q$1,'Stats 2020'!$D$18:$J$18,0),0) -> 1 | R2: =VLOOKUP($B2,'Stats 2020'!$D$25:$J$200,MATCH(Graphs!R$1,'Stats 2020'!$D$18:$J$18,0),0) | S2: =VLOOKUP($B2,'Stats 2020'!$D$25:$J$200,MATCH(Graphs!S$1,'Stats 2020'!$D$18:$J$18,0),0) -> 1 | T2: =VLOOKUP($B2,'Stats 2020'!$D$25:$J$200,MATCH(Graphs!T$1,'Stats 2020'!$D$18:$J$18,0),0) | U2: =VLOOKUP($B2,'Stats 2020'!$D$25:$J$200,MATCH(Graphs!U$1,'Stats 2020'!$D$18:$J$18,0),0) -> 1 | V2: =VLOOKUP($B2,'Stats 2020'!$D$25:$J$200,MATCH(Graphs!V$1,'Stats 2020'!$D$18:$J$18,0),0) -> 1 | X2: =B2 -> 43854 | Y2: =SUM(Q$2:Q2)/COUNTA($P$2:$P2) -> 1 | Z2: =SUM(R$2:R2)/COUNTA($P$2:$P2) -> 0 | AA2: =SUM(S$2:S2)/COUNTA($P$2:$P2) -> 1 | AB2: =SUM(T$2:T2)/COUNTA($P$2:$P2) -> 0 | AC2: =SUM(U$2:U2)/COUNTA($P$2:$P2) -> 1 | AD2: =SUM(V$2:V2)/COUNTA($P$2:$P2) -> 1 | AE2: =AVERAGE(Y2:AD2) -> 0.66666667 | AF2: =VLOOKUP($A2,$X$1:$AE$59,MATCH(AF$1,$X$1:$AE$1,0),0) -> #N/A | AG2: =VLOOKUP($A2,$X$1:$AE$59,MATCH(AG$1,$X$1:$AE$1,0),0) -> #N/A | AH2: =VLOOKUP($A2,$X$1:$AE$59,MATCH(AH$1,$X$1:$AE$1,0),0) -> #N/A | AI2: =VLOOKUP($A2,$X$1:$AE$59,MATCH(AI$1,$X$1:$AE$1,0),0) -> #N/A | AJ2: =VLOOKUP($A2,$X$1:$AE$59,MATCH(AJ$1,$X$1:$AE$1,0),0) -> #N/A | AK2: =VLOOKUP($A2,$X$1:$AE$59,MATCH(AK$1,$X$1:$AE$1,0),0) -> #N/A | AL2: =VLOOKUP($A2,$X$1:$AE$59,MATCH(AL$1,$X$1:$AE$1,0),0) -> #N/A | AO2: (PENIS)
A3: =IF(AND((TODAY()-B3)<7,(TODAY()-B3>=0)),B3,NA()) -> #N/A | B3: =B2+7 -> 43861 | C3: =IF($B3<=TODAY(),SUMIF('Stats 2020'!$M$24:$M$1048576,"<="&Graphs!$B3,'Stats 2020'!O$24:O$1048576),NA()) -> 50 | D3: =IF($B3<=TODAY(),MAX($C3,$E3,$G3,$H3)+11,NA()) -> 72 | E3: =IF($B3<=TODAY(),SUMIF('Stats 2020'!$M$24:$M$1048576,"<="&Graphs!$B3,'Stats 2020'!Q$24:Q$1048576),NA()) -> 50 | F3: =IF($B3<=TODAY(),MAX($C3,$E3,$G3,$H3)+11,NA()) -> 72 | G3: =IF($B3<=TODAY(),SUMIF('Stats 2020'!$M$24:$M$1048576,"<="&Graphs!$B3,'Stats 2020'!S$24:S$1048576),NA()) -> 61 | H3: =IF($B3<=TODAY(),SUMIF('Stats 2020'!$M$24:$M$1048576,"<="&Graphs!$B3,'Stats 2020'!T$24:T$1048576),NA()) -> 50 | I3: =VLOOKUP($A3,$B$1:$H$59,MATCH(I$1,$B$1:$H$1,0),0) -> #N/A | J3: =VLOOKUP($A3,$B$1:$H$59,MATCH(J$1,$B$1:$H$1,0),0) -> #N/A | K3: =VLOOKUP($A3,$B$1:$H$59,MATCH(K$1,$B$1:$H$1,0),0) -> #N/A | L3: =VLOOKUP($A3,$B$1:$H$59,MATCH(L$1,$B$1:$H$1,0),0) -> #N/A | M3: =VLOOKUP($A3,$B$1:$H$59,MATCH(M$1,$B$1:$H$1,0),0) -> #N/A | N3: =VLOOKUP($A3,$B$1:$H$59,MATCH(N$1,$B$1:$H$1,0),0) -> #N/A | P3: =B3 -> 43861 | Q3: =VLOOKUP($B3,'Stats 2020'!$D$25:$J$200,MATCH(Graphs!Q$1,'Stats 2020'!$D$18:$J$18,0),0) -> 1 | R3: =VLOOKUP($B3,'Stats 2020'!$D$25:$J$200,MATCH(Graphs!R$1,'Stats 2020'!$D$18:$J$18,0),0) | S3: =VLOOKUP($B3,'Stats 2020'!$D$25:$J$200,MATCH(Graphs!S$1,'Stats 2020'!$D$18:$J$18,0),0) -> 1 | T3: =VLOOKUP($B3,'Stats 2020'!$D$25:$J$200,MATCH(Graphs!T$1,'Stats 2020'!$D$18:$J$18,0),0) | U3: =VLOOKUP($B3,'Stats 2020'!$D$25:$J$200,MATCH(Graphs!U$1,'Stats 2020'!$D$18:$J$18,0),0) -> 0 | V3: =VLOOKUP($B3,'Stats 2020'!$D$25:$J$200,MATCH(Graphs!V$1,'Stats 2020'!$D$18:$J$18,0),0) -> 1 | X3: =B3 -> 43861 | Y3: =SUM(Q$2:Q3)/COUNTA($P$2:$P3) -> 1 | Z3: =SUM(R$2:R3)/COUNTA($P$2:$P3) -> 0 | AA3: =SUM(S$2:S3)/COUNTA($P$2:$P3) -> 1 | AB3: =SUM(T$2:T3)/COUNTA($P$2:$P3) -> 0 | AC3: =SUM(U$2:U3)/COUNTA($P$2:$P3) -> 0.5 | AD3: =SUM(V$2:V3)/COUNTA($P$2:$P3) -> 1 | AE3: =AVERAGE(Y3:AD3) -> 0.58333333 | AF3: =VLOOKUP($A3,$X$1:$AE$59,MATCH(AF$1,$X$1:$AE$1,0),0) -> #N/A | AG3: =VLOOKUP($A3,$X$1:$AE$59,MATCH(AG$1,$X$1:$AE$1,0),0) -> #N/A | AH3: =VLOOKUP($A3,$X$1:$AE$59,MATCH(AH$1,$X$1:$AE$1,0),0) -> #N/A | AI3: =VLOOKUP($A3,$X$1:$AE$59,MATCH(AI$1,$X$1:$AE$1,0),0) -> #N/A | AJ3: =VLOOKUP($A3,$X$1:$AE$59,MATCH(AJ$1,$X$1:$AE$1,0),0) -> #N/A | AK3: =VLOOKUP($A3,$X$1:$AE$59,MATCH(AK$1,$X$1:$AE$1,0),0) -> #N/A | AL3: =VLOOKUP($A3,$X$1:$AE$59,MATCH(AL$1,$X$1:$AE$1,0),0) -> #N/A
A4: =IF(AND((TODAY()-B4)<7,(TODAY()-B4>=0)),B4,NA()) -> #N/A | B4: =B3+7 -> 43868 | C4: =IF($B4<=TODAY(),SUMIF('Stats 2020'!$M$24:$M$1048576,"<="&Graphs!$B4,'Stats 2020'!O$24:O$1048576),NA()) -> 61 | D4: =IF($B4<=TODAY(),MAX($C4,$E4,$G4,$H4)+11,NA()) -> 83 | E4: =IF($B4<=TODAY(),SUMIF('Stats 2020'!$M$24:$M$1048576,"<="&Graphs!$B4,'Stats 2020'!Q$24:Q$1048576),NA()) -> 50 | F4: =IF($B4<=TODAY(),MAX($C4,$E4,$G4,$H4)+11,NA()) -> 83 | G4: =IF($B4<=TODAY(),SUMIF('Stats 2020'!$M$24:$M$1048576,"<="&Graphs!$B4,'Stats 2020'!S$24:S$1048576),NA()) -> 72 | H4: =IF($B4<=TODAY(),SUMIF('Stats 2020'!$M$24:$M$1048576,"<="&Graphs!$B4,'Stats 2020'!T$24:T$1048576),NA()) -> 50 | I4: =VLOOKUP($A4,$B$1:$H$59,MATCH(I$1,$B$1:$H$1,0),0) -> #N/A | J4: =VLOOKUP($A4,$B$1:$H$59,MATCH(J$1,$B$1:$H$1,0),0) -> #N/A | K4: =VLOOKUP($A4,$B$1:$H$59,MATCH(K$1,$B$1:$H$1,0),0) -> #N/A | L4: =VLOOKUP($A4,$B$1:$H$59,MATCH(L$1,$B$1:$H$1,0),0) -> #N/A | M4: =VLOOKUP($A4,$B$1:$H$59,MATCH(M$1,$B$1:$H$1,0),0) -> #N/A | N4: =VLOOKUP($A4,$B$1:$H$59,MATCH(N$1,$B$1:$H$1,0),0) -> #N/A | P4: =B4 -> 43868 | Q4: =VLOOKUP($B4,'Stats 2020'!$D$25:$J$200,MATCH(Graphs!Q$1,'Stats 2020'!$D$18:$J$18,0),0) -> 0 | R4: =VLOOKUP($B4,'Stats 2020'!$D$25:$J$200,MATCH(Graphs!R$1,'Stats 2020'!$D$18:$J$18,0),0) | S4: =VLOOKUP($B4,'Stats 2020'!$D$25:$J$200,MATCH(Graphs!S$1,'Stats 2020'!$D$18:$J$18,0),0) -> 1 | T4: =VLOOKUP($B4,'Stats 2020'!$D$25:$J$200,MATCH(Graphs!T$1,'Stats 2020'!$D$18:$J$18,0),0) | U4: =VLOOKUP($B4,'Stats 2020'!$D$25:$J$200,MATCH(Graphs!U$1,'Stats 2020'!$D$18:$J$18,0),0) -> 0 | V4: =VLOOKUP($B4,'Stats 2020'!$D$25:$J$200,MATCH(Graphs!V$1,'Stats 2020'!$D$18:$J$18,0),0) -> 1 | X4: =B4 -> 43868 | Y4: =SUM(Q$2:Q4)/COUNTA($P$2:$P4) -> 0.66666667 | Z4: =SUM(R$2:R4)/COUNTA($P$2:$P4) -> 0 | AA4: =SUM(S$2:S4)/COUNTA($P$2:$P4) -> 1 | AB4: =SUM(T$2:T4)/COUNTA($P$2:$P4) -> 0 | AC4: =SUM(U$2:U4)/COUNTA($P$2:$P4) -> 0.33333333 | AD4: =SUM(V$2:V4)/COUNTA($P$2:$P4) -> 1 | AE4: =AVERAGE(Y4:AD4) -> 0.5 | AF4: =VLOOKUP($A4,$X$1:$AE$59,MATCH(AF$1,$X$1:$AE$1,0),0) -> #N/A | AG4: =VLOOKUP($A4,$X$1:$AE$59,MATCH(AG$1,$X$1:$AE$1,0),0) -> #N/A | AH4: =VLOOKUP($A4,$X$1:$AE$59,MATCH(AH$1,$X$1:$AE$1,0),0) -> #N/A | AI4: =VLOOKUP($A4,$X$1:$AE$59,MATCH(AI$1,$X$1:$AE$1,0),0) -> #N/A | AJ4: =VLOOKUP($A4,$X$1:$AE$59,MATCH(AJ$1,$X$1:$AE$1,0),0) -> #N/A | AK4: =VLOOKUP($A4,$X$1:$AE$59,MATCH(AK$1,$X$1:$AE$1,0),0) -> #N/A | AL4: =VLOOKUP($A4,$X$1:$AE$59,MATCH(AL$1,$X$1:$AE$1,0),0) -> #N/A
A5: =IF(AND((TODAY()-B5)<7,(TODAY()-B5>=0)),B5,NA()) -> #N/A | B5: =B4+7 -> 43875 | C5: =IF($B5<=TODAY(),SUMIF('Stats 2020'!$M$24:$M$1048576,"<="&Graphs!$B5,'Stats 2020'!O$24:O$1048576),NA()) -> 61 | D5: =IF($B5<=TODAY(),MAX($C5,$E5,$G5,$H5)+11,NA()) -> 94 | E5: =IF($B5<=TODAY(),SUMIF('Stats 2020'!$M$24:$M$1048576,"<="&Graphs!$B5,'Stats 2020'!Q$24:Q$1048576),NA()) -> 50 | F5: =IF($B5<=TODAY(),MAX($C5,$E5,$G5,$H5)+11,NA()) -> 94 | G5: =IF($B5<=TODAY(),SUMIF('Stats 2020'!$M$24:$M$1048576,"<="&Graphs!$B5,'Stats 2020'!S$24:S$1048576),NA()) -> 83 | H5: =IF($B5<=TODAY(),SUMIF('Stats 2020'!$M$24:$M$1048576,"<="&Graphs!$B5,'Stats 2020'!T$24:T$1048576),NA()) -> 50 | I5: =VLOOKUP($A5,$B$1:$H$59,MATCH(I$1,$B$1:$H$1,0),0) -> #N/A | J5: =VLOOKUP($A5,$B$1:$H$59,MATCH(J$1,$B$1:$H$1,0),0) -> #N/A | K5: =VLOOKUP($A5,$B$1:$H$59,MATCH(K$1,$B$1:$H$1,0),0) -> #N/A | L5: =VLOOKUP($A5,$B$1:$H$59,MATCH(L$1,$B$1:$H$1,0),0) -> #N/A | M5: =VLOOKUP($A5,$B$1:$H$59,MATCH(M$1,$B$1:$H$1,0),0) -> #N/A | N5: =VLOOKUP($A5,$B$1:$H$59,MATCH(N$1,$B$1:$H$1,0),0) -> #N/A | P5: =B5 -> 43875 | Q5: =VLOOKUP($B5,'Stats 2020'!$D$25:$J$200,MATCH(Graphs!Q$1,'Stats 2020'!$D$18:$J$18,0),0) -> 1 | R5: =VLOOKUP($B5,'Stats 2020'!$D$25:$J$200,MATCH(Graphs!R$1,'Stats 2020'!$D$18:$J$18,0),0) | S5: =VLOOKUP($B5,'Stats 2020'!$D$25:$J$200,MATCH(Graphs!S$1,'Stats 2020'!$D$18:$J$18,0),0) -> 1 | T5: =VLOOKUP($B5,'Stats 2020'!$D$25:$J$200,MATCH(Graphs!T$1,'Stats 2020'!$D$18:$J$18,0),0) | U5: =VLOOKUP($B5,'Stats 2020'!$D$25:$J$200,MATCH(Graphs!U$1,'Stats 2020'!$D$18:$J$18,0),0) -> 0 | V5: =VLOOKUP($B5,'Stats 2020'!$D$25:$J$200,MATCH(Graphs!V$1,'Stats 2020'!$D$18:$J$18,0),0) -> 1 | X5: =B5 -> 43875 | Y5: =SUM(Q$2:Q5)/COUNTA($P$2:$P5) -> 0.75 | Z5: =SUM(R$2:R5)/COUNTA($P$2:$P5) -> 0 | AA5: =SUM(S$2:S5)/COUNTA($P$2:$P5) -> 1 | AB5: =SUM(T$2:T5)/COUNTA($P$2:$P5) -> 0 | AC5: =SUM(U$2:U5)/COUNTA($P$2:$P5) -> 0.25 | AD5: =SUM(V$2:V5)/COUNTA($P$2:$P5) -> 1 | AE5: =AVERAGE(Y5:AD5) -> 0.5 | AF5: =VLOOKUP($A5,$X$1:$AE$59,MATCH(AF$1,$X$1:$AE$1,0),0) -> #N/A | AG5: =VLOOKUP($A5,$X$1:$AE$59,MATCH(AG$1,$X$1:$AE$1,0),0) -> #N/A | AH5: =VLOOKUP($A5,$X$1:$AE$59,MATCH(AH$1,$X$1:$AE$1,0),0) -> #N/A | AI5: =VLOOKUP($A5,$X$1:$AE$59,MATCH(AI$1,$X$1:$AE$1,0),0) -> #N/A | AJ5: =VLOOKUP($A5,$X$1:$AE$59,MATCH(AJ$1,$X$1:$AE$1,0),0) -> #N/A | AK5: =VLOOKUP($A5,$X$1:$AE$59,MATCH(AK$1,$X$1:$AE$1,0),0) -> #N/A | AL5: =VLOOKUP($A5,$X$1:$AE$59,MATCH(AL$1,$X$1:$AE$1,0),0) -> #N/A | AO5: 1. YMI (203.8%)
A6: =IF(AND((TODAY()-B6)<7,(TODAY()-B6>=0)),B6,NA()) -> #N/A | B6: =B5+7 -> 43882 | C6: =IF($B6<=TODAY(),SUMIF('Stats 2020'!$M$24:$M$1048576,"<="&Graphs!$B6,'Stats 2020'!O$24:O$1048576),NA()) -> 61 | D6: =IF($B6<=TODAY(),MAX($C6,$E6,$G6,$H6)+11,NA()) -> 94 | E6: =IF($B6<=TODAY(),SUMIF('Stats 2020'!$M$24:$M$1048576,"<="&Graphs!$B6,'Stats 2020'!Q$24:Q$1048576),NA()) -> 50 | F6: =IF($B6<=TODAY(),MAX($C6,$E6,$G6,$H6)+11,NA()) -> 94 | G6: =IF($B6<=TODAY(),SUMIF('Stats 2020'!$M$24:$M$1048576,"<="&Graphs!$B6,'Stats 2020'!S$24:S$1048576),NA()) -> 83 | H6: =IF($B6<=TODAY(),SUMIF('Stats 2020'!$M$24:$M$1048576,"<="&Graphs!$B6,'Stats 2020'!T$24:T$1048576),NA()) -> 50 | I6: =VLOOKUP($A6,$B$1:$H$59,MATCH(I$1,$B$1:$H$1,0),0) -> #N/A | J6: =VLOOKUP($A6,$B$1:$H$59,MATCH(J$1,$B$1:$H$1,0),0) -> #N/A | K6: =VLOOKUP($A6,$B$1:$H$59,MATCH(K$1,$B$1:$H$1,0),0) -> #N/A | L6: =VLOOKUP($A6,$B$1:$H$59,MATCH(L$1,$B$1:$H$1,0),0) -> #N/A | M6: =VLOOKUP($A6,$B$1:$H$59,MATCH(M$1,$B$1:$H$1,0),0) -> #N/A | N6: =VLOOKUP($A6,$B$1:$H$59,MATCH(N$1,$B$1:$H$1,0),0) -> #N/A | P6: =B6 -> 43882 | Q6: =VLOOKUP($B6,'Stats 2020'!$D$25:$J$200,MATCH(Graphs!Q$1,'Stats 2020'!$D$18:$J$18,0),0) -> 1 | R6: =VLOOKUP($B6,'Stats 2020'!$D$25:$J$200,MATCH(Graphs!R$1,'Stats 2020'!$D$18:$J$18,0),0) | S6: =VLOOKUP($B6,'Stats 2020'!$D$25:$J$200,MATCH(Graphs!S$1,'Stats 2020'!$D$18:$J$18,0),0) -> 1 | T6: =VLOOKUP($B6,'Stats 2020'!$D$25:$J$200,MATCH(Graphs!T$1,'Stats 2020'!$D$18:$J$18,0),0) | U6: =VLOOKUP($B6,'Stats 2020'!$D$25:$J$200,MATCH(Graphs!U$1,'Stats 2020'!$D$18:$J$18,0),0) -> 1 | V6: =VLOOKUP($B6,'Stats 2020'!$D$25:$J$200,MATCH(Graphs!V$1,'Stats 2020'!$D$18:$J$18,0),0) -> 1 | X6: =B6 -> 43882 | Y6: =SUM(Q$2:Q6)/COUNTA($P$2:$P6) -> 0.8 | Z6: =SUM(R$2:R6)/COUNTA($P$2:$P6) -> 0 | AA6: =SUM(S$2:S6)/COUNTA($P$2:$P6) -> 1 | AB6: =SUM(T$2:T6)/COUNTA($P$2:$P6) -> 0 | AC6: =SUM(U$2:U6)/COUNTA($P$2:$P6) -> 0.4 | AD6: =SUM(V$2:V6)/COUNTA($P$2:$P6) -> 1 | AE6: =AVERAGE(Y6:AD6) -> 0.53333333 | AF6: =VLOOKUP($A6,$X$1:$AE$59,MATCH(AF$1,$X$1:$AE$1,0),0) -> #N/A | AG6: =VLOOKUP($A6,$X$1:$AE$59,MATCH(AG$1,$X$1:$AE$1,0),0) -> #N/A | AH6: =VLOOKUP($A6,$X$1:$AE$59,MATCH(AH$1,$X$1:$AE$1,0),0) -> #N/A | AI6: =VLOOKUP($A6,$X$1:$AE$59,MATCH(AI$1,$X$1:$AE$1,0),0) -> #N/A | AJ6: =VLOOKUP($A6,$X$1:$AE$59,MATCH(AJ$1,$X$1:$AE$1,0),0) -> #N/A | AK6: =VLOOKUP($A6,$X$1:$AE$59,MATCH(AK$1,$X$1:$AE$1,0),0) -> #N/A | AL6: =VLOOKUP($A6,$X$1:$AE$59,MATCH(AL$1,$X$1:$AE$1,0),0) -> #N/A | AO6: 2. SJU (134.6%)
A7: =IF(AND((TODAY()-B7)<7,(TODAY()-B7>=0)),B7,NA()) -> #N/A | B7: =B6+7 -> 43889 | C7: =IF($B7<=TODAY(),SUMIF('Stats 2020'!$M$24:$M$1048576,"<="&Graphs!$B7,'Stats 2020'!O$24:O$1048576),NA()) -> 63.75 | D7: =IF($B7<=TODAY(),MAX($C7,$E7,$G7,$H7)+11,NA()) -> 96.75 | E7: =IF($B7<=TODAY(),SUMIF('Stats 2020'!$M$24:$M$1048576,"<="&Graphs!$B7,'Stats 2020'!Q$24:Q$1048576),NA()) -> 61 | F7: =IF($B7<=TODAY(),MAX($C7,$E7,$G7,$H7)+11,NA()) -> 96.75 | G7: =IF($B7<=TODAY(),SUMIF('Stats 2020'!$M$24:$M$1048576,"<="&Graphs!$B7,'Stats 2020'!S$24:S$1048576),NA()) -> 85.75 | H7: =IF($B7<=TODAY(),SUMIF('Stats 2020'!$M$24:$M$1048576,"<="&Graphs!$B7,'Stats 2020'!T$24:T$1048576),NA()) -> 61 | I7: =VLOOKUP($A7,$B$1:$H$59,MATCH(I$1,$B$1:$H$1,0),0) -> #N/A | J7: =VLOOKUP($A7,$B$1:$H$59,MATCH(J$1,$B$1:$H$1,0),0) -> #N/A | K7: =VLOOKUP($A7,$B$1:$H$59,MATCH(K$1,$B$1:$H$1,0),0) -> #N/A | L7: =VLOOKUP($A7,$B$1:$H$59,MATCH(L$1,$B$1:$H$1,0),0) -> #N/A | M7: =VLOOKUP($A7,$B$1:$H$59,MATCH(M$1,$B$1:$H$1,0),0) -> #N/A | N7: =VLOOKUP($A7,$B$1:$H$59,MATCH(N$1,$B$1:$H$1,0),0) -> #N/A | P7: =B7 -> 43889 | Q7: =VLOOKUP($B7,'Stats 2020'!$D$25:$J$200,MATCH(Graphs!Q$1,'Stats 2020'!$D$18:$J$18,0),0) -> 1 | R7: =VLOOKUP($B7,'Stats 2020'!$D$25:$J$200,MATCH(Graphs!R$1,'Stats 2020'!$D$18:$J$18,0),0) | S7: =VLOOKUP($B7,'Stats 2020'!$D$25:$J$200,MATCH(Graphs!S$1,'Stats 2020'!$D$18:$J$18,0),0) -> 0 | T7: =VLOOKUP($B7,'Stats 2020'!$D$25:$J$200,MATCH(Graphs!T$1,'Stats 2020'!$D$18:$J$18,0),0) | U7: =VLOOKUP($B7,'Stats 2020'!$D$25:$J$200,MATCH(Graphs!U$1,'Stats 2020'!$D$18:$J$18,0),0) -> 1 | V7: =VLOOKUP($B7,'Stats 2020'!$D$25:$J$200,MATCH(Graphs!V$1,'Stats 2020'!$D$18:$J$18,0),0) -> 0 | X7: =B7 -> 43889 | Y7: =SUM(Q$2:Q7)/COUNTA($P$2:$P7) -> 0.83333333 | Z7: =SUM(R$2:R7)/COUNTA($P$2:$P7) -> 0 | AA7: =SUM(S$2:S7)/COUNTA($P$2:$P7) -> 0.83333333 | AB7: =SUM(T$2:T7)/COUNTA($P$2:$P7) -> 0 | AC7: =SUM(U$2:U7)/COUNTA($P$2:$P7) -> 0.5 | AD7: =SUM(V$2:V7)/COUNTA($P$2:$P7) -> 0.83333333 | AE7: =AVERAGE(Y7:AD7) -> 0.5 | AF7: =VLOOKUP($A7,$X$1:$AE$59,MATCH(AF$1,$X$1:$AE$1,0),0) -> #N/A | AG7: =VLOOKUP($A7,$X$1:$AE$59,MATCH(AG$1,$X$1:$AE$1,0),0) -> #N/A | AH7: =VLOOKUP($A7,$X$1:$AE$59,MATCH(AH$1,$X$1:$AE$1,0),0) -> #N/A | AI7: =VLOOKUP($A7,$X$1:$AE$59,MATCH(AI$1,$X$1:$AE$1,0),0) -> #N/A | AJ7: =VLOOKUP($A7,$X$1:$AE$59,MATCH(AJ$1,$X$1:$AE$1,0),0) -> #N/A | AK7: =VLOOKUP($A7,$X$1:$AE$59,MATCH(AK$1,$X$1:$AE$1,0),0) -> #N/A | AL7: =VLOOKUP($A7,$X$1:$AE$59,MATCH(AL$1,$X$1:$AE$1,0),0) -> #N/A | AO7: 3. PKN (123.1%)
A8: =IF(AND((TODAY()-B8)<7,(TODAY()-B8>=0)),B8,NA()) -> #N/A | B8: =B7+7 -> 43896 | C8: =IF($B8<=TODAY(),SUMIF('Stats 2020'!$M$24:$M$1048576,"<="&Graphs!$B8,'Stats 2020'!O$24:O$1048576),NA()) -> 63.75 | D8: =IF($B8<=TODAY(),MAX($C8,$E8,$G8,$H8)+11,NA()) -> 96.75 | E8: =IF($B8<=TODAY(),SUMIF('Stats 2020'!$M$24:$M$1048576,"<="&Graphs!$B8,'Stats 2020'!Q$24:Q$1048576),NA()) -> 61 | F8: =IF($B8<=TODAY(),MAX($C8,$E8,$G8,$H8)+11,NA()) -> 96.75 | G8: =IF($B8<=TODAY(),SUMIF('Stats 2020'!$M$24:$M$1048576,"<="&Graphs!$B8,'Stats 2020'!S$24:S$1048576),NA()) -> 85.75 | H8: =IF($B8<=TODAY(),SUMIF('Stats 2020'!$M$24:$M$1048576,"<="&Graphs!$B8,'Stats 2020'!T$24:T$1048576),NA()) -> 61 | I8: =VLOOKUP($A8,$B$1:$H$59,MATCH(I$1,$B$1:$H$1,0),0) -> #N/A | J8: =VLOOKUP($A8,$B$1:$H$59,MATCH(J$1,$B$1:$H$1,0),0) -> #N/A | K8: =VLOOKUP($A8,$B$1:$H$59,MATCH(K$1,$B$1:$H$1,0),0) -> #N/A | L8: =VLOOKUP($A8,$B$1:$H$59,MATCH(L$1,$B$1:$H$1,0),0) -> #N/A | M8: =VLOOKUP($A8,$B$1:$H$59,MATCH(M$1,$B$1:$H$1,0),0) -> #N/A | N8: =VLOOKUP($A8,$B$1:$H$59,MATCH(N$1,$B$1:$H$1,0),0) -> #N/A | P8: =B8 -> 43896 | Q8: =VLOOKUP($B8,'Stats 2020'!$D$25:$J$200,MATCH(Graphs!Q$1,'Stats 2020'!$D$18:$J$18,0),0) -> 1 | R8: =VLOOKUP($B8,'Stats 2020'!$D$25:$J$200,MATCH(Graphs!R$1,'Stats 2020'!$D$18:$J$18,0),0) | S8: =VLOOKUP($B8,'Stats 2020'!$D$25:$J$200,MATCH(Graphs!S$1,'Stats 2020'!$D$18:$J$18,0),0) -> 1 | T8: =VLOOKUP($B8,'Stats 2020'!$D$25:$J$200,MATCH(Graphs!T$1,'Stats 2020'!$D$18:$J$18,0),0) | U8: =VLOOKUP($B8,'Stats 2020'!$D$25:$J$200,MATCH(Graphs!U$1,'Stats 2020'!$D$18:$J$18,0),0) -> 1 | V8: =VLOOKUP($B8,'Stats 2020'!$D$25:$J$200,MATCH(Graphs!V$1,'Stats 2020'!$D$18:$J$18,0),0) -> 1 | X8: =B8 -> 43896 | Y8: =SUM(Q$2:Q8)/COUNTA($P$2:$P8) -> 0.85714286 | Z8: =SUM(R$2:R8)/COUNTA($P$2:$P8) -> 0 | AA8: =SUM(S$2:S8)/COUNTA($P$2:$P8) -> 0.85714286 | AB8: =SUM(T$2:T8)/COUNTA($P$2:$P8) -> 0 | AC8: =SUM(U$2:U8)/COUNTA($P$2:$P8) -> 0.57142857 | AD8: =SUM(V$2:V8)/COUNTA($P$2:$P8) -> 0.85714286 | AE8: =AVERAGE(Y8:AD8) -> 0.52380952 | AF8: =VLOOKUP($A8,$X$1:$AE$59,MATCH(AF$1,$X$1:$AE$1,0),0) -> #N/A | AG8: =VLOOKUP($A8,$X$1:$AE$59,MATCH(AG$1,$X$1:$AE$1,0),0) -> #N/A | AH8: =VLOOKUP($A8,$X$1:$AE$59,MATCH(AH$1,$X$1:$AE$1,0),0) -> #N/A | AI8: =VLOOKUP($A8,$X$1:$AE$59,MATCH(AI$1,$X$1:$AE$1,0),0) -> #N/A | AJ8: =VLOOKUP($A8,$X$1:$AE$59,MATCH(AJ$1,$X$1:$AE$1,0),0) -> #N/A | AK8: =VLOOKUP($A8,$X$1:$AE$59,MATCH(AK$1,$X$1:$AE$1,0),0) -> #N/A | AL8: =VLOOKUP($A8,$X$1:$AE$59,MATCH(AL$1,$X$1:$AE$1,0),0) -> #N/A | AO8: 4. MSO/MST und JWU (je 116.5%)
A9: =IF(AND((TODAY()-B9)<7,(TODAY()-B9>=0)),B9,NA()) -> #N/A | B9: =B8+7 -> 43903 | C9: =IF($B9<=TODAY(),SUMIF('Stats 2020'!$M$24:$M$1048576,"<="&Graphs!$B9,'Stats 2020'!O$24:O$1048576),NA()) -> 63.75 | D9: =IF($B9<=TODAY(),MAX($C9,$E9,$G9,$H9)+11+16.5,NA()) -> 113.25 | E9: =IF($B9<=TODAY(),SUMIF('Stats 2020'!$M$24:$M$1048576,"<="&Graphs!$B9,'Stats 2020'!Q$24:Q$1048576),NA()) -> 72 | F9: =IF($B9<=TODAY(),MAX($C9,$E9,$G9,$H9)+11+16.5,NA()) -> 113.25 | G9: =IF($B9<=TODAY(),SUMIF('Stats 2020'!$M$24:$M$1048576,"<="&Graphs!$B9,'Stats 2020'!S$24:S$1048576),NA()) -> 85.75 | H9: =IF($B9<=TODAY(),SUMIF('Stats 2020'!$M$24:$M$1048576,"<="&Graphs!$B9,'Stats 2020'!T$24:T$1048576),NA()) -> 61 | I9: =VLOOKUP($A9,$B$1:$H$59,MATCH(I$1,$B$1:$H$1,0),0) -> #N/A | J9: =VLOOKUP($A9,$B$1:$H$59,MATCH(J$1,$B$1:$H$1,0),0) -> #N/A | K9: =VLOOKUP($A9,$B$1:$H$59,MATCH(K$1,$B$1:$H$1,0),0) -> #N/A | L9: =VLOOKUP($A9,$B$1:$H$59,MATCH(L$1,$B$1:$H$1,0),0) -> #N/A | M9: =VLOOKUP($A9,$B$1:$H$59,MATCH(M$1,$B$1:$H$1,0),0) -> #N/A | N9: =VLOOKUP($A9,$B$1:$H$59,MATCH(N$1,$B$1:$H$1,0),0) -> #N/A | P9: =B9 -> 43903 | Q9: =VLOOKUP($B9,'Stats 2020'!$D$25:$J$200,MATCH(Graphs!Q$1,'Stats 2020'!$D$18:$J$18,0),0) -> 1 | R9: =VLOOKUP($B9,'Stats 2020'!$D$25:$J$200,MATCH(Graphs!R$1,'Stats 2020'!$D$18:$J$18,0),0) | S9: =VLOOKUP($B9,'Stats 2020'!$D$25:$J$200,MATCH(Graphs!S$1,'Stats 2020'!$D$18:$J$18,0),0) -> 0 | T9: =VLOOKUP($B9,'Stats 2020'!$D$25:$J$200,MATCH(Graphs!T$1,'Stats 2020'!$D$18:$J$18,0),0) | U9: =VLOOKUP($B9,'Stats 2020'!$D$25:$J$200,MATCH(Graphs!U$1,'Stats 2020'!$D$18:$J$18,0),0) -> 1 | V9: =VLOOKUP($B9,'Stats 2020'!$D$25:$J$200,MATCH(Graphs!V$1,'Stats 2020'!$D$18:$J$18,0),0) -> 1 | X9: =B9 -> 43903 | Y9: =SUM(Q$2:Q9)/COUNTA($P$2:$P9) -> 0.875 | Z9: =SUM(R$2:R9)/COUNTA($P$2:$P9) -> 0 | AA9: =SUM(S$2:S9)/COUNTA($P$2:$P9) -> 0.75 | AB9: =SUM(T$2:T9)/COUNTA($P$2:$P9) -> 0 | AC9: =SUM(U$2:U9)/COUNTA($P$2:$P9) -> 0.625 | AD9: =SUM(V$2:V9)/COUNTA($P$2:$P9) -> 0.875 | AE9: =AVERAGE(Y9:AD9) -> 0.52083333 | AF9: =VLOOKUP($A9,$X$1:$AE$59,MATCH(AF$1,$X$1:$AE$1,0),0) -> #N/A | AG9: =VLOOKUP($A9,$X$1:$AE$59,MATCH(AG$1,$X$1:$AE$1,0),0) -> #N/A | AH9: =VLOOKUP($A9,$X$1:$AE$59,MATCH(AH$1,$X$1:$AE$1,0),0) -> #N/A | AI9: =VLOOKUP($A9,$X$1:$AE$59,MATCH(AI$1,$X$1:$AE$1,0),0) -> #N/A | AJ9: =VLOOKUP($A9,$X$1:$AE$59,MATCH(AJ$1,$X$1:$AE$1,0),0) -> #N/A | AK9: =VLOOKUP($A9,$X$1:$AE$59,MATCH(AK$1,$X$1:$AE$1,0),0) -> #N/A | AL9: =VLOOKUP($A9,$X$1:$AE$59,MATCH(AL$1,$X$1:$AE$1,0),0) -> #N/A | AO9: 5. CBO (-11.5%)
A10: =IF(AND((TODAY()-B10)<7,(TODAY()-B10>=0)),B10,NA()) -> #N/A | B10: =B9+7 -> 43910 | C10: =IF($B10<=TODAY(),SUMIF('Stats 2020'!$M$24:$M$1048576,"<="&Graphs!$B10,'Stats 2020'!O$24:O$1048576),NA()) -> 63.75 | D10: =IF($B10<=TODAY(),MAX($C10,$E10,$G10,$H10)+11+16.5,NA()) -> 113.25 | E10: =IF($B10<=TODAY(),SUMIF('Stats 2020'!$M$24:$M$1048576,"<="&Graphs!$B10,'Stats 2020'!Q$24:Q$1048576),NA()) -> 72 | F10: =IF($B10<=TODAY(),MAX($C10,$E10,$G10,$H10)+11+16.5,NA()) -> 113.25 | G10: =IF($B10<=TODAY(),SUMIF('Stats 2020'!$M$24:$M$1048576,"<="&Graphs!$B10,'Stats 2020'!S$24:S$1048576),NA()) -> 85.75 | H10: =IF($B10<=TODAY(),SUMIF('Stats 2020'!$M$24:$M$1048576,"<="&Graphs!$B10,'Stats 2020'!T$24:T$1048576),NA()) -> 61 | I10: =VLOOKUP($A10,$B$1:$H$59,MATCH(I$1,$B$1:$H$1,0),0) -> #N/A | J10: =VLOOKUP($A10,$B$1:$H$59,MATCH(J$1,$B$1:$H$1,0),0) -> #N/A | K10: =VLOOKUP($A10,$B$1:$H$59,MATCH(K$1,$B$1:$H$1,0),0) -> #N/A | L10: =VLOOKUP($A10,$B$1:$H$59,MATCH(L$1,$B$1:$H$1,0),0) -> #N/A | M10: =VLOOKUP($A10,$B$1:$H$59,MATCH(M$1,$B$1:$H$1,0),0) -> #N/A | N10: =VLOOKUP($A10,$B$1:$H$59,MATCH(N$1,$B$1:$H$1,0),0) -> #N/A | P10: =B10 -> 43910 | Q10: =VLOOKUP($B10,'Stats 2020'!$D$25:$J$200,MATCH(Graphs!Q$1,'Stats 2020'!$D$18:$J$18,0),0) -> 1 | R10: =VLOOKUP($B10,'Stats 2020'!$D$25:$J$200,MATCH(Graphs!R$1,'Stats 2020'!$D$18:$J$18,0),0) | S10: =VLOOKUP($B10,'Stats 2020'!$D$25:$J$200,MATCH(Graphs!S$1,'Stats 2020'!$D$18:$J$18,0),0) -> 1 | T10: =VLOOKUP($B10,'Stats 2020'!$D$25:$J$200,MATCH(Graphs!T$1,'Stats 2020'!$D$18:$J$18,0),0) -> 1 | U10: =VLOOKUP($B10,'Stats 2020'!$D$25:$J$200,MATCH(Graphs!U$1,'Stats 2020'!$D$18:$J$18,0),0) -> 1 | V10: =VLOOKUP($B10,'Stats 2020'!$D$25:$J$200,MATCH(Graphs!V$1,'Stats 2020'!$D$18:$J$18,0),0) -> 1 | X10: =B10 -> 43910 | Y10: =SUM(Q$2:Q10)/COUNTA($P$2:$P10) -> 0.88888889 | Z10: =SUM(R$2:R10)/COUNTA($P$2:$P10) -> 0 | AA10: =SUM(S$2:S10)/COUNTA($P$2:$P10) -> 0.77777778 | AB10: =SUM(T$2:T10)/COUNTA($P$2:$P10) -> 0.11111111 | AC10: =SUM(U$2:U10)/COUNTA($P$2:$P10) -> 0.66666667 | AD10: =SUM(V$2:V10)/COUNTA($P$2:$P10) -> 0.88888889 | AE10: =AVERAGE(Y10:AD10) -> 0.55555556 | AF10: =VLOOKUP($A10,$X$1:$AE$59,MATCH(AF$1,$X$1:$AE$1,0),0) -> #N/A | AG10: =VLOOKUP($A10,$X$1:$AE$59,MATCH(AG$1,$X$1:$AE$1,0),0) -> #N/A | AH10: =VLOOKUP($A10,$X$1:$AE$59,MATCH(AH$1,$X$1:$AE$1,0),0) -> #N/A | AI10: =VLOOKUP($A10,$X$1:$AE$59,MATCH(AI$1,$X$1:$AE$1,0),0) -> #N/A | AJ10: =VLOOKUP($A10,$X$1:$AE$59,MATCH(AJ$1,$X$1:$AE$1,0),0) -> #N/A | AK10: =VLOOKUP($A10,$X$1:$AE$59,MATCH(AK$1,$X$1:$AE$1,0),0) -> #N/A | AL10: =VLOOKUP($A10,$X$1:$AE$59,MATCH(AL$1,$X$1:$AE$1,0),0) -> #N/A
A11: =IF(AND((TODAY()-B11)<7,(TODAY()-B11>=0)),B11,NA()) -> #N/A | B11: =7+B10 -> 43917 | C11: =IF($B11<=TODAY(),SUMIF('Stats 2020'!$M$24:$M$1048576,"<="&Graphs!$B11,'Stats 2020'!O$24:O$1048576),NA()) -> 63.75 | D11: =IF($B11<=TODAY(),MAX($C11,$E11,$G11,$H11)+11+16.5,NA()) -> 113.25 | E11: =IF($B11<=TODAY(),SUMIF('Stats 2020'!$M$24:$M$1048576,"<="&Graphs!$B11,'Stats 2020'!Q$24:Q$1048576),NA()) -> 72 | F11: =IF($B11<=TODAY(),MAX($C11,$E11,$G11,$H11)+11+16.5,NA()) -> 113.25 | G11: =IF($B11<=TODAY(),SUMIF('Stats 2020'!$M$24:$M$1048576,"<="&Graphs!$B11,'Stats 2020'!S$24:S$1048576),NA()) -> 85.75 | H11: =IF($B11<=TODAY(),SUMIF('Stats 2020'!$M$24:$M$1048576,"<="&Graphs!$B11,'Stats 2020'!T$24:T$1048576),NA()) -> 61 | I11: =VLOOKUP($A11,$B$1:$H$59,MATCH(I$1,$B$1:$H$1,0),0) -> #N/A | J11: =VLOOKUP($A11,$B$1:$H$59,MATCH(J$1,$B$1:$H$1,0),0) -> #N/A | K11: =VLOOKUP($A11,$B$1:$H$59,MATCH(K$1,$B$1:$H$1,0),0) -> #N/A | L11: =VLOOKUP($A11,$B$1:$H$59,MATCH(L$1,$B$1:$H$1,0),0) -> #N/A | M11: =VLOOKUP($A11,$B$1:$H$59,MATCH(M$1,$B$1:$H$1,0),0) -> #N/A | N11: =VLOOKUP($A11,$B$1:$H$59,MATCH(N$1,$B$1:$H$1,0),0) -> #N/A | P11: =B11 -> 43917 | Q11: =VLOOKUP($B11,'Stats 2020'!$D$25:$J$200,MATCH(Graphs!Q$1,'Stats 2020'!$D$18:$J$18,0),0) -> 1 | R11: =VLOOKUP($B11,'Stats 2020'!$D$25:$J$200,MATCH(Graphs!R$1,'Stats 2020'!$D$18:$J$18,0),0) -> 1 | S11: =VLOOKUP($B11,'Stats 2020'!$D$25:$J$200,MATCH(Graphs!S$1,'Stats 2020'!$D$18:$J$18,0),0) -> 1 | T11: =VLOOKUP($B11,'Stats 2020'!$D$25:$J$200,MATCH(Graphs!T$1,'Stats 2020'!$D$18:$J$18,0),0) -> 1 | U11: =VLOOKUP($B11,'Stats 2020'!$D$25:$J$200,MATCH(Graphs!U$1,'Stats 2020'!$D$18:$J$18,0),0) -> 1 | V11: =VLOOKUP($B11,'Stats 2020'!$D$25:$J$200,MATCH(Graphs!V$1,'Stats 2020'!$D$18:$J$18,0),0) -> 1 | X11: =B11 -> 43917 | Y11: =SUM(Q$2:Q11)/COUNTA($P$2:$P11) -> 0.9 | Z11: =SUM(R$2:R11)/COUNTA($P$2:$P11) -> 0.1 | AA11: =SUM(S$2:S11)/COUNTA($P$2:$P11) -> 0.8 | AB11: =SUM(T$2:T11)/COUNTA($P$2:$P11) -> 0.2 | AC11: =SUM(U$2:U11)/COUNTA($P$2:$P11) -> 0.7 | AD11: =SUM(V$2:V11)/COUNTA($P$2:$P11) -> 0.9 | AE11: =AVERAGE(Y11:AD11) -> 0.6 | AF11: =VLOOKUP($A11,$X$1:$AE$59,MATCH(AF$1,$X$1:$AE$1,0),0) -> #N/A | AG11: =VLOOKUP($A11,$X$1:$AE$59,MATCH(AG$1,$X$1:$AE$1,0),0) -> #N/A | AH11: =VLOOKUP($A11,$X$1:$AE$59,MATCH(AH$1,$X$1:$AE$1,0),0) -> #N/A | AI11: =VLOOKUP($A11,$X$1:$AE$59,MATCH(AI$1,$X$1:$AE$1,0),0) -> #N/A | AJ11: =VLOOKUP($A11,$X$1:$AE$59,MATCH(AJ$1,$X$1:$AE$1,0),0) -> #N/A | AK11: =VLOOKUP($A11,$X$1:$AE$59,MATCH(AK$1,$X$1:$AE$1,0),0) -> #N/A | AL11: =VLOOKUP($A11,$X$1:$AE$59,MATCH(AL$1,$X$1:$AE$1,0),0) -> #N/A
A12: =IF(AND((TODAY()-B12)<7,(TODAY()-B12>=0)),B12,NA()) -> #N/A | B12: =B10+14 -> 43924 | C12: =IF($B12<=TODAY(),SUMIF('Stats 2020'!$M$24:$M$1048576,"<="&Graphs!$B12,'Stats 2020'!O$24:O$1048576),NA()) -> 63.75 | D12: =IF($B12<=TODAY(),MAX($C12,$E12,$G12,$H12)+11+16.5,NA()) -> 113.25 | E12: =IF($B12<=TODAY(),SUMIF('Stats 2020'!$M$24:$M$1048576,"<="&Graphs!$B12,'Stats 2020'!Q$24:Q$1048576),NA()) -> 72 | F12: =IF($B12<=TODAY(),MAX($C12,$E12,$G12,$H12)+11+16.5,NA()) -> 113.25 | G12: =IF($B12<=TODAY(),SUMIF('Stats 2020'!$M$24:$M$1048576,"<="&Graphs!$B12,'Stats 2020'!S$24:S$1048576),NA()) -> 85.75 | H12: =IF($B12<=TODAY(),SUMIF('Stats 2020'!$M$24:$M$1048576,"<="&Graphs!$B12,'Stats 2020'!T$24:T$1048576),NA()) -> 61 | I12: =VLOOKUP($A12,$B$1:$H$59,MATCH(I$1,$B$1:$H$1,0),0) -> #N/A | J12: =VLOOKUP($A12,$B$1:$H$59,MATCH(J$1,$B$1:$H$1,0),0) -> #N/A | K12: =VLOOKUP($A12,$B$1:$H$59,MATCH(K$1,$B$1:$H$1,0),0) -> #N/A | L12: =VLOOKUP($A12,$B$1:$H$59,MATCH(L$1,$B$1:$H$1,0),0) -> #N/A | M12: =VLOOKUP($A12,$B$1:$H$59,MATCH(M$1,$B$1:$H$1,0),0) -> #N/A | N12: =VLOOKUP($A12,$B$1:$H$59,MATCH(N$1,$B$1:$H$1,0),0) -> #N/A | P12: =B12 -> 43924 | Q12: =VLOOKUP($B12,'Stats 2020'!$D$25:$J$200,MATCH(Graphs!Q$1,'Stats 2020'!$D$18:$J$18,0),0) -> 1 | R12: =VLOOKUP($B12,'Stats 2020'!$D$25:$J$200,MATCH(Graphs!R$1,'Stats 2020'!$D$18:$J$18,0),0) | S12: =VLOOKUP($B12,'Stats 2020'!$D$25:$J$200,MATCH(Graphs!S$1,'Stats 2020'!$D$18:$J$18,0),0) -> 1 | T12: =VLOOKUP($B12,'Stats 2020'!$D$25:$J$200,MATCH(Graphs!T$1,'Stats 2020'!$D$18:$J$18,0),0) -> 1 | U12: =VLOOKUP($B12,'Stats 2020'!$D$25:$J$200,MATCH(Graphs!U$1,'Stats 2020'!$D$18:$J$18,0),0) -> 1 | V12: =VLOOKUP($B12,'Stats 2020'!$D$25:$J$200,MATCH(Graphs!V$1,'Stats 2020'!$D$18:$J$18,0),0) -> 1 | X12: =B12 -> 43924 | Y12: =SUM(Q$2:Q12)/COUNTA($P$2:$P12) -> 0.90909091 | Z12: =SUM(R$2:R12)/COUNTA($P$2:$P12) -> 0.090909091 | AA12: =SUM(S$2:S12)/COUNTA($P$2:$P12) -> 0.81818182 | AB12: =SUM(T$2:T12)/COUNTA($P$2:$P12) -> 0.27272727 | AC12: =SUM(U$2:U12)/COUNTA($P$2:$P12) -> 0.72727273 | AD12: =SUM(V$2:V12)/COUNTA($P$2:$P12) -> 0.90909091 | AE12: =AVERAGE(Y12:AD12) -> 0.62121212 | AF12: =VLOOKUP($A12,$X$1:$AE$59,MATCH(AF$1,$X$1:$AE$1,0),0) -> #N/A | AG12: =VLOOKUP($A12,$X$1:$AE$59,MATCH(AG$1,$X$1:$AE$1,0),0) -> #N/A | AH12: =VLOOKUP($A12,$X$1:$AE$59,MATCH(AH$1,$X$1:$AE$1,0),0) -> #N/A | AI12: =VLOOKUP($A12,$X$1:$AE$59,MATCH(AI$1,$X$1:$AE$1,0),0) -> #N/A | AJ12: =VLOOKUP($A12,$X$1:$AE$59,MATCH(AJ$1,$X$1:$AE$1,0),0) -> #N/A | AK12: =VLOOKUP($A12,$X$1:$AE$59,MATCH(AK$1,$X$1:$AE$1,0),0) -> #N/A | AL12: =VLOOKUP($A12,$X$1:$AE$59,MATCH(AL$1,$X$1:$AE$1,0),0) -> #N/A
A13: =IF(AND((TODAY()-B13)<7,(TODAY()-B13>=0)),B13,NA()) -> #N/A | B13: =B12+7 -> 43931 | C13: =IF($B13<=TODAY(),SUMIF('Stats 2020'!$M$24:$M$1048576,"<="&Graphs!$B13,'Stats 2020'!O$24:O$1048576),NA()) -> 63.75 | D13: =IF($B13<=TODAY(),MAX($C13,$E13,$G13,$H13)+11+16.5,NA()) -> 113.25 | E13: =IF($B13<=TODAY(),SUMIF('Stats 2020'!$M$24:$M$1048576,"<="&Graphs!$B13,'Stats 2020'!Q$24:Q$1048576),NA()) -> 72 | F13: =IF($B13<=TODAY(),MAX($C13,$E13,$G13,$H13)+11+16.5,NA()) -> 113.25 | G13: =IF($B13<=TODAY(),SUMIF('Stats 2020'!$M$24:$M$1048576,"<="&Graphs!$B13,'Stats 2020'!S$24:S$1048576),NA()) -> 85.75 | H13: =IF($B13<=TODAY(),SUMIF('Stats 2020'!$M$24:$M$1048576,"<="&Graphs!$B13,'Stats 2020'!T$24:T$1048576),NA()) -> 61 | I13: =VLOOKUP($A13,$B$1:$H$59,MATCH(I$1,$B$1:$H$1,0),0) -> #N/A | J13: =VLOOKUP($A13,$B$1:$H$59,MATCH(J$1,$B$1:$H$1,0),0) -> #N/A | K13: =VLOOKUP($A13,$B$1:$H$59,MATCH(K$1,$B$1:$H$1,0),0) -> #N/A | L13: =VLOOKUP($A13,$B$1:$H$59,MATCH(L$1,$B$1:$H$1,0),0) -> #N/A | M13: =VLOOKUP($A13,$B$1:$H$59,MATCH(M$1,$B$1:$H$1,0),0) -> #N/A | N13: =VLOOKUP($A13,$B$1:$H$59,MATCH(N$1,$B$1:$H$1,0),0) -> #N/A | P13: =B13 -> 43931 | X13: =B13 -> 43931 | Y13: =SUM(Q$2:Q12)/COUNTA($P$2:$P12) -> 0.90909091 | Z13: =SUM(R$2:R12)/COUNTA($P$2:$P12) -> 0.090909091 | AA13: =SUM(S$2:S12)/COUNTA($P$2:$P12) -> 0.81818182 | AB13: =SUM(T$2:T12)/COUNTA($P$2:$P12) -> 0.27272727 | AC13: =SUM(U$2:U12)/COUNTA($P$2:$P12) -> 0.72727273 | AD13: =SUM(V$2:V12)/COUNTA($P$2:$P12) -> 0.90909091 | AE13: =AVERAGE(Y13:AD13) -> 0.62121212 | AF13: =VLOOKUP($A13,$X$1:$AE$59,MATCH(AF$1,$X$1:$AE$1,0),0) -> #N/A | AG13: =VLOOKUP($A13,$X$1:$AE$59,MATCH(AG$1,$X$1:$AE$1,0),0) -> #N/A | AH13: =VLOOKUP($A13,$X$1:$AE$59,MATCH(AH$1,$X$1:$AE$1,0),0) -> #N/A | AI13: =VLOOKUP($A13,$X$1:$AE$59,MATCH(AI$1,$X$1:$AE$1,0),0) -> #N/A | AJ13: =VLOOKUP($A13,$X$1:$AE$59,MATCH(AJ$1,$X$1:$AE$1,0),0) -> #N/A | AK13: =VLOOKUP($A13,$X$1:$AE$59,MATCH(AK$1,$X$1:$AE$1,0),0) -> #N/A | AL13: =VLOOKUP($A13,$X$1:$AE$59,MATCH(AL$1,$X$1:$AE$1,0),0) -> #N/A
A14: =IF(AND((TODAY()-B14)<7,(TODAY()-B14>=0)),B14,NA()) -> #N/A | B14: =B13+7 -> 43938 | C14: =IF($B14<=TODAY(),SUMIF('Stats 2020'!$M$24:$M$1048576,"<="&Graphs!$B14,'Stats 2020'!O$24:O$1048576),NA()) -> 74.75 | D14: =IF($B14<=TODAY(),MAX($C14,$E14,$G14,$H14)+11+16.5,NA()) -> 113.25 | E14: =IF($B14<=TODAY(),SUMIF('Stats 2020'!$M$24:$M$1048576,"<="&Graphs!$B14,'Stats 2020'!Q$24:Q$1048576),NA()) -> 72 | F14: =IF($B14<=TODAY(),MAX($C14,$E14,$G14,$H14)+11+16.5,NA()) -> 113.25 | G14: =IF($B14<=TODAY(),SUMIF('Stats 2020'!$M$24:$M$1048576,"<="&Graphs!$B14,'Stats 2020'!S$24:S$1048576),NA()) -> 85.75 | H14: =IF($B14<=TODAY(),SUMIF('Stats 2020'!$M$24:$M$1048576,"<="&Graphs!$B14,'Stats 2020'!T$24:T$1048576),NA()) -> 61 | I14: =VLOOKUP($A14,$B$1:$H$59,MATCH(I$1,$B$1:$H$1,0),0) -> #N/A | J14: =VLOOKUP($A14,$B$1:$H$59,MATCH(J$1,$B$1:$H$1,0),0) -> #N/A | K14: =VLOOKUP($A14,$B$1:$H$59,MATCH(K$1,$B$1:$H$1,0),0) -> #N/A | L14: =VLOOKUP($A14,$B$1:$H$59,MATCH(L$1,$B$1:$H$1,0),0) -> #N/A | M14: =VLOOKUP($A14,$B$1:$H$59,MATCH(M$1,$B$1:$H$1,0),0) -> #N/A | N14: =VLOOKUP($A14,$B$1:$H$59,MATCH(N$1,$B$1:$H$1,0),0) -> #N/A | P14: =B14 -> 43938 | Q14: =VLOOKUP($B14,'Stats 2020'!$D$25:$J$200,MATCH(Graphs!Q$1,'Stats 2020'!$D$18:$J$18,0),0) -> 1 | R14: =VLOOKUP($B14,'Stats 2020'!$D$25:$J$200,MATCH(Graphs!R$1,'Stats 2020'!$D$18:$J$18,0),0) | S14: =VLOOKUP($B14,'Stats 2020'!$D$25:$J$200,MATCH(Graphs!S$1,'Stats 2020'!$D$18:$J$18,0),0) -> 1 | T14: =VLOOKUP($B14,'Stats 2020'!$D$25:$J$200,MATCH(Graphs!T$1,'Stats 2020'!$D$18:$J$18,0),0) | U14: =VLOOKUP($B14,'Stats 2020'!$D$25:$J$200,MATCH(Graphs!U$1,'Stats 2020'!$D$18:$J$18,0),0) -> 1 | V14: =VLOOKUP($B14,'Stats 2020'!$D$25:$J$200,MATCH(Graphs!V$1,'Stats 2020'!$D$18:$J$18,0),0) -> 1 | X14: =B14 -> 43938 | Y14: =SUM(Q$2:Q14)/COUNTA($P$2:$P14) -> 0.84615385 | Z14: =SUM(R$2:R14)/COUNTA($P$2:$P14) -> 0.076923077 | AA14: =SUM(S$2:S14)/COUNTA($P$2:$P14) -> 0.76923077 | AB14: =SUM(T$2:T14)/COUNTA($P$2:$P14) -> 0.23076923 | AC14: =SUM(U$2:U14)/COUNTA($P$2:$P14) -> 0.69230769 | AD14: =SUM(V$2:V14)/COUNTA($P$2:$P14) -> 0.84615385 | AE14: =AVERAGE(Y14:AD14) -> 0.57692308 | AF14: =VLOOKUP($A14,$X$1:$AE$59,MATCH(AF$1,$X$1:$AE$1,0),0) -> #N/A | AG14: =VLOOKUP($A14,$X$1:$AE$59,MATCH(AG$1,$X$1:$AE$1,0),0) -> #N/A | AH14: =VLOOKUP($A14,$X$1:$AE$59,MATCH(AH$1,$X$1:$AE$1,0),0) -> #N/A | AI14: =VLOOKUP($A14,$X$1:$AE$59,MATCH(AI$1,$X$1:$AE$1,0),0) -> #N/A | AJ14: =VLOOKUP($A14,$X$1:$AE$59,MATCH(AJ$1,$X$1:$AE$1,0),0) -> #N/A | AK14: =VLOOKUP($A14,$X$1:$AE$59,MATCH(AK$1,$X$1:$AE$1,0),0) -> #N/A | AL14: =VLOOKUP($A14,$X$1:$AE$59,MATCH(AL$1,$X$1:$AE$1,0),0) -> #N/A
A15: =IF(AND((TODAY()-B15)<7,(TODAY()-B15>=0)),B15,NA()) -> #N/A | B15: =B14+7 -> 43945 | C15: =IF($B15<=TODAY(),SUMIF('Stats 2020'!$M$24:$M$1048576,"<="&Graphs!$B15,'Stats 2020'!O$24:O$1048576),NA()) -> 74.75 | D15: =IF($B15<=TODAY(),MAX($C15,$E15,$G15,$H15)+11+16.5,NA()) -> 113.25 | E15: =IF($B15<=TODAY(),SUMIF('Stats 2020'!$M$24:$M$1048576,"<="&Graphs!$B15,'Stats 2020'!Q$24:Q$1048576),NA()) -> 72 | F15: =IF($B15<=TODAY(),MAX($C15,$E15,$G15,$H15)+11+16.5,NA()) -> 113.25 | G15: =IF($B15<=TODAY(),SUMIF('Stats 2020'!$M$24:$M$1048576,"<="&Graphs!$B15,'Stats 2020'!S$24:S$1048576),NA()) -> 85.75 | H15: =IF($B15<=TODAY(),SUMIF('Stats 2020'!$M$24:$M$1048576,"<="&Graphs!$B15,'Stats 2020'!T$24:T$1048576),NA()) -> 61 | I15: =VLOOKUP($A15,$B$1:$H$59,MATCH(I$1,$B$1:$H$1,0),0) -> #N/A | J15: =VLOOKUP($A15,$B$1:$H$59,MATCH(J$1,$B$1:$H$1,0),0) -> #N/A | K15: =VLOOKUP($A15,$B$1:$H$59,MATCH(K$1,$B$1:$H$1,0),0) -> #N/A | L15: =VLOOKUP($A15,$B$1:$H$59,MATCH(L$1,$B$1:$H$1,0),0) -> #N/A | M15: =VLOOKUP($A15,$B$1:$H$59,MATCH(M$1,$B$1:$H$1,0),0) -> #N/A | N15: =VLOOKUP($A15,$B$1:$H$59,MATCH(N$1,$B$1:$H$1,0),0) -> #N/A | P15: =B15 -> 43945 | Q15: =VLOOKUP($B15,'Stats 2020'!$D$25:$J$200,MATCH(Graphs!Q$1,'Stats 2020'!$D$18:$J$18,0),0) -> 1 | R15: =VLOOKUP($B15,'Stats 2020'!$D$25:$J$200,MATCH(Graphs!R$1,'Stats 2020'!$D$18:$J$18,0),0) | S15: =VLOOKUP($B15,'Stats 2020'!$D$25:$J$200,MATCH(Graphs!S$1,'Stats 2020'!$D$18:$J$18,0),0) -> 1 | T15: =VLOOKUP($B15,'Stats 2020'!$D$25:$J$200,MATCH(Graphs!T$1,'Stats 2020'!$D$18:$J$18,0),0) -> 1 | U15: =VLOOKUP($B15,'Stats 2020'!$D$25:$J$200,MATCH(Graphs!U$1,'Stats 2020'!$D$18:$J$18,0),0) -> 1 | V15: =VLOOKUP($B15,'Stats 2020'!$D$25:$J$200,MATCH(Graphs!V$1,'Stats 2020'!$D$18:$J$18,0),0) -> 1 | X15: =B15 -> 43945 | Y15: =SUM(Q$2:Q15)/COUNTA($P$2:$P15) -> 0.85714286 | Z15: =SUM(R$2:R15)/COUNTA($P$2:$P15) -> 0.071428571 | AA15: =SUM(S$2:S15)/COUNTA($P$2:$P15) -> 0.78571429 | AB15: =SUM(T$2:T15)/COUNTA($P$2:$P15) -> 0.28571429 | AC15: =SUM(U$2:U15)/COUNTA($P$2:$P15) -> 0.71428571 | AD15: =SUM(V$2:V15)/COUNTA($P$2:$P15) -> 0.85714286 | AE15: =AVERAGE(Y15:AD15) -> 0.5952381 | AF15: =VLOOKUP($A15,$X$1:$AE$59,MATCH(AF$1,$X$1:$AE$1,0),0) -> #N/A | AG15: =VLOOKUP($A15,$X$1:$AE$59,MATCH(AG$1,$X$1:$AE$1,0),0) -> #N/A | AH15: =VLOOKUP($A15,$X$1:$AE$59,MATCH(AH$1,$X$1:$AE$1,0),0) -> #N/A | AI15: =VLOOKUP($A15,$X$1:$AE$59,MATCH(AI$1,$X$1:$AE$1,0),0) -> #N/A | AJ15: =VLOOKUP($A15,$X$1:$AE$59,MATCH(AJ$1,$X$1:$AE$1,0),0) -> #N/A | AK15: =VLOOKUP($A15,$X$1:$AE$59,MATCH(AK$1,$X$1:$AE$1,0),0) -> #N/A | AL15: =VLOOKUP($A15,$X$1:$AE$59,MATCH(AL$1,$X$1:$AE$1,0),0) -> #N/A
A16: =IF(AND((TODAY()-B16)<7,(TODAY()-B16>=0)),B16,NA()) -> #N/A | B16: =B15+7 -> 43952 | C16: =IF($B16<=TODAY(),SUMIF('Stats 2020'!$M$24:$M$1048576,"<="&Graphs!$B16,'Stats 2020'!O$24:O$1048576),NA()) -> 74.75 | D16: =IF($B16<=TODAY(),MAX($C16,$E16,$G16,$H16)+11+16.5,NA()) -> 113.25 | E16: =IF($B16<=TODAY(),SUMIF('Stats 2020'!$M$24:$M$1048576,"<="&Graphs!$B16,'Stats 2020'!Q$24:Q$1048576),NA()) -> 72 | F16: =IF($B16<=TODAY(),MAX($C16,$E16,$G16,$H16)+11+16.5,NA()) -> 113.25 | G16: =IF($B16<=TODAY(),SUMIF('Stats 2020'!$M$24:$M$1048576,"<="&Graphs!$B16,'Stats 2020'!S$24:S$1048576),NA()) -> 85.75 | H16: =IF($B16<=TODAY(),SUMIF('Stats 2020'!$M$24:$M$1048576,"<="&Graphs!$B16,'Stats 2020'!T$24:T$1048576),NA()) -> 61 | I16: =VLOOKUP($A16,$B$1:$H$59,MATCH(I$1,$B$1:$H$1,0),0) -> #N/A | J16: =VLOOKUP($A16,$B$1:$H$59,MATCH(J$1,$B$1:$H$1,0),0) -> #N/A | K16: =VLOOKUP($A16,$B$1:$H$59,MATCH(K$1,$B$1:$H$1,0),0) -> #N/A | L16: =VLOOKUP($A16,$B$1:$H$59,MATCH(L$1,$B$1:$H$1,0),0) -> #N/A | M16: =VLOOKUP($A16,$B$1:$H$59,MATCH(M$1,$B$1:$H$1,0),0) -> #N/A | N16: =VLOOKUP($A16,$B$1:$H$59,MATCH(N$1,$B$1:$H$1,0),0) -> #N/A | P16: =B16 -> 43952 | Q16: =VLOOKUP($B16,'Stats 2020'!$D$25:$J$200,MATCH(Graphs!Q$1,'Stats 2020'!$D$18:$J$18,0),0) -> 1 | R16: =VLOOKUP($B16,'Stats 2020'!$D$25:$J$200,MATCH(Graphs!R$1,'Stats 2020'!$D$18:$J$18,0),0) | S16: =VLOOKUP($B16,'Stats 2020'!$D$25:$J$200,MATCH(Graphs!S$1,'Stats 2020'!$D$18:$J$18,0),0) -> 1 | T16: =VLOOKUP($B16,'Stats 2020'!$D$25:$J$200,MATCH(Graphs!T$1,'Stats 2020'!$D$18:$J$18,0),0) -> 1 | U16: =VLOOKUP($B16,'Stats 2020'!$D$25:$J$200,MATCH(Graphs!U$1,'Stats 2020'!$D$18:$J$18,0),0) -> 1 | V16: =VLOOKUP($B16,'Stats 2020'!$D$25:$J$200,MATCH(Graphs!V$1,'Stats 2020'!$D$18:$J$18,0),0) -> 1 | X16: =B16 -> 43952 | Y16: =SUM(Q$2:Q16)/COUNTA($P$2:$P16) -> 0.86666667 | Z16: =SUM(R$2:R16)/COUNTA($P$2:$P16) -> 0.066666667 | AA16: =SUM(S$2:S16)/COUNTA($P$2:$P16) -> 0.8 | AB16: =SUM(T$2:T16)/COUNTA($P$2:$P16) -> 0.33333333 | AC16: =SUM(U$2:U16)/COUNTA($P$2:$P16) -> 0.73333333 | AD16: =SUM(V$2:V16)/COUNTA($P$2:$P16) -> 0.86666667 | AE16: =AVERAGE(Y16:AD16) -> 0.61111111 | AF16: =VLOOKUP($A16,$X$1:$AE$59,MATCH(AF$1,$X$1:$AE$1,0),0) -> #N/A | AG16: =VLOOKUP($A16,$X$1:$AE$59,MATCH(AG$1,$X$1:$AE$1,0),0) -> #N/A | AH16: =VLOOKUP($A16,$X$1:$AE$59,MATCH(AH$1,$X$1:$AE$1,0),0) -> #N/A | AI16: =VLOOKUP($A16,$X$1:$AE$59,MATCH(AI$1,$X$1:$AE$1,0),0) -> #N/A | AJ16: =VLOOKUP($A16,$X$1:$AE$59,MATCH(AJ$1,$X$1:$AE$1,0),0) -> #N/A | AK16: =VLOOKUP($A16,$X$1:$AE$59,MATCH(AK$1,$X$1:$AE$1,0),0) -> #N/A | AL16: =VLOOKUP($A16,$X$1:$AE$59,MATCH(AL$1,$X$1:$AE$1,0),0) -> #N/A
A17: =IF(AND((TODAY()-B17)<7,(TODAY()-B17>=0)),B17,NA()) -> #N/A | B17: =B16+7 -> 43959 | C17: =IF($B17<=TODAY(),SUMIF('Stats 2020'!$M$24:$M$1048576,"<="&Graphs!$B17,'Stats 2020'!O$24:O$1048576),NA()) -> 74.75 | D17: =IF($B17<=TODAY(),MAX($C17,$E17,$G17,$H17)+11+16.5,NA()) -> 113.25 | E17: =IF($B17<=TODAY(),SUMIF('Stats 2020'!$M$24:$M$1048576,"<="&Graphs!$B17,'Stats 2020'!Q$24:Q$1048576),NA()) -> 72 | F17: =IF($B17<=TODAY(),MAX($C17,$E17,$G17,$H17)+11+16.5,NA()) -> 113.25 | G17: =IF($B17<=TODAY(),SUMIF('Stats 2020'!$M$24:$M$1048576,"<="&Graphs!$B17,'Stats 2020'!S$24:S$1048576),NA()) -> 85.75 | H17: =IF($B17<=TODAY(),SUMIF('Stats 2020'!$M$24:$M$1048576,"<="&Graphs!$B17,'Stats 2020'!T$24:T$1048576),NA()) -> 61 | I17: =VLOOKUP($A17,$B$1:$H$59,MATCH(I$1,$B$1:$H$1,0),0) -> #N/A | J17: =VLOOKUP($A17,$B$1:$H$59,MATCH(J$1,$B$1:$H$1,0),0) -> #N/A | K17: =VLOOKUP($A17,$B$1:$H$59,MATCH(K$1,$B$1:$H$1,0),0) -> #N/A | L17: =VLOOKUP($A17,$B$1:$H$59,MATCH(L$1,$B$1:$H$1,0),0) -> #N/A | M17: =VLOOKUP($A17,$B$1:$H$59,MATCH(M$1,$B$1:$H$1,0),0) -> #N/A | N17: =VLOOKUP($A17,$B$1:$H$59,MATCH(N$1,$B$1:$H$1,0),0) -> #N/A | P17: =B17 -> 43959 | Q17: =VLOOKUP($B17,'Stats 2020'!$D$25:$J$200,MATCH(Graphs!Q$1,'Stats 2020'!$D$18:$J$18,0),0) -> 1 | R17: =VLOOKUP($B17,'Stats 2020'!$D$25:$J$200,MATCH(Graphs!R$1,'Stats 2020'!$D$18:$J$18,0),0) | S17: =VLOOKUP($B17,'Stats 2020'!$D$25:$J$200,MATCH(Graphs!S$1,'Stats 2020'!$D$18:$J$18,0),0) -> 1 | T17: =VLOOKUP($B17,'Stats 2020'!$D$25:$J$200,MATCH(Graphs!T$1,'Stats 2020'!$D$18:$J$18,0),0) | U17: =VLOOKUP($B17,'Stats 2020'!$D$25:$J$200,MATCH(Graphs!U$1,'Stats 2020'!$D$18:$J$18,0),0) -> 1 | V17: =VLOOKUP($B17,'Stats 2020'!$D$25:$J$200,MATCH(Graphs!V$1,'Stats 2020'!$D$18:$J$18,0),0) -> 1 | X17: =B17 -> 43959 | Y17: =SUM(Q$2:Q17)/COUNTA($P$2:$P17) -> 0.875 | Z17: =SUM(R$2:R17)/COUNTA($P$2:$P17) -> 0.0625 | AA17: =SUM(S$2:S17)/COUNTA($P$2:$P17) -> 0.8125 | AB17: =SUM(T$2:T17)/COUNTA($P$2:$P17) -> 0.3125 | AC17: =SUM(U$2:U17)/COUNTA($P$2:$P17) -> 0.75 | AD17: =SUM(V$2:V17)/COUNTA($P$2:$P17) -> 0.875 | AE17: =AVERAGE(Y17:AD17) -> 0.61458333 | AF17: =VLOOKUP($A17,$X$1:$AE$59,MATCH(AF$1,$X$1:$AE$1,0),0) -> #N/A | AG17: =VLOOKUP($A17,$X$1:$AE$59,MATCH(AG$1,$X$1:$AE$1,0),0) -> #N/A | AH17: =VLOOKUP($A17,$X$1:$AE$59,MATCH(AH$1,$X$1:$AE$1,0),0) -> #N/A | AI17: =VLOOKUP($A17,$X$1:$AE$59,MATCH(AI$1,$X$1:$AE$1,0),0) -> #N/A | AJ17: =VLOOKUP($A17,$X$1:$AE$59,MATCH(AJ$1,$X$1:$AE$1,0),0) -> #N/A | AK17: =VLOOKUP($A17,$X$1:$AE$59,MATCH(AK$1,$X$1:$AE$1,0),0) -> #N/A | AL17: =VLOOKUP($A17,$X$1:$AE$59,MATCH(AL$1,$X$1:$AE$1,0),0) -> #N/A
A18: =IF(AND((TODAY()-B18)<7,(TODAY()-B18>=0)),B18,NA()) -> #N/A | B18: =B17+7 -> 43966 | C18: =IF($B18<=TODAY(),SUMIF('Stats 2020'!$M$24:$M$1048576,"<="&Graphs!$B18,'Stats 2020'!O$24:O$1048576),NA()) -> 74.75 | D18: =IF($B18<=TODAY(),MAX($C18,$E18,$G18,$H18)+11+16.5,NA()) -> 113.25 | E18: =IF($B18<=TODAY(),SUMIF('Stats 2020'!$M$24:$M$1048576,"<="&Graphs!$B18,'Stats 2020'!Q$24:Q$1048576),NA()) -> 72 | F18: =IF($B18<=TODAY(),MAX($C18,$E18,$G18,$H18)+11+16.5,NA()) -> 113.25 | G18: =IF($B18<=TODAY(),SUMIF('Stats 2020'!$M$24:$M$1048576,"<="&Graphs!$B18,'Stats 2020'!S$24:S$1048576),NA()) -> 85.75 | H18: =IF($B18<=TODAY(),SUMIF('Stats 2020'!$M$24:$M$1048576,"<="&Graphs!$B18,'Stats 2020'!T$24:T$1048576),NA()) -> 61 | I18: =VLOOKUP($A18,$B$1:$H$59,MATCH(I$1,$B$1:$H$1,0),0) -> #N/A | J18: =VLOOKUP($A18,$B$1:$H$59,MATCH(J$1,$B$1:$H$1,0),0) -> #N/A | K18: =VLOOKUP($A18,$B$1:$H$59,MATCH(K$1,$B$1:$H$1,0),0) -> #N/A | L18: =VLOOKUP($A18,$B$1:$H$59,MATCH(L$1,$B$1:$H$1,0),0) -> #N/A | M18: =VLOOKUP($A18,$B$1:$H$59,MATCH(M$1,$B$1:$H$1,0),0) -> #N/A | N18: =VLOOKUP($A18,$B$1:$H$59,MATCH(N$1,$B$1:$H$1,0),0) -> #N/A | P18: =B18 -> 43966 | Q18: =VLOOKUP($B18,'Stats 2020'!$D$25:$J$200,MATCH(Graphs!Q$1,'Stats 2020'!$D$18:$J$18,0),0) -> 1 | R18: =VLOOKUP($B18,'Stats 2020'!$D$25:$J$200,MATCH(Graphs!R$1,'Stats 2020'!$D$18:$J$18,0),0) | S18: =VLOOKUP($B18,'Stats 2020'!$D$25:$J$200,MATCH(Graphs!S$1,'Stats 2020'!$D$18:$J$18,0),0) -> 1 | T18: =VLOOKUP($B18,'Stats 2020'!$D$25:$J$200,MATCH(Graphs!T$1,'Stats 2020'!$D$18:$J$18,0),0) | U18: =VLOOKUP($B18,'Stats 2020'!$D$25:$J$200,MATCH(Graphs!U$1,'Stats 2020'!$D$18:$J$18,0),0) -> 1 | V18: =VLOOKUP($B18,'Stats 2020'!$D$25:$J$200,MATCH(Graphs!V$1,'Stats 2020'!$D$18:$J$18,0),0) -> 1 | X18: =B18 -> 43966 | Y18: =SUM(Q$2:Q18)/COUNTA($P$2:$P18) -> 0.88235294 | Z18: =SUM(R$2:R18)/COUNTA($P$2:$P18) -> 0.058823529 | AA18: =SUM(S$2:S18)/COUNTA($P$2:$P18) -> 0.82352941 | AB18: =SUM(T$2:T18)/COUNTA($P$2:$P18) -> 0.29411765 | AC18: =SUM(U$2:U18)/COUNTA($P$2:$P18) -> 0.76470588 | AD18: =SUM(V$2:V18)/COUNTA($P$2:$P18) -> 0.88235294 | AE18: =AVERAGE(Y18:AD18) -> 0.61764706 | AF18: =VLOOKUP($A18,$X$1:$AE$59,MATCH(AF$1,$X$1:$AE$1,0),0) -> #N/A | AG18: =VLOOKUP($A18,$X$1:$AE$59,MATCH(AG$1,$X$1:$AE$1,0),0) -> #N/A | AH18: =VLOOKUP($A18,$X$1:$AE$59,MATCH(AH$1,$X$1:$AE$1,0),0) -> #N/A | AI18: =VLOOKUP($A18,$X$1:$AE$59,MATCH(AI$1,$X$1:$AE$1,0),0) -> #N/A | AJ18: =VLOOKUP($A18,$X$1:$AE$59,MATCH(AJ$1,$X$1:$AE$1,0),0) -> #N/A | AK18: =VLOOKUP($A18,$X$1:$AE$59,MATCH(AK$1,$X$1:$AE$1,0),0) -> #N/A | AL18: =VLOOKUP($A18,$X$1:$AE$59,MATCH(AL$1,$X$1:$AE$1,0),0) -> #N/A
A19: =IF(AND((TODAY()-B19)<7,(TODAY()-B19>=0)),B19,NA()) -> #N/A | B19: =B18+7 -> 43973 | C19: =IF($B19<=TODAY(),SUMIF('Stats 2020'!$M$24:$M$1048576,"<="&Graphs!$B19,'Stats 2020'!O$24:O$1048576),NA()) -> 74.75 | D19: =IF($B19<=TODAY(),MAX($C19,$E19,$G19,$H19)+11+16.5,NA()) -> 113.25 | E19: =IF($B19<=TODAY(),SUMIF('Stats 2020'!$M$24:$M$1048576,"<="&Graphs!$B19,'Stats 2020'!Q$24:Q$1048576),NA()) -> 72 | F19: =IF($B19<=TODAY(),MAX($C19,$E19,$G19,$H19)+11+16.5,NA()) -> 113.25 | G19: =IF($B19<=TODAY(),SUMIF('Stats 2020'!$M$24:$M$1048576,"<="&Graphs!$B19,'Stats 2020'!S$24:S$1048576),NA()) -> 85.75 | H19: =IF($B19<=TODAY(),SUMIF('Stats 2020'!$M$24:$M$1048576,"<="&Graphs!$B19,'Stats 2020'!T$24:T$1048576),NA()) -> 72 | I19: =VLOOKUP($A19,$B$1:$H$59,MATCH(I$1,$B$1:$H$1,0),0) -> #N/A | J19: =VLOOKUP($A19,$B$1:$H$59,MATCH(J$1,$B$1:$H$1,0),0) -> #N/A | K19: =VLOOKUP($A19,$B$1:$H$59,MATCH(K$1,$B$1:$H$1,0),0) -> #N/A | L19: =VLOOKUP($A19,$B$1:$H$59,MATCH(L$1,$B$1:$H$1,0),0) -> #N/A | M19: =VLOOKUP($A19,$B$1:$H$59,MATCH(M$1,$B$1:$H$1,0),0) -> #N/A | N19: =VLOOKUP($A19,$B$1:$H$59,MATCH(N$1,$B$1:$H$1,0),0) -> #N/A | P19: =B19 -> 43973 | Q19: =VLOOKUP($B19,'Stats 2020'!$D$25:$J$200,MATCH(Graphs!Q$1,'Stats 2020'!$D$18:$J$18,0),0) -> 1 | R19: =VLOOKUP($B19,'Stats 2020'!$D$25:$J$200,MATCH(Graphs!R$1,'Stats 2020'!$D$18:$J$18,0),0) | S19: =VLOOKUP($B19,'Stats 2020'!$D$25:$J$200,MATCH(Graphs!S$1,'Stats 2020'!$D$18:$J$18,0),0) -> 1 | T19: =VLOOKUP($B19,'Stats 2020'!$D$25:$J$200,MATCH(Graphs!T$1,'Stats 2020'!$D$18:$J$18,0),0) | U19: =VLOOKUP($B19,'Stats 2020'!$D$25:$J$200,MATCH(Graphs!U$1,'Stats 2020'!$D$18:$J$18,0),0) -> 1 | V19: =VLOOKUP($B19,'Stats 2020'!$D$25:$J$200,MATCH(Graphs!V$1,'Stats 2020'!$D$18:$J$18,0),0) -> 0 | X19: =B19 -> 43973 | Y19: =SUM(Q$2:Q19)/COUNTA($P$2:$P19) -> 0.88888889 | Z19: =SUM(R$2:R19)/COUNTA($P$2:$P19) -> 0.055555556 | AA19: =SUM(S$2:S19)/COUNTA($P$2:$P19) -> 0.83333333 | AB19: =SUM(T$2:T19)/COUNTA($P$2:$P19) -> 0.27777778 | AC19: =SUM(U$2:U19)/COUNTA($P$2:$P19) -> 0.77777778 | AD19: =SUM(V$2:V19)/COUNTA($P$2:$P19) -> 0.83333333 | AE19: =AVERAGE(Y19:AD19) -> 0.61111111 | AF19: =VLOOKUP($A19,$X$1:$AE$59,MATCH(AF$1,$X$1:$AE$1,0),0) -> #N/A | AG19: =VLOOKUP($A19,$X$1:$AE$59,MATCH(AG$1,$X$1:$AE$1,0),0) -> #N/A | AH19: =VLOOKUP($A19,$X$1:$AE$59,MATCH(AH$1,$X$1:$AE$1,0),0) -> #N/A | AI19: =VLOOKUP($A19,$X$1:$AE$59,MATCH(AI$1,$X$1:$AE$1,0),0) -> #N/A | AJ19: =VLOOKUP($A19,$X$1:$AE$59,MATCH(AJ$1,$X$1:$AE$1,0),0) -> #N/A | AK19: =VLOOKUP($A19,$X$1:$AE$59,MATCH(AK$1,$X$1:$AE$1,0),0) -> #N/A | AL19: =VLOOKUP($A19,$X$1:$AE$59,MATCH(AL$1,$X$1:$AE$1,0),0) -> #N/A
A20: =IF(AND((TODAY()-B20)<7,(TODAY()-B20>=0)),B20,NA()) -> #N/A | B20: =B19+7 -> 43980 | C20: =IF($B20<=TODAY(),SUMIF('Stats 2020'!$M$24:$M$1048576,"<="&Graphs!$B20,'Stats 2020'!O$24:O$1048576),NA()) -> 77.5 | D20: =IF($B20<=TODAY(),MAX($C20,$E20,$G20,$H20)+11+16.5,NA()) -> 113.25 | E20: =IF($B20<=TODAY(),SUMIF('Stats 2020'!$M$24:$M$1048576,"<="&Graphs!$B20,'Stats 2020'!Q$24:Q$1048576),NA()) -> 72 | F20: =IF($B20<=TODAY(),MAX($C20,$E20,$G20,$H20)+11+16.5,NA()) -> 113.25 | G20: =IF($B20<=TODAY(),SUMIF('Stats 2020'!$M$24:$M$1048576,"<="&Graphs!$B20,'Stats 2020'!S$24:S$1048576),NA()) -> 85.75 | H20: =IF($B20<=TODAY(),SUMIF('Stats 2020'!$M$24:$M$1048576,"<="&Graphs!$B20,'Stats 2020'!T$24:T$1048576),NA()) -> 72 | I20: =VLOOKUP($A20,$B$1:$H$59,MATCH(I$1,$B$1:$H$1,0),0) -> #N/A | J20: =VLOOKUP($A20,$B$1:$H$59,MATCH(J$1,$B$1:$H$1,0),0) -> #N/A | K20: =VLOOKUP($A20,$B$1:$H$59,MATCH(K$1,$B$1:$H$1,0),0) -> #N/A | L20: =VLOOKUP($A20,$B$1:$H$59,MATCH(L$1,$B$1:$H$1,0),0) -> #N/A | M20: =VLOOKUP($A20,$B$1:$H$59,MATCH(M$1,$B$1:$H$1,0),0) -> #N/A | N20: =VLOOKUP($A20,$B$1:$H$59,MATCH(N$1,$B$1:$H$1,0),0) -> #N/A | P20: =B20 -> 43980 | Q20: =VLOOKUP($B20,'Stats 2020'!$D$25:$J$200,MATCH(Graphs!Q$1,'Stats 2020'!$D$18:$J$18,0),0) -> 1 | R20: =VLOOKUP($B20,'Stats 2020'!$D$25:$J$200,MATCH(Graphs!R$1,'Stats 2020'!$D$18:$J$18,0),0) | S20: =VLOOKUP($B20,'Stats 2020'!$D$25:$J$200,MATCH(Graphs!S$1,'Stats 2020'!$D$18:$J$18,0),0) -> 1 | T20: =VLOOKUP($B20,'Stats 2020'!$D$25:$J$200,MATCH(Graphs!T$1,'Stats 2020'!$D$18:$J$18,0),0) | U20: =VLOOKUP($B20,'Stats 2020'!$D$25:$J$200,MATCH(Graphs!U$1,'Stats 2020'!$D$18:$J$18,0),0) -> 1 | V20: =VLOOKUP($B20,'Stats 2020'!$D$25:$J$200,MATCH(Graphs!V$1,'Stats 2020'!$D$18:$J$18,0),0) -> 1 | X20: =B20 -> 43980 | Y20: =SUM(Q$2:Q20)/COUNTA($P$2:$P20) -> 0.89473684 | Z20: =SUM(R$2:R20)/COUNTA($P$2:$P20) -> 0.052631579 | AA20: =SUM(S$2:S20)/COUNTA($P$2:$P20) -> 0.84210526 | AB20: =SUM(T$2:T20)/COUNTA($P$2:$P20) -> 0.26315789 | AC20: =SUM(U$2:U20)/COUNTA($P$2:$P20) -> 0.78947368 | AD20: =SUM(V$2:V20)/COUNTA($P$2:$P20) -> 0.84210526 | AE20: =AVERAGE(Y20:AD20) -> 0.61403509 | AF20: =VLOOKUP($A20,$X$1:$AE$59,MATCH(AF$1,$X$1:$AE$1,0),0) -> #N/A | AG20: =VLOOKUP($A20,$X$1:$AE$59,MATCH(AG$1,$X$1:$AE$1,0),0) -> #N/A | AH20: =VLOOKUP($A20,$X$1:$AE$59,MATCH(AH$1,$X$1:$AE$1,0),0) -> #N/A | AI20: =VLOOKUP($A20,$X$1:$AE$59,MATCH(AI$1,$X$1:$AE$1,0),0) -> #N/A | AJ20: =VLOOKUP($A20,$X$1:$AE$59,MATCH(AJ$1,$X$1:$AE$1,0),0) -> #N/A | AK20: =VLOOKUP($A20,$X$1:$AE$59,MATCH(AK$1,$X$1:$AE$1,0),0) -> #N/A | AL20: =VLOOKUP($A20,$X$1:$AE$59,MATCH(AL$1,$X$1:$AE$1,0),0) -> #N/A
A21: =IF(AND((TODAY()-B21)<7,(TODAY()-B21>=0)),B21,NA()) -> #N/A | B21: =B20+7 -> 43987 | C21: =IF($B21<=TODAY(),SUMIF('Stats 2020'!$M$24:$M$1048576,"<="&Graphs!$B21,'Stats 2020'!O$24:O$1048576),NA()) -> 77.5 | D21: =IF($B21<=TODAY(),MAX($C21,$E21,$G21,$H21)+11+16.5,NA()) -> 113.25 | E21: =IF($B21<=TODAY(),SUMIF('Stats 2020'!$M$24:$M$1048576,"<="&Graphs!$B21,'Stats 2020'!Q$24:Q$1048576),NA()) -> 72 | F21: =IF($B21<=TODAY(),MAX($C21,$E21,$G21,$H21)+11+16.5,NA()) -> 113.25 | G21: =IF($B21<=TODAY(),SUMIF('Stats 2020'!$M$24:$M$1048576,"<="&Graphs!$B21,'Stats 2020'!S$24:S$1048576),NA()) -> 85.75 | H21: =IF($B21<=TODAY(),SUMIF('Stats 2020'!$M$24:$M$1048576,"<="&Graphs!$B21,'Stats 2020'!T$24:T$1048576),NA()) -> 72 | I21: =VLOOKUP($A21,$B$1:$H$59,MATCH(I$1,$B$1:$H$1,0),0) -> #N/A | J21: =VLOOKUP($A21,$B$1:$H$59,MATCH(J$1,$B$1:$H$1,0),0) -> #N/A | K21: =VLOOKUP($A21,$B$1:$H$59,MATCH(K$1,$B$1:$H$1,0),0) -> #N/A | L21: =VLOOKUP($A21,$B$1:$H$59,MATCH(L$1,$B$1:$H$1,0),0) -> #N/A | M21: =VLOOKUP($A21,$B$1:$H$59,MATCH(M$1,$B$1:$H$1,0),0) -> #N/A | N21: =VLOOKUP($A21,$B$1:$H$59,MATCH(N$1,$B$1:$H$1,0),0) -> #N/A | P21: =B21 -> 43987 | Q21: =VLOOKUP($B21,'Stats 2020'!$D$25:$J$200,MATCH(Graphs!Q$1,'Stats 2020'!$D$18:$J$18,0),0) -> 1 | R21: =VLOOKUP($B21,'Stats 2020'!$D$25:$J$200,MATCH(Graphs!R$1,'Stats 2020'!$D$18:$J$18,0),0) | S21: =VLOOKUP($B21,'Stats 2020'!$D$25:$J$200,MATCH(Graphs!S$1,'Stats 2020'!$D$18:$J$18,0),0) -> 1 | T21: =VLOOKUP($B21,'Stats 2020'!$D$25:$J$200,MATCH(Graphs!T$1,'Stats 2020'!$D$18:$J$18,0),0) | U21: =VLOOKUP($B21,'Stats 2020'!$D$25:$J$200,MATCH(Graphs!U$1,'Stats 2020'!$D$18:$J$18,0),0) -> 1 | V21: =VLOOKUP($B21,'Stats 2020'!$D$25:$J$200,MATCH(Graphs!V$1,'Stats 2020'!$D$18:$J$18,0),0) -> 1 | X21: =B21 -> 43987 | Y21: =SUM(Q$2:Q21)/COUNTA($P$2:$P21) -> 0.9 | Z21: =SUM(R$2:R21)/COUNTA($P$2:$P21) -> 0.05 | AA21: =SUM(S$2:S21)/COUNTA($P$2:$P21) -> 0.85 | AB21: =SUM(T$2:T21)/COUNTA($P$2:$P21) -> 0.25 | AC21: =SUM(U$2:U21)/COUNTA($P$2:$P21) -> 0.8 | AD21: =SUM(V$2:V21)/COUNTA($P$2:$P21) -> 0.85 | AE21: =AVERAGE(Y21:AD21) -> 0.61666667 | AF21: =VLOOKUP($A21,$X$1:$AE$59,MATCH(AF$1,$X$1:$AE$1,0),0) -> #N/A | AG21: =VLOOKUP($A21,$X$1:$AE$59,MATCH(AG$1,$X$1:$AE$1,0),0) -> #N/A | AH21: =VLOOKUP($A21,$X$1:$AE$59,MATCH(AH$1,$X$1:$AE$1,0),0) -> #N/A | AI21: =VLOOKUP($A21,$X$1:$AE$59,MATCH(AI$1,$X$1:$AE$1,0),0) -> #N/A | AJ21: =VLOOKUP($A21,$X$1:$AE$59,MATCH(AJ$1,$X$1:$AE$1,0),0) -> #N/A | AK21: =VLOOKUP($A21,$X$1:$AE$59,MATCH(AK$1,$X$1:$AE$1,0),0) -> #N/A | AL21: =VLOOKUP($A21,$X$1:$AE$59,MATCH(AL$1,$X$1:$AE$1,0),0) -> #N/A
A22: =IF(AND((TODAY()-B22)<7,(TODAY()-B22>=0)),B22,NA()) -> #N/A | B22: =B21+7 -> 43994 | C22: =IF($B22<=TODAY(),SUMIF('Stats 2020'!$M$24:$M$1048576,"<="&Graphs!$B22,'Stats 2020'!O$24:O$1048576),NA()) -> 77.5 | D22: =IF($B22<=TODAY(),MAX($C22,$E22,$G22,$H22)+11+16.5,NA()) -> 113.25 | E22: =IF($B22<=TODAY(),SUMIF('Stats 2020'!$M$24:$M$1048576,"<="&Graphs!$B22,'Stats 2020'!Q$24:Q$1048576),NA()) -> 72 | F22: =IF($B22<=TODAY(),MAX($C22,$E22,$G22,$H22)+11+16.5,NA()) -> 113.25 | G22: =IF($B22<=TODAY(),SUMIF('Stats 2020'!$M$24:$M$1048576,"<="&Graphs!$B22,'Stats 2020'!S$24:S$1048576),NA()) -> 85.75 | H22: =IF($B22<=TODAY(),SUMIF('Stats 2020'!$M$24:$M$1048576,"<="&Graphs!$B22,'Stats 2020'!T$24:T$1048576),NA()) -> 72 | I22: =VLOOKUP($A22,$B$1:$H$59,MATCH(I$1,$B$1:$H$1,0),0) -> #N/A | J22: =VLOOKUP($A22,$B$1:$H$59,MATCH(J$1,$B$1:$H$1,0),0) -> #N/A | K22: =VLOOKUP($A22,$B$1:$H$59,MATCH(K$1,$B$1:$H$1,0),0) -> #N/A | L22: =VLOOKUP($A22,$B$1:$H$59,MATCH(L$1,$B$1:$H$1,0),0) -> #N/A | M22: =VLOOKUP($A22,$B$1:$H$59,MATCH(M$1,$B$1:$H$1,0),0) -> #N/A | N22: =VLOOKUP($A22,$B$1:$H$59,MATCH(N$1,$B$1:$H$1,0),0) -> #N/A | P22: =B22 -> 43994 | Q22: =VLOOKUP($B22,'Stats 2020'!$D$25:$J$200,MATCH(Graphs!Q$1,'Stats 2020'!$D$18:$J$18,0),0) -> 1 | R22: =VLOOKUP($B22,'Stats 2020'!$D$25:$J$200,MATCH(Graphs!R$1,'Stats 2020'!$D$18:$J$18,0),0) | S22: =VLOOKUP($B22,'Stats 2020'!$D$25:$J$200,MATCH(Graphs!S$1,'Stats 2020'!$D$18:$J$18,0),0) -> 1 | T22: =VLOOKUP($B22,'Stats 2020'!$D$25:$J$200,MATCH(Graphs!T$1,'Stats 2020'!$D$18:$J$18,0),0) -> 1 | U22: =VLOOKUP($B22,'Stats 2020'!$D$25:$J$200,MATCH(Graphs!U$1,'Stats 2020'!$D$18:$J$18,0),0) -> 1 | V22: =VLOOKUP($B22,'Stats 2020'!$D$25:$J$200,MATCH(Graphs!V$1,'Stats 2020'!$D$18:$J$18,0),0) -> 1 | X22: =B22 -> 43994 | Y22: =SUM(Q$2:Q22)/COUNTA($P$2:$P22) -> 0.9047619 | Z22: =SUM(R$2:R22)/COUNTA($P$2:$P22) -> 0.047619048 | AA22: =SUM(S$2:S22)/COUNTA($P$2:$P22) -> 0.85714286 | AB22: =SUM(T$2:T22)/COUNTA($P$2:$P22) -> 0.28571429 | AC22: =SUM(U$2:U22)/COUNTA($P$2:$P22) -> 0.80952381 | AD22: =SUM(V$2:V22)/COUNTA($P$2:$P22) -> 0.85714286 | AE22: =AVERAGE(Y22:AD22) -> 0.62698413 | AF22: =VLOOKUP($A22,$X$1:$AE$59,MATCH(AF$1,$X$1:$AE$1,0),0) -> #N/A | AG22: =VLOOKUP($A22,$X$1:$AE$59,MATCH(AG$1,$X$1:$AE$1,0),0) -> #N/A | AH22: =VLOOKUP($A22,$X$1:$AE$59,MATCH(AH$1,$X$1:$AE$1,0),0) -> #N/A | AI22: =VLOOKUP($A22,$X$1:$AE$59,MATCH(AI$1,$X$1:$AE$1,0),0) -> #N/A | AJ22: =VLOOKUP($A22,$X$1:$AE$59,MATCH(AJ$1,$X$1:$AE$1,0),0) -> #N/A | AK22: =VLOOKUP($A22,$X$1:$AE$59,MATCH(AK$1,$X$1:$AE$1,0),0) -> #N/A | AL22: =VLOOKUP($A22,$X$1:$AE$59,MATCH(AL$1,$X$1:$AE$1,0),0) -> #N/A
A23: =IF(AND((TODAY()-B23)<7,(TODAY()-B23>=0)),B23,NA()) -> #N/A | B23: =B22+7 -> 44001 | C23: =IF($B23<=TODAY(),SUMIF('Stats 2020'!$M$24:$M$1048576,"<="&Graphs!$B23,'Stats 2020'!O$24:O$1048576),NA()) -> 88.5 | D23: =IF($B23<=TODAY(),MAX($C23,$E23,$G23,$H23)+11+16.5,NA()) -> 116 | E23: =IF($B23<=TODAY(),SUMIF('Stats 2020'!$M$24:$M$1048576,"<="&Graphs!$B23,'Stats 2020'!Q$24:Q$1048576),NA()) -> 72 | F23: =IF($B23<=TODAY(),MAX($C23,$E23,$G23,$H23)+11+16.5,NA()) -> 116 | G23: =IF($B23<=TODAY(),SUMIF('Stats 2020'!$M$24:$M$1048576,"<="&Graphs!$B23,'Stats 2020'!S$24:S$1048576),NA()) -> 88.5 | H23: =IF($B23<=TODAY(),SUMIF('Stats 2020'!$M$24:$M$1048576,"<="&Graphs!$B23,'Stats 2020'!T$24:T$1048576),NA()) -> 74.75 | I23: =VLOOKUP($A23,$B$1:$H$59,MATCH(I$1,$B$1:$H$1,0),0) -> #N/A | J23: =VLOOKUP($A23,$B$1:$H$59,MATCH(J$1,$B$1:$H$1,0),0) -> #N/A | K23: =VLOOKUP($A23,$B$1:$H$59,MATCH(K$1,$B$1:$H$1,0),0) -> #N/A | L23: =VLOOKUP($A23,$B$1:$H$59,MATCH(L$1,$B$1:$H$1,0),0) -> #N/A | M23: =VLOOKUP($A23,$B$1:$H$59,MATCH(M$1,$B$1:$H$1,0),0) -> #N/A | N23: =VLOOKUP($A23,$B$1:$H$59,MATCH(N$1,$B$1:$H$1,0),0) -> #N/A | P23: =B23 -> 44001 | Q23: =VLOOKUP($B23,'Stats 2020'!$D$25:$J$200,MATCH(Graphs!Q$1,'Stats 2020'!$D$18:$J$18,0),0) -> 0 | R23: =VLOOKUP($B23,'Stats 2020'!$D$25:$J$200,MATCH(Graphs!R$1,'Stats 2020'!$D$18:$J$18,0),0) | S23: =VLOOKUP($B23,'Stats 2020'!$D$25:$J$200,MATCH(Graphs!S$1,'Stats 2020'!$D$18:$J$18,0),0) -> 1 | T23: =VLOOKUP($B23,'Stats 2020'!$D$25:$J$200,MATCH(Graphs!T$1,'Stats 2020'!$D$18:$J$18,0),0) -> 1 | U23: =VLOOKUP($B23,'Stats 2020'!$D$25:$J$200,MATCH(Graphs!U$1,'Stats 2020'!$D$18:$J$18,0),0) -> 1 | V23: =VLOOKUP($B23,'Stats 2020'!$D$25:$J$200,MATCH(Graphs!V$1,'Stats 2020'!$D$18:$J$18,0),0) -> 1 | X23: =B23 -> 44001 | Y23: =SUM(Q$2:Q23)/COUNTA($P$2:$P23) -> 0.86363636 | Z23: =SUM(R$2:R23)/COUNTA($P$2:$P23) -> 0.045454545 | AA23: =SUM(S$2:S23)/COUNTA($P$2:$P23) -> 0.86363636 | AB23: =SUM(T$2:T23)/COUNTA($P$2:$P23) -> 0.31818182 | AC23: =SUM(U$2:U23)/COUNTA($P$2:$P23) -> 0.81818182 | AD23: =SUM(V$2:V23)/COUNTA($P$2:$P23) -> 0.86363636 | AE23: =AVERAGE(Y23:AD23) -> 0.62878788 | AF23: =VLOOKUP($A23,$X$1:$AE$59,MATCH(AF$1,$X$1:$AE$1,0),0) -> #N/A | AG23: =VLOOKUP($A23,$X$1:$AE$59,MATCH(AG$1,$X$1:$AE$1,0),0) -> #N/A | AH23: =VLOOKUP($A23,$X$1:$AE$59,MATCH(AH$1,$X$1:$AE$1,0),0) -> #N/A | AI23: =VLOOKUP($A23,$X$1:$AE$59,MATCH(AI$1,$X$1:$AE$1,0),0) -> #N/A | AJ23: =VLOOKUP($A23,$X$1:$AE$59,MATCH(AJ$1,$X$1:$AE$1,0),0) -> #N/A | AK23: =VLOOKUP($A23,$X$1:$AE$59,MATCH(AK$1,$X$1:$AE$1,0),0) -> #N/A | AL23: =VLOOKUP($A23,$X$1:$AE$59,MATCH(AL$1,$X$1:$AE$1,0),0) -> #N/A
A24: =IF(AND((TODAY()-B24)<7,(TODAY()-B24>=0)),B24,NA()) -> #N/A | B24: =B23+7 -> 44008 | C24: =IF($B24<=TODAY(),SUMIF('Stats 2020'!$M$24:$M$1048576,"<="&Graphs!$B24,'Stats 2020'!O$24:O$1048576),NA()) -> 99.5 | D24: =IF($B24<=TODAY(),MAX($C24,$E24,$G24,$H24)+11+16.5,NA()) -> 127 | E24: =IF($B24<=TODAY(),SUMIF('Stats 2020'!$M$24:$M$1048576,"<="&Graphs!$B24,'Stats 2020'!Q$24:Q$1048576),NA()) -> 72 | F24: =IF($B24<=TODAY(),MAX($C24,$E24,$G24,$H24)+11+16.5,NA()) -> 127 | G24: =IF($B24<=TODAY(),SUMIF('Stats 2020'!$M$24:$M$1048576,"<="&Graphs!$B24,'Stats 2020'!S$24:S$1048576),NA()) -> 88.5 | H24: =IF($B24<=TODAY(),SUMIF('Stats 2020'!$M$24:$M$1048576,"<="&Graphs!$B24,'Stats 2020'!T$24:T$1048576),NA()) -> 74.75 | I24: =VLOOKUP($A24,$B$1:$H$59,MATCH(I$1,$B$1:$H$1,0),0) -> #N/A | J24: =VLOOKUP($A24,$B$1:$H$59,MATCH(J$1,$B$1:$H$1,0),0) -> #N/A | K24: =VLOOKUP($A24,$B$1:$H$59,MATCH(K$1,$B$1:$H$1,0),0) -> #N/A | L24: =VLOOKUP($A24,$B$1:$H$59,MATCH(L$1,$B$1:$H$1,0),0) -> #N/A | M24: =VLOOKUP($A24,$B$1:$H$59,MATCH(M$1,$B$1:$H$1,0),0) -> #N/A | N24: =VLOOKUP($A24,$B$1:$H$59,MATCH(N$1,$B$1:$H$1,0),0) -> #N/A | P24: =B24 -> 44008 | Q24: =VLOOKUP($B24,'Stats 2020'!$D$25:$J$200,MATCH(Graphs!Q$1,'Stats 2020'!$D$18:$J$18,0),0) -> 0 | R24: =VLOOKUP($B24,'Stats 2020'!$D$25:$J$200,MATCH(Graphs!R$1,'Stats 2020'!$D$18:$J$18,0),0) | S24: =VLOOKUP($B24,'Stats 2020'!$D$25:$J$200,MATCH(Graphs!S$1,'Stats 2020'!$D$18:$J$18,0),0) -> 1 | T24: =VLOOKUP($B24,'Stats 2020'!$D$25:$J$200,MATCH(Graphs!T$1,'Stats 2020'!$D$18:$J$18,0),0) | U24: =VLOOKUP($B24,'Stats 2020'!$D$25:$J$200,MATCH(Graphs!U$1,'Stats 2020'!$D$18:$J$18,0),0) -> 1 | V24: =VLOOKUP($B24,'Stats 2020'!$D$25:$J$200,MATCH(Graphs!V$1,'Stats 2020'!$D$18:$J$18,0),0) -> 1 | X24: =B24 -> 44008 | Y24: =SUM(Q$2:Q24)/COUNTA($P$2:$P24) -> 0.82608696 | Z24: =SUM(R$2:R24)/COUNTA($P$2:$P24) -> 0.043478261 | AA24: =SUM(S$2:S24)/COUNTA($P$2:$P24) -> 0.86956522 | AB24: =SUM(T$2:T24)/COUNTA($P$2:$P24) -> 0.30434783 | AC24: =SUM(U$2:U24)/COUNTA($P$2:$P24) -> 0.82608696 | AD24: =SUM(V$2:V24)/COUNTA($P$2:$P24) -> 0.86956522 | AE24: =AVERAGE(Y24:AD24) -> 0.62318841 | AF24: =VLOOKUP($A24,$X$1:$AE$59,MATCH(AF$1,$X$1:$AE$1,0),0) -> #N/A | AG24: =VLOOKUP($A24,$X$1:$AE$59,MATCH(AG$1,$X$1:$AE$1,0),0) -> #N/A | AH24: =VLOOKUP($A24,$X$1:$AE$59,MATCH(AH$1,$X$1:$AE$1,0),0) -> #N/A | AI24: =VLOOKUP($A24,$X$1:$AE$59,MATCH(AI$1,$X$1:$AE$1,0),0) -> #N/A | AJ24: =VLOOKUP($A24,$X$1:$AE$59,MATCH(AJ$1,$X$1:$AE$1,0),0) -> #N/A | AK24: =VLOOKUP($A24,$X$1:$AE$59,MATCH(AK$1,$X$1:$AE$1,0),0) -> #N/A | AL24: =VLOOKUP($A24,$X$1:$AE$59,MATCH(AL$1,$X$1:$AE$1,0),0) -> #N/A
A25: =IF(AND((TODAY()-B25)<7,(TODAY()-B25>=0)),B25,NA()) -> #N/A | B25: =B24+7 -> 44015 | C25: =IF($B25<=TODAY(),SUMIF('Stats 2020'!$M$24:$M$1048576,"<="&Graphs!$B25,'Stats 2020'!O$24:O$1048576),NA()) -> 102.25 | D25: =IF($B25<=TODAY(),MAX($C25,$E25,$G25,$H25)+11+16.5,NA()) -> 129.75 | E25: =IF($B25<=TODAY(),SUMIF('Stats 2020'!$M$24:$M$1048576,"<="&Graphs!$B25,'Stats 2020'!Q$24:Q$1048576),NA()) -> 72 | F25: =IF($B25<=TODAY(),MAX($C25,$E25,$G25,$H25)+11+16.5,NA()) -> 129.75 | G25: =IF($B25<=TODAY(),SUMIF('Stats 2020'!$M$24:$M$1048576,"<="&Graphs!$B25,'Stats 2020'!S$24:S$1048576),NA()) -> 88.5 | H25: =IF($B25<=TODAY(),SUMIF('Stats 2020'!$M$24:$M$1048576,"<="&Graphs!$B25,'Stats 2020'!T$24:T$1048576),NA()) -> 74.75 | I25: =VLOOKUP($A25,$B$1:$H$59,MATCH(I$1,$B$1:$H$1,0),0) -> #N/A | J25: =VLOOKUP($A25,$B$1:$H$59,MATCH(J$1,$B$1:$H$1,0),0) -> #N/A | K25: =VLOOKUP($A25,$B$1:$H$59,MATCH(K$1,$B$1:$H$1,0),0) -> #N/A | L25: =VLOOKUP($A25,$B$1:$H$59,MATCH(L$1,$B$1:$H$1,0),0) -> #N/A | M25: =VLOOKUP($A25,$B$1:$H$59,MATCH(M$1,$B$1:$H$1,0),0) -> #N/A | N25: =VLOOKUP($A25,$B$1:$H$59,MATCH(N$1,$B$1:$H$1,0),0) -> #N/A | P25: =B25 -> 44015 | Q25: =VLOOKUP($B25,'Stats 2020'!$D$25:$J$200,MATCH(Graphs!Q$1,'Stats 2020'!$D$18:$J$18,0),0) -> 1 | R25: =VLOOKUP($B25,'Stats 2020'!$D$25:$J$200,MATCH(Graphs!R$1,'Stats 2020'!$D$18:$J$18,0),0) | S25: =VLOOKUP($B25,'Stats 2020'!$D$25:$J$200,MATCH(Graphs!S$1,'Stats 2020'!$D$18:$J$18,0),0) -> 1 | T25: =VLOOKUP($B25,'Stats 2020'!$D$25:$J$200,MATCH(Graphs!T$1,'Stats 2020'!$D$18:$J$18,0),0) | U25: =VLOOKUP($B25,'Stats 2020'!$D$25:$J$200,MATCH(Graphs!U$1,'Stats 2020'!$D$18:$J$18,0),0) -> 1 | V25: =VLOOKUP($B25,'Stats 2020'!$D$25:$J$200,MATCH(Graphs!V$1,'Stats 2020'!$D$18:$J$18,0),0) -> 1 | X25: =B25 -> 44015 | Y25: =SUM(Q$2:Q24)/COUNTA($P$2:$P24) -> 0.82608696 | Z25: =SUM(R$2:R24)/COUNTA($P$2:$P24) -> 0.043478261 | AA25: =SUM(S$2:S24)/COUNTA($P$2:$P24) -> 0.86956522 | AB25: =SUM(T$2:T24)/COUNTA($P$2:$P24) -> 0.30434783 | AC25: =SUM(U$2:U24)/COUNTA($P$2:$P24) -> 0.82608696 | AD25: =SUM(V$2:V24)/COUNTA($P$2:$P24) -> 0.86956522 | AE25: =AVERAGE(Y25:AD25) -> 0.62318841 | AF25: =VLOOKUP($A25,$X$1:$AE$59,MATCH(AF$1,$X$1:$AE$1,0),0) -> #N/A | AG25: =VLOOKUP($A25,$X$1:$AE$59,MATCH(AG$1,$X$1:$AE$1,0),0) -> #N/A | AH25: =VLOOKUP($A25,$X$1:$AE$59,MATCH(AH$1,$X$1:$AE$1,0),0) -> #N/A | AI25: =VLOOKUP($A25,$X$1:$AE$59,MATCH(AI$1,$X$1:$AE$1,0),0) -> #N/A | AJ25: =VLOOKUP($A25,$X$1:$AE$59,MATCH(AJ$1,$X$1:$AE$1,0),0) -> #N/A | AK25: =VLOOKUP($A25,$X$1:$AE$59,MATCH(AK$1,$X$1:$AE$1,0),0) -> #N/A | AL25: =VLOOKUP($A25,$X$1:$AE$59,MATCH(AL$1,$X$1:$AE$1,0),0) -> #N/A
A26: =IF(AND((TODAY()-B26)<7,(TODAY()-B26>=0)),B26,NA()) -> #N/A | B26: =B25+7 -> 44022 | C26: =IF($B26<=TODAY(),SUMIF('Stats 2020'!$M$24:$M$1048576,"<="&Graphs!$B26,'Stats 2020'!O$24:O$1048576),NA()) -> 105 | D26: =IF($B26<=TODAY(),MAX($C26,$E26,$G26,$H26)+11+16.5,NA()) -> 132.5 | E26: =IF($B26<=TODAY(),SUMIF('Stats 2020'!$M$24:$M$1048576,"<="&Graphs!$B26,'Stats 2020'!Q$24:Q$1048576),NA()) -> 72 | F26: =IF($B26<=TODAY(),MAX($C26,$E26,$G26,$H26)+11+16.5,NA()) -> 132.5 | G26: =IF($B26<=TODAY(),SUMIF('Stats 2020'!$M$24:$M$1048576,"<="&Graphs!$B26,'Stats 2020'!S$24:S$1048576),NA()) -> 99.5 | H26: =IF($B26<=TODAY(),SUMIF('Stats 2020'!$M$24:$M$1048576,"<="&Graphs!$B26,'Stats 2020'!T$24:T$1048576),NA()) -> 74.75 | I26: =VLOOKUP($A26,$B$1:$H$59,MATCH(I$1,$B$1:$H$1,0),0) -> #N/A | J26: =VLOOKUP($A26,$B$1:$H$59,MATCH(J$1,$B$1:$H$1,0),0) -> #N/A | K26: =VLOOKUP($A26,$B$1:$H$59,MATCH(K$1,$B$1:$H$1,0),0) -> #N/A | L26: =VLOOKUP($A26,$B$1:$H$59,MATCH(L$1,$B$1:$H$1,0),0) -> #N/A | M26: =VLOOKUP($A26,$B$1:$H$59,MATCH(M$1,$B$1:$H$1,0),0) -> #N/A | N26: =VLOOKUP($A26,$B$1:$H$59,MATCH(N$1,$B$1:$H$1,0),0) -> #N/A | P26: =B26 -> 44022 | Q26: =VLOOKUP($B26,'Stats 2020'!$D$25:$J$200,MATCH(Graphs!Q$1,'Stats 2020'!$D$18:$J$18,0),0) -> 1 | R26: =VLOOKUP($B26,'Stats 2020'!$D$25:$J$200,MATCH(Graphs!R$1,'Stats 2020'!$D$18:$J$18,0),0) | S26: =VLOOKUP($B26,'Stats 2020'!$D$25:$J$200,MATCH(Graphs!S$1,'Stats 2020'!$D$18:$J$18,0),0) -> 1 | T26: =VLOOKUP($B26,'Stats 2020'!$D$25:$J$200,MATCH(Graphs!T$1,'Stats 2020'!$D$18:$J$18,0),0) | U26: =VLOOKUP($B26,'Stats 2020'!$D$25:$J$200,MATCH(Graphs!U$1,'Stats 2020'!$D$18:$J$18,0),0) -> 0 | V26: =VLOOKUP($B26,'Stats 2020'!$D$25:$J$200,MATCH(Graphs!V$1,'Stats 2020'!$D$18:$J$18,0),0) -> 1 | X26: =B26 -> 44022 | Y26: =SUM(Q$2:Q26)/COUNTA($P$2:$P26) -> 0.84 | Z26: =SUM(R$2:R26)/COUNTA($P$2:$P26) -> 0.04 | AA26: =SUM(S$2:S26)/COUNTA($P$2:$P26) -> 0.88 | AB26: =SUM(T$2:T26)/COUNTA($P$2:$P26) -> 0.28 | AC26: =SUM(U$2:U26)/COUNTA($P$2:$P26) -> 0.8 | AD26: =SUM(V$2:V26)/COUNTA($P$2:$P26) -> 0.88 | AE26: =AVERAGE(Y26:AD26) -> 0.62 | AF26: =VLOOKUP($A26,$X$1:$AE$59,MATCH(AF$1,$X$1:$AE$1,0),0) -> #N/A | AG26: =VLOOKUP($A26,$X$1:$AE$59,MATCH(AG$1,$X$1:$AE$1,0),0) -> #N/A | AH26: =VLOOKUP($A26,$X$1:$AE$59,MATCH(AH$1,$X$1:$AE$1,0),0) -> #N/A | AI26: =VLOOKUP($A26,$X$1:$AE$59,MATCH(AI$1,$X$1:$AE$1,0),0) -> #N/A | AJ26: =VLOOKUP($A26,$X$1:$AE$59,MATCH(AJ$1,$X$1:$AE$1,0),0) -> #N/A | AK26: =VLOOKUP($A26,$X$1:$AE$59,MATCH(AK$1,$X$1:$AE$1,0),0) -> #N/A | AL26: =VLOOKUP($A26,$X$1:$AE$59,MATCH(AL$1,$X$1:$AE$1,0),0) -> #N/A
A27: =IF(AND((TODAY()-B27)<7,(TODAY()-B27>=0)),B27,NA()) -> #N/A | B27: =B26+7 -> 44029 | C27: =IF($B27<=TODAY(),SUMIF('Stats 2020'!$M$24:$M$1048576,"<="&Graphs!$B27,'Stats 2020'!O$24:O$1048576),NA()) -> 116 | D27: =IF($B27<=TODAY(),MAX($C27,$E27,$G27,$H27)+11+16.5,NA()) -> 143.5 | E27: =IF($B27<=TODAY(),SUMIF('Stats 2020'!$M$24:$M$1048576,"<="&Graphs!$B27,'Stats 2020'!Q$24:Q$1048576),NA()) -> 83 | F27: =IF($B27<=TODAY(),MAX($C27,$E27,$G27,$H27)+11+16.5,NA()) -> 143.5 | G27: =IF($B27<=TODAY(),SUMIF('Stats 2020'!$M$24:$M$1048576,"<="&Graphs!$B27,'Stats 2020'!S$24:S$1048576),NA()) -> 99.5 | H27: =IF($B27<=TODAY(),SUMIF('Stats 2020'!$M$24:$M$1048576,"<="&Graphs!$B27,'Stats 2020'!T$24:T$1048576),NA()) -> 74.75 | I27: =VLOOKUP($A27,$B$1:$H$59,MATCH(I$1,$B$1:$H$1,0),0) -> #N/A | J27: =VLOOKUP($A27,$B$1:$H$59,MATCH(J$1,$B$1:$H$1,0),0) -> #N/A | K27: =VLOOKUP($A27,$B$1:$H$59,MATCH(K$1,$B$1:$H$1,0),0) -> #N/A | L27: =VLOOKUP($A27,$B$1:$H$59,MATCH(L$1,$B$1:$H$1,0),0) -> #N/A | M27: =VLOOKUP($A27,$B$1:$H$59,MATCH(M$1,$B$1:$H$1,0),0) -> #N/A | N27: =VLOOKUP($A27,$B$1:$H$59,MATCH(N$1,$B$1:$H$1,0),0) -> #N/A | P27: =B27 -> 44029 | Q27: =VLOOKUP($B27,'Stats 2020'!$D$25:$J$200,MATCH(Graphs!Q$1,'Stats 2020'!$D$18:$J$18,0),0) -> 0 | R27: =VLOOKUP($B27,'Stats 2020'!$D$25:$J$200,MATCH(Graphs!R$1,'Stats 2020'!$D$18:$J$18,0),0) | S27: =VLOOKUP($B27,'Stats 2020'!$D$25:$J$200,MATCH(Graphs!S$1,'Stats 2020'!$D$18:$J$18,0),0) -> 0 | T27: =VLOOKUP($B27,'Stats 2020'!$D$25:$J$200,MATCH(Graphs!T$1,'Stats 2020'!$D$18:$J$18,0),0) | U27: =VLOOKUP($B27,'Stats 2020'!$D$25:$J$200,MATCH(Graphs!U$1,'Stats 2020'!$D$18:$J$18,0),0) -> 1 | V27: =VLOOKUP($B27,'Stats 2020'!$D$25:$J$200,MATCH(Graphs!V$1,'Stats 2020'!$D$18:$J$18,0),0) -> 1 | X27: =B27 -> 44029 | Y27: =SUM(Q$2:Q27)/COUNTA($P$2:$P27) -> 0.80769231 | Z27: =SUM(R$2:R27)/COUNTA($P$2:$P27) -> 0.038461538 | AA27: =SUM(S$2:S27)/COUNTA($P$2:$P27) -> 0.84615385 | AB27: =SUM(T$2:T27)/COUNTA($P$2:$P27) -> 0.26923077 | AC27: =SUM(U$2:U27)/COUNTA($P$2:$P27) -> 0.80769231 | AD27: =SUM(V$2:V27)/COUNTA($P$2:$P27) -> 0.88461538 | AE27: =AVERAGE(Y27:AD27) -> 0.60897436 | AF27: =VLOOKUP($A27,$X$1:$AE$59,MATCH(AF$1,$X$1:$AE$1,0),0) -> #N/A | AG27: =VLOOKUP($A27,$X$1:$AE$59,MATCH(AG$1,$X$1:$AE$1,0),0) -> #N/A | AH27: =VLOOKUP($A27,$X$1:$AE$59,MATCH(AH$1,$X$1:$AE$1,0),0) -> #N/A | AI27: =VLOOKUP($A27,$X$1:$AE$59,MATCH(AI$1,$X$1:$AE$1,0),0) -> #N/A | AJ27: =VLOOKUP($A27,$X$1:$AE$59,MATCH(AJ$1,$X$1:$AE$1,0),0) -> #N/A | AK27: =VLOOKUP($A27,$X$1:$AE$59,MATCH(AK$1,$X$1:$AE$1,0),0) -> #N/A | AL27: =VLOOKUP($A27,$X$1:$AE$59,MATCH(AL$1,$X$1:$AE$1,0),0) -> #N/A
A28: =IF(AND((TODAY()-B28)<7,(TODAY()-B28>=0)),B28,NA()) -> #N/A | B28: =B27+7 -> 44036 | C28: =IF($B28<=TODAY(),SUMIF('Stats 2020'!$M$24:$M$1048576,"<="&Graphs!$B28,'Stats 2020'!O$24:O$1048576),NA()) -> 116 | D28: =IF($B28<=TODAY(),MAX($C28,$E28,$G28,$H28)+11+16.5,NA()) -> 143.5 | E28: =IF($B28<=TODAY(),SUMIF('Stats 2020'!$M$24:$M$1048576,"<="&Graphs!$B28,'Stats 2020'!Q$24:Q$1048576),NA()) -> 83 | F28: =IF($B28<=TODAY(),MAX($C28,$E28,$G28,$H28)+11+16.5,NA()) -> 143.5 | G28: =IF($B28<=TODAY(),SUMIF('Stats 2020'!$M$24:$M$1048576,"<="&Graphs!$B28,'Stats 2020'!S$24:S$1048576),NA()) -> 99.5 | H28: =IF($B28<=TODAY(),SUMIF('Stats 2020'!$M$24:$M$1048576,"<="&Graphs!$B28,'Stats 2020'!T$24:T$1048576),NA()) -> 85.75 | I28: =VLOOKUP($A28,$B$1:$H$59,MATCH(I$1,$B$1:$H$1,0),0) -> #N/A | J28: =VLOOKUP($A28,$B$1:$H$59,MATCH(J$1,$B$1:$H$1,0),0) -> #N/A | K28: =VLOOKUP($A28,$B$1:$H$59,MATCH(K$1,$B$1:$H$1,0),0) -> #N/A | L28: =VLOOKUP($A28,$B$1:$H$59,MATCH(L$1,$B$1:$H$1,0),0) -> #N/A | M28: =VLOOKUP($A28,$B$1:$H$59,MATCH(M$1,$B$1:$H$1,0),0) -> #N/A | N28: =VLOOKUP($A28,$B$1:$H$59,MATCH(N$1,$B$1:$H$1,0),0) -> #N/A | P28: =B28 -> 44036 | Q28: =VLOOKUP($B28,'Stats 2020'!$D$25:$J$200,MATCH(Graphs!Q$1,'Stats 2020'!$D$18:$J$18,0),0) -> 1 | R28: =VLOOKUP($B28,'Stats 2020'!$D$25:$J$200,MATCH(Graphs!R$1,'Stats 2020'!$D$18:$J$18,0),0) -> 1 | S28: =VLOOKUP($B28,'Stats 2020'!$D$25:$J$200,MATCH(Graphs!S$1,'Stats 2020'!$D$18:$J$18,0),0) -> 1 | T28: =VLOOKUP($B28,'Stats 2020'!$D$25:$J$200,MATCH(Graphs!T$1,'Stats 2020'!$D$18:$J$18,0),0) -> 1 | U28: =VLOOKUP($B28,'Stats 2020'!$D$25:$J$200,MATCH(Graphs!U$1,'Stats 2020'!$D$18:$J$18,0),0) -> 1 | V28: =VLOOKUP($B28,'Stats 2020'!$D$25:$J$200,MATCH(Graphs!V$1,'Stats 2020'!$D$18:$J$18,0),0) -> 0 | X28: =B28 -> 44036 | Y28: =SUM(Q$2:Q28)/COUNTA($P$2:$P28) -> 0.81481481 | Z28: =SUM(R$2:R28)/COUNTA($P$2:$P28) -> 0.074074074 | AA28: =SUM(S$2:S28)/COUNTA($P$2:$P28) -> 0.85185185 | AB28: =SUM(T$2:T28)/COUNTA($P$2:$P28) -> 0.2962963 | AC28: =SUM(U$2:U28)/COUNTA($P$2:$P28) -> 0.81481481 | AD28: =SUM(V$2:V28)/COUNTA($P$2:$P28) -> 0.85185185 | AE28: =AVERAGE(Y28:AD28) -> 0.61728395 | AF28: =VLOOKUP($A28,$X$1:$AE$59,MATCH(AF$1,$X$1:$AE$1,0),0) -> #N/A | AG28: =VLOOKUP($A28,$X$1:$AE$59,MATCH(AG$1,$X$1:$AE$1,0),0) -> #N/A | AH28: =VLOOKUP($A28,$X$1:$AE$59,MATCH(AH$1,$X$1:$AE$1,0),0) -> #N/A | AI28: =VLOOKUP($A28,$X$1:$AE$59,MATCH(AI$1,$X$1:$AE$1,0),0) -> #N/A | AJ28: =VLOOKUP($A28,$X$1:$AE$59,MATCH(AJ$1,$X$1:$AE$1,0),0) -> #N/A | AK28: =VLOOKUP($A28,$X$1:$AE$59,MATCH(AK$1,$X$1:$AE$1,0),0) -> #N/A | AL28: =VLOOKUP($A28,$X$1:$AE$59,MATCH(AL$1,$X$1:$AE$1,0),0) -> #N/A
A29: =IF(AND((TODAY()-B29)<7,(TODAY()-B29>=0)),B29,NA()) -> #N/A | B29: =B28+7 -> 44043 | C29: =IF($B29<=TODAY(),SUMIF('Stats 2020'!$M$24:$M$1048576,"<="&Graphs!$B29,'Stats 2020'!O$24:O$1048576),NA()) -> 127 | D29: =IF($B29<=TODAY(),MAX($C29,$E29,$G29,$H29)+11+16.5,NA()) -> 154.5 | E29: =IF($B29<=TODAY(),SUMIF('Stats 2020'!$M$24:$M$1048576,"<="&Graphs!$B29,'Stats 2020'!Q$24:Q$1048576),NA()) -> 83 | F29: =IF($B29<=TODAY(),MAX($C29,$E29,$G29,$H29)+11+16.5,NA()) -> 154.5 | G29: =IF($B29<=TODAY(),SUMIF('Stats 2020'!$M$24:$M$1048576,"<="&Graphs!$B29,'Stats 2020'!S$24:S$1048576),NA()) -> 99.5 | H29: =IF($B29<=TODAY(),SUMIF('Stats 2020'!$M$24:$M$1048576,"<="&Graphs!$B29,'Stats 2020'!T$24:T$1048576),NA()) -> 85.75 | I29: =VLOOKUP($A29,$B$1:$H$59,MATCH(I$1,$B$1:$H$1,0),0) -> #N/A | J29: =VLOOKUP($A29,$B$1:$H$59,MATCH(J$1,$B$1:$H$1,0),0) -> #N/A | K29: =VLOOKUP($A29,$B$1:$H$59,MATCH(K$1,$B$1:$H$1,0),0) -> #N/A | L29: =VLOOKUP($A29,$B$1:$H$59,MATCH(L$1,$B$1:$H$1,0),0) -> #N/A | M29: =VLOOKUP($A29,$B$1:$H$59,MATCH(M$1,$B$1:$H$1,0),0) -> #N/A | N29: =VLOOKUP($A29,$B$1:$H$59,MATCH(N$1,$B$1:$H$1,0),0) -> #N/A | P29: =B29 -> 44043 | Q29: =VLOOKUP($B29,'Stats 2020'!$D$25:$J$200,MATCH(Graphs!Q$1,'Stats 2020'!$D$18:$J$18,0),0) -> 0 | R29: =VLOOKUP($B29,'Stats 2020'!$D$25:$J$200,MATCH(Graphs!R$1,'Stats 2020'!$D$18:$J$18,0),0) | S29: =VLOOKUP($B29,'Stats 2020'!$D$25:$J$200,MATCH(Graphs!S$1,'Stats 2020'!$D$18:$J$18,0),0) -> 1 | T29: =VLOOKUP($B29,'Stats 2020'!$D$25:$J$200,MATCH(Graphs!T$1,'Stats 2020'!$D$18:$J$18,0),0) | U29: =VLOOKUP($B29,'Stats 2020'!$D$25:$J$200,MATCH(Graphs!U$1,'Stats 2020'!$D$18:$J$18,0),0) -> 1 | V29: =VLOOKUP($B29,'Stats 2020'!$D$25:$J$200,MATCH(Graphs!V$1,'Stats 2020'!$D$18:$J$18,0),0) -> 1 | X29: =B29 -> 44043 | Y29: =SUM(Q$2:Q29)/COUNTA($P$2:$P29) -> 0.78571429 | Z29: =SUM(R$2:R29)/COUNTA($P$2:$P29) -> 0.071428571 | AA29: =SUM(S$2:S29)/COUNTA($P$2:$P29) -> 0.85714286 | AB29: =SUM(T$2:T29)/COUNTA($P$2:$P29) -> 0.28571429 | AC29: =SUM(U$2:U29)/COUNTA($P$2:$P29) -> 0.82142857 | AD29: =SUM(V$2:V29)/COUNTA($P$2:$P29) -> 0.85714286 | AE29: =AVERAGE(Y29:AD29) -> 0.61309524 | AF29: =VLOOKUP($A29,$X$1:$AE$59,MATCH(AF$1,$X$1:$AE$1,0),0) -> #N/A | AG29: =VLOOKUP($A29,$X$1:$AE$59,MATCH(AG$1,$X$1:$AE$1,0),0) -> #N/A | AH29: =VLOOKUP($A29,$X$1:$AE$59,MATCH(AH$1,$X$1:$AE$1,0),0) -> #N/A | AI29: =VLOOKUP($A29,$X$1:$AE$59,MATCH(AI$1,$X$1:$AE$1,0),0) -> #N/A | AJ29: =VLOOKUP($A29,$X$1:$AE$59,MATCH(AJ$1,$X$1:$AE$1,0),0) -> #N/A | AK29: =VLOOKUP($A29,$X$1:$AE$59,MATCH(AK$1,$X$1:$AE$1,0),0) -> #N/A | AL29: =VLOOKUP($A29,$X$1:$AE$59,MATCH(AL$1,$X$1:$AE$1,0),0) -> #N/A
A30: =IF(AND((TODAY()-B30)<7,(TODAY()-B30>=0)),B30,NA()) -> #N/A | B30: =B29+7 -> 44050 | C30: =IF($B30<=TODAY(),SUMIF('Stats 2020'!$M$24:$M$1048576,"<="&Graphs!$B30,'Stats 2020'!O$24:O$1048576),NA()) -> 127 | D30: =IF($B30<=TODAY(),MAX($C30,$E30,$G30,$H30)+11+16.5,NA()) -> 154.5 | E30: =IF($B30<=TODAY(),SUMIF('Stats 2020'!$M$24:$M$1048576,"<="&Graphs!$B30,'Stats 2020'!Q$24:Q$1048576),NA()) -> 83 | F30: =IF($B30<=TODAY(),MAX($C30,$E30,$G30,$H30)+11+16.5,NA()) -> 154.5 | G30: =IF($B30<=TODAY(),SUMIF('Stats 2020'!$M$24:$M$1048576,"<="&Graphs!$B30,'Stats 2020'!S$24:S$1048576),NA()) -> 99.5 | H30: =IF($B30<=TODAY(),SUMIF('Stats 2020'!$M$24:$M$1048576,"<="&Graphs!$B30,'Stats 2020'!T$24:T$1048576),NA()) -> 85.75 | I30: =VLOOKUP($A30,$B$1:$H$59,MATCH(I$1,$B$1:$H$1,0),0) -> #N/A | J30: =VLOOKUP($A30,$B$1:$H$59,MATCH(J$1,$B$1:$H$1,0),0) -> #N/A | K30: =VLOOKUP($A30,$B$1:$H$59,MATCH(K$1,$B$1:$H$1,0),0) -> #N/A | L30: =VLOOKUP($A30,$B$1:$H$59,MATCH(L$1,$B$1:$H$1,0),0) -> #N/A | M30: =VLOOKUP($A30,$B$1:$H$59,MATCH(M$1,$B$1:$H$1,0),0) -> #N/A | N30: =VLOOKUP($A30,$B$1:$H$59,MATCH(N$1,$B$1:$H$1,0),0) -> #N/A | P30: =B30 -> 44050 | Q30: =VLOOKUP($B30,'Stats 2020'!$D$25:$J$200,MATCH(Graphs!Q$1,'Stats 2020'!$D$18:$J$18,0),0) -> 1 | R30: =VLOOKUP($B30,'Stats 2020'!$D$25:$J$200,MATCH(Graphs!R$1,'Stats 2020'!$D$18:$J$18,0),0) | S30: =VLOOKUP($B30,'Stats 2020'!$D$25:$J$200,MATCH(Graphs!S$1,'Stats 2020'!$D$18:$J$18,0),0) -> 1 | T30: =VLOOKUP($B30,'Stats 2020'!$D$25:$J$200,MATCH(Graphs!T$1,'Stats 2020'!$D$18:$J$18,0),0) | U30: =VLOOKUP($B30,'Stats 2020'!$D$25:$J$200,MATCH(Graphs!U$1,'Stats 2020'!$D$18:$J$18,0),0) -> 1 | V30: =VLOOKUP($B30,'Stats 2020'!$D$25:$J$200,MATCH(Graphs!V$1,'Stats 2020'!$D$18:$J$18,0),0) -> 1 | X30: =B30 -> 44050 | Y30: =SUM(Q$2:Q30)/COUNTA($P$2:$P30) -> 0.79310345 | Z30: =SUM(R$2:R30)/COUNTA($P$2:$P30) -> 0.068965517 | AA30: =SUM(S$2:S30)/COUNTA($P$2:$P30) -> 0.86206897 | AB30: =SUM(T$2:T30)/COUNTA($P$2:$P30) -> 0.27586207 | AC30: =SUM(U$2:U30)/COUNTA($P$2:$P30) -> 0.82758621 | AD30: =SUM(V$2:V30)/COUNTA($P$2:$P30) -> 0.86206897 | AE30: =AVERAGE(Y30:AD30) -> 0.61494253 | AF30: =VLOOKUP($A30,$X$1:$AE$59,MATCH(AF$1,$X$1:$AE$1,0),0) -> #N/A | AG30: =VLOOKUP($A30,$X$1:$AE$59,MATCH(AG$1,$X$1:$AE$1,0),0) -> #N/A | AH30: =VLOOKUP($A30,$X$1:$AE$59,MATCH(AH$1,$X$1:$AE$1,0),0) -> #N/A | AI30: =VLOOKUP($A30,$X$1:$AE$59,MATCH(AI$1,$X$1:$AE$1,0),0) -> #N/A | AJ30: =VLOOKUP($A30,$X$1:$AE$59,MATCH(AJ$1,$X$1:$AE$1,0),0) -> #N/A | AK30: =VLOOKUP($A30,$X$1:$AE$59,MATCH(AK$1,$X$1:$AE$1,0),0) -> #N/A | AL30: =VLOOKUP($A30,$X$1:$AE$59,MATCH(AL$1,$X$1:$AE$1,0),0) -> #N/A
A31: =IF(AND((TODAY()-B31)<7,(TODAY()-B31>=0)),B31,NA()) -> #N/A | B31: =B30+7 -> 44057 | C31: =IF($B31<=TODAY(),SUMIF('Stats 2020'!$M$24:$M$1048576,"<="&Graphs!$B31,'Stats 2020'!O$24:O$1048576),NA()) -> 129.75 | D31: =IF($B31<=TODAY(),MAX($C31,$E31,$G31,$H31)+11+16.5,NA()) -> 157.25 | E31: =IF($B31<=TODAY(),SUMIF('Stats 2020'!$M$24:$M$1048576,"<="&Graphs!$B31,'Stats 2020'!Q$24:Q$1048576),NA()) -> 83 | F31: =IF($B31<=TODAY(),MAX($C31,$E31,$G31,$H31)+11+16.5,NA()) -> 157.25 | G31: =IF($B31<=TODAY(),SUMIF('Stats 2020'!$M$24:$M$1048576,"<="&Graphs!$B31,'Stats 2020'!S$24:S$1048576),NA()) -> 99.5 | H31: =IF($B31<=TODAY(),SUMIF('Stats 2020'!$M$24:$M$1048576,"<="&Graphs!$B31,'Stats 2020'!T$24:T$1048576),NA()) -> 85.75 | I31: =VLOOKUP($A31,$B$1:$H$59,MATCH(I$1,$B$1:$H$1,0),0) -> #N/A | J31: =VLOOKUP($A31,$B$1:$H$59,MATCH(J$1,$B$1:$H$1,0),0) -> #N/A | K31: =VLOOKUP($A31,$B$1:$H$59,MATCH(K$1,$B$1:$H$1,0),0) -> #N/A | L31: =VLOOKUP($A31,$B$1:$H$59,MATCH(L$1,$B$1:$H$1,0),0) -> #N/A | M31: =VLOOKUP($A31,$B$1:$H$59,MATCH(M$1,$B$1:$H$1,0),0) -> #N/A | N31: =VLOOKUP($A31,$B$1:$H$59,MATCH(N$1,$B$1:$H$1,0),0) -> #N/A | P31: =B31 -> 44057 | Q31: =VLOOKUP($B31,'Stats 2020'!$D$25:$J$200,MATCH(Graphs!Q$1,'Stats 2020'!$D$18:$J$18,0),0) -> 1 | R31: =VLOOKUP($B31,'Stats 2020'!$D$25:$J$200,MATCH(Graphs!R$1,'Stats 2020'!$D$18:$J$18,0),0) -> 1 | S31: =VLOOKUP($B31,'Stats 2020'!$D$25:$J$200,MATCH(Graphs!S$1,'Stats 2020'!$D$18:$J$18,0),0) -> 1 | T31: =VLOOKUP($B31,'Stats 2020'!$D$25:$J$200,MATCH(Graphs!T$1,'Stats 2020'!$D$18:$J$18,0),0) | U31: =VLOOKUP($B31,'Stats 2020'!$D$25:$J$200,MATCH(Graphs!U$1,'Stats 2020'!$D$18:$J$18,0),0) -> 1 | V31: =VLOOKUP($B31,'Stats 2020'!$D$25:$J$200,MATCH(Graphs!V$1,'Stats 2020'!$D$18:$J$18,0),0) -> 1 | X31: =B31 -> 44057 | Y31: =SUM(Q$2:Q31)/COUNTA($P$2:$P31) -> 0.8 | Z31: =SUM(R$2:R31)/COUNTA($P$2:$P31) -> 0.1 | AA31: =SUM(S$2:S31)/COUNTA($P$2:$P31) -> 0.86666667 | AB31: =SUM(T$2:T31)/COUNTA($P$2:$P31) -> 0.26666667 | AC31: =SUM(U$2:U31)/COUNTA($P$2:$P31) -> 0.83333333 | AD31: =SUM(V$2:V31)/COUNTA($P$2:$P31) -> 0.86666667 | AE31: =AVERAGE(Y31:AD31) -> 0.62222222 | AF31: =VLOOKUP($A31,$X$1:$AE$59,MATCH(AF$1,$X$1:$AE$1,0),0) -> #N/A | AG31: =VLOOKUP($A31,$X$1:$AE$59,MATCH(AG$1,$X$1:$AE$1,0),0) -> #N/A | AH31: =VLOOKUP($A31,$X$1:$AE$59,MATCH(AH$1,$X$1:$AE$1,0),0) -> #N/A | AI31: =VLOOKUP($A31,$X$1:$AE$59,MATCH(AI$1,$X$1:$AE$1,0),0) -> #N/A | AJ31: =VLOOKUP($A31,$X$1:$AE$59,MATCH(AJ$1,$X$1:$AE$1,0),0) -> #N/A | AK31: =VLOOKUP($A31,$X$1:$AE$59,MATCH(AK$1,$X$1:$AE$1,0),0) -> #N/A | AL31: =VLOOKUP($A31,$X$1:$AE$59,MATCH(AL$1,$X$1:$AE$1,0),0) -> #N/A
A32: =IF(AND((TODAY()-B32)<7,(TODAY()-B32>=0)),B32,NA()) -> #N/A | B32: =B31+7 -> 44064 | C32: =IF($B32<=TODAY(),SUMIF('Stats 2020'!$M$24:$M$1048576,"<="&Graphs!$B32,'Stats 2020'!O$24:O$1048576),NA()) -> 129.75 | D32: =IF($B32<=TODAY(),MAX($C32,$E32,$G32,$H32)+11+16.5,NA()) -> 157.25 | E32: =IF($B32<=TODAY(),SUMIF('Stats 2020'!$M$24:$M$1048576,"<="&Graphs!$B32,'Stats 2020'!Q$24:Q$1048576),NA()) -> 94 | F32: =IF($B32<=TODAY(),MAX($C32,$E32,$G32,$H32)+11+16.5,NA()) -> 157.25 | G32: =IF($B32<=TODAY(),SUMIF('Stats 2020'!$M$24:$M$1048576,"<="&Graphs!$B32,'Stats 2020'!S$24:S$1048576),NA()) -> 99.5 | H32: =IF($B32<=TODAY(),SUMIF('Stats 2020'!$M$24:$M$1048576,"<="&Graphs!$B32,'Stats 2020'!T$24:T$1048576),NA()) -> 85.75 | I32: =VLOOKUP($A32,$B$1:$H$59,MATCH(I$1,$B$1:$H$1,0),0) -> #N/A | J32: =VLOOKUP($A32,$B$1:$H$59,MATCH(J$1,$B$1:$H$1,0),0) -> #N/A | K32: =VLOOKUP($A32,$B$1:$H$59,MATCH(K$1,$B$1:$H$1,0),0) -> #N/A | L32: =VLOOKUP($A32,$B$1:$H$59,MATCH(L$1,$B$1:$H$1,0),0) -> #N/A | M32: =VLOOKUP($A32,$B$1:$H$59,MATCH(M$1,$B$1:$H$1,0),0) -> #N/A | N32: =VLOOKUP($A32,$B$1:$H$59,MATCH(N$1,$B$1:$H$1,0),0) -> #N/A | P32: =B32 -> 44064 | Q32: =VLOOKUP($B32,'Stats 2020'!$D$25:$J$200,MATCH(Graphs!Q$1,'Stats 2020'!$D$18:$J$18,0),0) -> 1 | R32: =VLOOKUP($B32,'Stats 2020'!$D$25:$J$200,MATCH(Graphs!R$1,'Stats 2020'!$D$18:$J$18,0),0) | S32: =VLOOKUP($B32,'Stats 2020'!$D$25:$J$200,MATCH(Graphs!S$1,'Stats 2020'!$D$18:$J$18,0),0) -> 0 | T32: =VLOOKUP($B32,'Stats 2020'!$D$25:$J$200,MATCH(Graphs!T$1,'Stats 2020'!$D$18:$J$18,0),0) -> 1 | U32: =VLOOKUP($B32,'Stats 2020'!$D$25:$J$200,MATCH(Graphs!U$1,'Stats 2020'!$D$18:$J$18,0),0) -> 1 | V32: =VLOOKUP($B32,'Stats 2020'!$D$25:$J$200,MATCH(Graphs!V$1,'Stats 2020'!$D$18:$J$18,0),0) -> 1 | X32: =B32 -> 44064 | Y32: =SUM(Q$2:Q32)/COUNTA($P$2:$P32) -> 0.80645161 | Z32: =SUM(R$2:R32)/COUNTA($P$2:$P32) -> 0.096774194 | AA32: =SUM(S$2:S32)/COUNTA($P$2:$P32) -> 0.83870968 | AB32: =SUM(T$2:T32)/COUNTA($P$2:$P32) -> 0.29032258 | AC32: =SUM(U$2:U32)/COUNTA($P$2:$P32) -> 0.83870968 | AD32: =SUM(V$2:V32)/COUNTA($P$2:$P32) -> 0.87096774 | AE32: =AVERAGE(Y32:AD32) -> 0.62365591 | AF32: =VLOOKUP($A32,$X$1:$AE$59,MATCH(AF$1,$X$1:$AE$1,0),0) -> #N/A | AG32: =VLOOKUP($A32,$X$1:$AE$59,MATCH(AG$1,$X$1:$AE$1,0),0) -> #N/A | AH32: =VLOOKUP($A32,$X$1:$AE$59,MATCH(AH$1,$X$1:$AE$1,0),0) -> #N/A | AI32: =VLOOKUP($A32,$X$1:$AE$59,MATCH(AI$1,$X$1:$AE$1,0),0) -> #N/A | AJ32: =VLOOKUP($A32,$X$1:$AE$59,MATCH(AJ$1,$X$1:$AE$1,0),0) -> #N/A | AK32: =VLOOKUP($A32,$X$1:$AE$59,MATCH(AK$1,$X$1:$AE$1,0),0) -> #N/A | AL32: =VLOOKUP($A32,$X$1:$AE$59,MATCH(AL$1,$X$1:$AE$1,0),0) -> #N/A
A33: =IF(AND((TODAY()-B33)<7,(TODAY()-B33>=0)),B33,NA()) -> #N/A | B33: =B32+7 -> 44071 | C33: =IF($B33<=TODAY(),SUMIF('Stats 2020'!$M$24:$M$1048576,"<="&Graphs!$B33,'Stats 2020'!O$24:O$1048576),NA()) -> 140.75 | D33: =IF($B33<=TODAY(),MAX($C33,$E33,$G33,$H33)+11+16.5,NA()) -> 168.25 | E33: =IF($B33<=TODAY(),SUMIF('Stats 2020'!$M$24:$M$1048576,"<="&Graphs!$B33,'Stats 2020'!Q$24:Q$1048576),NA()) -> 94 | F33: =IF($B33<=TODAY(),MAX($C33,$E33,$G33,$H33)+11+16.5,NA()) -> 168.25 | G33: =IF($B33<=TODAY(),SUMIF('Stats 2020'!$M$24:$M$1048576,"<="&Graphs!$B33,'Stats 2020'!S$24:S$1048576),NA()) -> 110.5 | H33: =IF($B33<=TODAY(),SUMIF('Stats 2020'!$M$24:$M$1048576,"<="&Graphs!$B33,'Stats 2020'!T$24:T$1048576),NA()) -> 85.75 | I33: =VLOOKUP($A33,$B$1:$H$59,MATCH(I$1,$B$1:$H$1,0),0) -> #N/A | J33: =VLOOKUP($A33,$B$1:$H$59,MATCH(J$1,$B$1:$H$1,0),0) -> #N/A | K33: =VLOOKUP($A33,$B$1:$H$59,MATCH(K$1,$B$1:$H$1,0),0) -> #N/A | L33: =VLOOKUP($A33,$B$1:$H$59,MATCH(L$1,$B$1:$H$1,0),0) -> #N/A | M33: =VLOOKUP($A33,$B$1:$H$59,MATCH(M$1,$B$1:$H$1,0),0) -> #N/A | N33: =VLOOKUP($A33,$B$1:$H$59,MATCH(N$1,$B$1:$H$1,0),0) -> #N/A | P33: =B33 -> 44071 | Q33: =VLOOKUP($B33,'Stats 2020'!$D$25:$J$200,MATCH(Graphs!Q$1,'Stats 2020'!$D$18:$J$18,0),0) -> 0 | R33: =VLOOKUP($B33,'Stats 2020'!$D$25:$J$200,MATCH(Graphs!R$1,'Stats 2020'!$D$18:$J$18,0),0) | S33: =VLOOKUP($B33,'Stats 2020'!$D$25:$J$200,MATCH(Graphs!S$1,'Stats 2020'!$D$18:$J$18,0),0) -> 1 | T33: =VLOOKUP($B33,'Stats 2020'!$D$25:$J$200,MATCH(Graphs!T$1,'Stats 2020'!$D$18:$J$18,0),0) -> 1 | U33: =VLOOKUP($B33,'Stats 2020'!$D$25:$J$200,MATCH(Graphs!U$1,'Stats 2020'!$D$18:$J$18,0),0) -> 0 | V33: =VLOOKUP($B33,'Stats 2020'!$D$25:$J$200,MATCH(Graphs!V$1,'Stats 2020'!$D$18:$J$18,0),0) -> 1 | X33: =B33 -> 44071 | Y33: =SUM(Q$2:Q33)/COUNTA($P$2:$P33) -> 0.78125 | Z33: =SUM(R$2:R33)/COUNTA($P$2:$P33) -> 0.09375 | AA33: =SUM(S$2:S33)/COUNTA($P$2:$P33) -> 0.84375 | AB33: =SUM(T$2:T33)/COUNTA($P$2:$P33) -> 0.3125 | AC33: =SUM(U$2:U33)/COUNTA($P$2:$P33) -> 0.8125 | AD33: =SUM(V$2:V33)/COUNTA($P$2:$P33) -> 0.875 | AE33: =AVERAGE(Y33:AD33) -> 0.61979167 | AF33: =VLOOKUP($A33,$X$1:$AE$59,MATCH(AF$1,$X$1:$AE$1,0),0) -> #N/A | AG33: =VLOOKUP($A33,$X$1:$AE$59,MATCH(AG$1,$X$1:$AE$1,0),0) -> #N/A | AH33: =VLOOKUP($A33,$X$1:$AE$59,MATCH(AH$1,$X$1:$AE$1,0),0) -> #N/A | AI33: =VLOOKUP($A33,$X$1:$AE$59,MATCH(AI$1,$X$1:$AE$1,0),0) -> #N/A | AJ33: =VLOOKUP($A33,$X$1:$AE$59,MATCH(AJ$1,$X$1:$AE$1,0),0) -> #N/A | AK33: =VLOOKUP($A33,$X$1:$AE$59,MATCH(AK$1,$X$1:$AE$1,0),0) -> #N/A | AL33: =VLOOKUP($A33,$X$1:$AE$59,MATCH(AL$1,$X$1:$AE$1,0),0) -> #N/A
A34: =IF(AND((TODAY()-B34)<7,(TODAY()-B34>=0)),B34,NA()) -> #N/A | B34: =B33+7 -> 44078 | C34: =IF($B34<=TODAY(),SUMIF('Stats 2020'!$M$24:$M$1048576,"<="&Graphs!$B34,'Stats 2020'!O$24:O$1048576),NA()) -> 143.5 | D34: =IF($B34<=TODAY(),MAX($C34,$E34,$G34,$H34)+11+16.5,NA()) -> 171 | E34: =IF($B34<=TODAY(),SUMIF('Stats 2020'!$M$24:$M$1048576,"<="&Graphs!$B34,'Stats 2020'!Q$24:Q$1048576),NA()) -> 94 | F34: =IF($B34<=TODAY(),MAX($C34,$E34,$G34,$H34)+11+16.5,NA()) -> 171 | G34: =IF($B34<=TODAY(),SUMIF('Stats 2020'!$M$24:$M$1048576,"<="&Graphs!$B34,'Stats 2020'!S$24:S$1048576),NA()) -> 110.5 | H34: =IF($B34<=TODAY(),SUMIF('Stats 2020'!$M$24:$M$1048576,"<="&Graphs!$B34,'Stats 2020'!T$24:T$1048576),NA()) -> 85.75 | I34: =VLOOKUP($A34,$B$1:$H$59,MATCH(I$1,$B$1:$H$1,0),0) -> #N/A | J34: =VLOOKUP($A34,$B$1:$H$59,MATCH(J$1,$B$1:$H$1,0),0) -> #N/A | K34: =VLOOKUP($A34,$B$1:$H$59,MATCH(K$1,$B$1:$H$1,0),0) -> #N/A | L34: =VLOOKUP($A34,$B$1:$H$59,MATCH(L$1,$B$1:$H$1,0),0) -> #N/A | M34: =VLOOKUP($A34,$B$1:$H$59,MATCH(M$1,$B$1:$H$1,0),0) -> #N/A | N34: =VLOOKUP($A34,$B$1:$H$59,MATCH(N$1,$B$1:$H$1,0),0) -> #N/A | P34: =B34 -> 44078 | Q34: =VLOOKUP($B34,'Stats 2020'!$D$25:$J$200,MATCH(Graphs!Q$1,'Stats 2020'!$D$18:$J$18,0),0) -> 1 | R34: =VLOOKUP($B34,'Stats 2020'!$D$25:$J$200,MATCH(Graphs!R$1,'Stats 2020'!$D$18:$J$18,0),0) | S34: =VLOOKUP($B34,'Stats 2020'!$D$25:$J$200,MATCH(Graphs!S$1,'Stats 2020'!$D$18:$J$18,0),0) -> 1 | T34: =VLOOKUP($B34,'Stats 2020'!$D$25:$J$200,MATCH(Graphs!T$1,'Stats 2020'!$D$18:$J$18,0),0) -> 1 | U34: =VLOOKUP($B34,'Stats 2020'!$D$25:$J$200,MATCH(Graphs!U$1,'Stats 2020'!$D$18:$J$18,0),0) -> 1 | V34: =VLOOKUP($B34,'Stats 2020'!$D$25:$J$200,MATCH(Graphs!V$1,'Stats 2020'!$D$18:$J$18,0),0) -> 1 | X34: =B34 -> 44078 | Y34: =SUM(Q$2:Q34)/COUNTA($P$2:$P34) -> 0.78787879 | Z34: =SUM(R$2:R34)/COUNTA($P$2:$P34) -> 0.090909091 | AA34: =SUM(S$2:S34)/COUNTA($P$2:$P34) -> 0.84848485 | AB34: =SUM(T$2:T34)/COUNTA($P$2:$P34) -> 0.33333333 | AC34: =SUM(U$2:U34)/COUNTA($P$2:$P34) -> 0.81818182 | AD34: =SUM(V$2:V34)/COUNTA($P$2:$P34) -> 0.87878788 | AE34: =AVERAGE(Y34:AD34) -> 0.62626263 | AF34: =VLOOKUP($A34,$X$1:$AE$59,MATCH(AF$1,$X$1:$AE$1,0),0) -> #N/A | AG34: =VLOOKUP($A34,$X$1:$AE$59,MATCH(AG$1,$X$1:$AE$1,0),0) -> #N/A | AH34: =VLOOKUP($A34,$X$1:$AE$59,MATCH(AH$1,$X$1:$AE$1,0),0) -> #N/A | AI34: =VLOOKUP($A34,$X$1:$AE$59,MATCH(AI$1,$X$1:$AE$1,0),0) -> #N/A | AJ34: =VLOOKUP($A34,$X$1:$AE$59,MATCH(AJ$1,$X$1:$AE$1,0),0) -> #N/A | AK34: =VLOOKUP($A34,$X$1:$AE$59,MATCH(AK$1,$X$1:$AE$1,0),0) -> #N/A | AL34: =VLOOKUP($A34,$X$1:$AE$59,MATCH(AL$1,$X$1:$AE$1,0),0) -> #N/A
A35: =IF(AND((TODAY()-B35)<7,(TODAY()-B35>=0)),B35,NA()) -> #N/A | B35: =B34+7 -> 44085 | C35: =IF($B35<=TODAY(),SUMIF('Stats 2020'!$M$24:$M$1048576,"<="&Graphs!$B35,'Stats 2020'!O$24:O$1048576),NA()) -> 143.5 | D35: =IF($B35<=TODAY(),MAX($C35,$E35,$G35,$H35)+11+16.5,NA()) -> 171 | E35: =IF($B35<=TODAY(),SUMIF('Stats 2020'!$M$24:$M$1048576,"<="&Graphs!$B35,'Stats 2020'!Q$24:Q$1048576),NA()) -> 94 | F35: =IF($B35<=TODAY(),MAX($C35,$E35,$G35,$H35)+11+16.5,NA()) -> 171 | G35: =IF($B35<=TODAY(),SUMIF('Stats 2020'!$M$24:$M$1048576,"<="&Graphs!$B35,'Stats 2020'!S$24:S$1048576),NA()) -> 110.5 | H35: =IF($B35<=TODAY(),SUMIF('Stats 2020'!$M$24:$M$1048576,"<="&Graphs!$B35,'Stats 2020'!T$24:T$1048576),NA()) -> 85.75 | I35: =VLOOKUP($A35,$B$1:$H$59,MATCH(I$1,$B$1:$H$1,0),0) -> #N/A | J35: =VLOOKUP($A35,$B$1:$H$59,MATCH(J$1,$B$1:$H$1,0),0) -> #N/A | K35: =VLOOKUP($A35,$B$1:$H$59,MATCH(K$1,$B$1:$H$1,0),0) -> #N/A | L35: =VLOOKUP($A35,$B$1:$H$59,MATCH(L$1,$B$1:$H$1,0),0) -> #N/A | M35: =VLOOKUP($A35,$B$1:$H$59,MATCH(M$1,$B$1:$H$1,0),0) -> #N/A | N35: =VLOOKUP($A35,$B$1:$H$59,MATCH(N$1,$B$1:$H$1,0),0) -> #N/A | P35: =B35 -> 44085 | Q35: =VLOOKUP($B35,'Stats 2020'!$D$25:$J$200,MATCH(Graphs!Q$1,'Stats 2020'!$D$18:$J$18,0),0) -> 1 | R35: =VLOOKUP($B35,'Stats 2020'!$D$25:$J$200,MATCH(Graphs!R$1,'Stats 2020'!$D$18:$J$18,0),0) | S35: =VLOOKUP($B35,'Stats 2020'!$D$25:$J$200,MATCH(Graphs!S$1,'Stats 2020'!$D$18:$J$18,0),0) -> 1 | T35: =VLOOKUP($B35,'Stats 2020'!$D$25:$J$200,MATCH(Graphs!T$1,'Stats 2020'!$D$18:$J$18,0),0) | U35: =VLOOKUP($B35,'Stats 2020'!$D$25:$J$200,MATCH(Graphs!U$1,'Stats 2020'!$D$18:$J$18,0),0) -> 1 | V35: =VLOOKUP($B35,'Stats 2020'!$D$25:$J$200,MATCH(Graphs!V$1,'Stats 2020'!$D$18:$J$18,0),0) -> 1 | X35: =B35 -> 44085 | Y35: =SUM(Q$2:Q35)/COUNTA($P$2:$P35) -> 0.79411765 | Z35: =SUM(R$2:R35)/COUNTA($P$2:$P35) -> 0.088235294 | AA35: =SUM(S$2:S35)/COUNTA($P$2:$P35) -> 0.85294118 | AB35: =SUM(T$2:T35)/COUNTA($P$2:$P35) -> 0.32352941 | AC35: =SUM(U$2:U35)/COUNTA($P$2:$P35) -> 0.82352941 | AD35: =SUM(V$2:V35)/COUNTA($P$2:$P35) -> 0.88235294 | AE35: =AVERAGE(Y35:AD35) -> 0.62745098 | AF35: =VLOOKUP($A35,$X$1:$AE$59,MATCH(AF$1,$X$1:$AE$1,0),0) -> #N/A | AG35: =VLOOKUP($A35,$X$1:$AE$59,MATCH(AG$1,$X$1:$AE$1,0),0) -> #N/A | AH35: =VLOOKUP($A35,$X$1:$AE$59,MATCH(AH$1,$X$1:$AE$1,0),0) -> #N/A | AI35: =VLOOKUP($A35,$X$1:$AE$59,MATCH(AI$1,$X$1:$AE$1,0),0) -> #N/A | AJ35: =VLOOKUP($A35,$X$1:$AE$59,MATCH(AJ$1,$X$1:$AE$1,0),0) -> #N/A | AK35: =VLOOKUP($A35,$X$1:$AE$59,MATCH(AK$1,$X$1:$AE$1,0),0) -> #N/A | AL35: =VLOOKUP($A35,$X$1:$AE$59,MATCH(AL$1,$X$1:$AE$1,0),0) -> #N/A
A36: =IF(AND((TODAY()-B36)<7,(TODAY()-B36>=0)),B36,NA()) -> #N/A | B36: =B35+7 -> 44092 | C36: =IF($B36<=TODAY(),SUMIF('Stats 2020'!$M$24:$M$1048576,"<="&Graphs!$B36,'Stats 2020'!O$24:O$1048576),NA()) -> 143.5 | D36: =IF($B36<=TODAY(),MAX($C36,$E36,$G36,$H36)+11+16.5,NA()) -> 171 | E36: =IF($B36<=TODAY(),SUMIF('Stats 2020'!$M$24:$M$1048576,"<="&Graphs!$B36,'Stats 2020'!Q$24:Q$1048576),NA()) -> 94 | F36: =IF($B36<=TODAY(),MAX($C36,$E36,$G36,$H36)+11+16.5,NA()) -> 171 | G36: =IF($B36<=TODAY(),SUMIF('Stats 2020'!$M$24:$M$1048576,"<="&Graphs!$B36,'Stats 2020'!S$24:S$1048576),NA()) -> 121.5 | H36: =IF($B36<=TODAY(),SUMIF('Stats 2020'!$M$24:$M$1048576,"<="&Graphs!$B36,'Stats 2020'!T$24:T$1048576),NA()) -> 85.75 | I36: =VLOOKUP($A36,$B$1:$H$59,MATCH(I$1,$B$1:$H$1,0),0) -> #N/A | J36: =VLOOKUP($A36,$B$1:$H$59,MATCH(J$1,$B$1:$H$1,0),0) -> #N/A | K36: =VLOOKUP($A36,$B$1:$H$59,MATCH(K$1,$B$1:$H$1,0),0) -> #N/A | L36: =VLOOKUP($A36,$B$1:$H$59,MATCH(L$1,$B$1:$H$1,0),0) -> #N/A | M36: =VLOOKUP($A36,$B$1:$H$59,MATCH(M$1,$B$1:$H$1,0),0) -> #N/A | N36: =VLOOKUP($A36,$B$1:$H$59,MATCH(N$1,$B$1:$H$1,0),0) -> #N/A | P36: =B36 -> 44092 | Q36: =VLOOKUP($B36,'Stats 2020'!$D$25:$J$200,MATCH(Graphs!Q$1,'Stats 2020'!$D$18:$J$18,0),0) -> 1 | R36: =VLOOKUP($B36,'Stats 2020'!$D$25:$J$200,MATCH(Graphs!R$1,'Stats 2020'!$D$18:$J$18,0),0) | S36: =VLOOKUP($B36,'Stats 2020'!$D$25:$J$200,MATCH(Graphs!S$1,'Stats 2020'!$D$18:$J$18,0),0) -> 1 | T36: =VLOOKUP($B36,'Stats 2020'!$D$25:$J$200,MATCH(Graphs!T$1,'Stats 2020'!$D$18:$J$18,0),0) -> 1 | U36: =VLOOKUP($B36,'Stats 2020'!$D$25:$J$200,MATCH(Graphs!U$1,'Stats 2020'!$D$18:$J$18,0),0) -> 0 | V36: =VLOOKUP($B36,'Stats 2020'!$D$25:$J$200,MATCH(Graphs!V$1,'Stats 2020'!$D$18:$J$18,0),0) -> 1 | X36: =B36 -> 44092 | Y36: =SUM(Q$2:Q36)/COUNTA($P$2:$P36) -> 0.8 | Z36: =SUM(R$2:R36)/COUNTA($P$2:$P36) -> 0.085714286 | AA36: =SUM(S$2:S36)/COUNTA($P$2:$P36) -> 0.85714286 | AB36: =SUM(T$2:T36)/COUNTA($P$2:$P36) -> 0.34285714 | AC36: =SUM(U$2:U36)/COUNTA($P$2:$P36) -> 0.8 | AD36: =SUM(V$2:V36)/COUNTA($P$2:$P36) -> 0.88571429 | AE36: =AVERAGE(Y36:AD36) -> 0.62857143 | AF36: =VLOOKUP($A36,$X$1:$AE$59,MATCH(AF$1,$X$1:$AE$1,0),0) -> #N/A | AG36: =VLOOKUP($A36,$X$1:$AE$59,MATCH(AG$1,$X$1:$AE$1,0),0) -> #N/A | AH36: =VLOOKUP($A36,$X$1:$AE$59,MATCH(AH$1,$X$1:$AE$1,0),0) -> #N/A | AI36: =VLOOKUP($A36,$X$1:$AE$59,MATCH(AI$1,$X$1:$AE$1,0),0) -> #N/A | AJ36: =VLOOKUP($A36,$X$1:$AE$59,MATCH(AJ$1,$X$1:$AE$1,0),0) -> #N/A | AK36: =VLOOKUP($A36,$X$1:$AE$59,MATCH(AK$1,$X$1:$AE$1,0),0) -> #N/A | AL36: =VLOOKUP($A36,$X$1:$AE$59,MATCH(AL$1,$X$1:$AE$1,0),0) -> #N/A
A37: =IF(AND((TODAY()-B37)<7,(TODAY()-B37>=0)),B37,NA()) -> #N/A | B37: =B36+7 -> 44099 | C37: =IF($B37<=TODAY(),SUMIF('Stats 2020'!$M$24:$M$1048576,"<="&Graphs!$B37,'Stats 2020'!O$24:O$1048576),NA()) -> 146.25 | D37: =IF($B37<=TODAY(),MAX($C37,$E37,$G37,$H37)+11+16.5,NA()) -> 173.75 | E37: =IF($B37<=TODAY(),SUMIF('Stats 2020'!$M$24:$M$1048576,"<="&Graphs!$B37,'Stats 2020'!Q$24:Q$1048576),NA()) -> 94 | F37: =IF($B37<=TODAY(),MAX($C37,$E37,$G37,$H37)+11+16.5,NA()) -> 173.75 | G37: =IF($B37<=TODAY(),SUMIF('Stats 2020'!$M$24:$M$1048576,"<="&Graphs!$B37,'Stats 2020'!S$24:S$1048576),NA()) -> 121.5 | H37: =IF($B37<=TODAY(),SUMIF('Stats 2020'!$M$24:$M$1048576,"<="&Graphs!$B37,'Stats 2020'!T$24:T$1048576),NA()) -> 85.75 | I37: =VLOOKUP($A37,$B$1:$H$59,MATCH(I$1,$B$1:$H$1,0),0) -> #N/A | J37: =VLOOKUP($A37,$B$1:$H$59,MATCH(J$1,$B$1:$H$1,0),0) -> #N/A | K37: =VLOOKUP($A37,$B$1:$H$59,MATCH(K$1,$B$1:$H$1,0),0) -> #N/A | L37: =VLOOKUP($A37,$B$1:$H$59,MATCH(L$1,$B$1:$H$1,0),0) -> #N/A | M37: =VLOOKUP($A37,$B$1:$H$59,MATCH(M$1,$B$1:$H$1,0),0) -> #N/A | N37: =VLOOKUP($A37,$B$1:$H$59,MATCH(N$1,$B$1:$H$1,0),0) -> #N/A | P37: =B37 -> 44099 | Q37: =VLOOKUP($B37,'Stats 2020'!$D$25:$J$200,MATCH(Graphs!Q$1,'Stats 2020'!$D$18:$J$18,0),0) -> 1 | R37: =VLOOKUP($B37,'Stats 2020'!$D$25:$J$200,MATCH(Graphs!R$1,'Stats 2020'!$D$18:$J$18,0),0) | S37: =VLOOKUP($B37,'Stats 2020'!$D$25:$J$200,MATCH(Graphs!S$1,'Stats 2020'!$D$18:$J$18,0),0) -> 1 | T37: =VLOOKUP($B37,'Stats 2020'!$D$25:$J$200,MATCH(Graphs!T$1,'Stats 2020'!$D$18:$J$18,0),0) | U37: =VLOOKUP($B37,'Stats 2020'!$D$25:$J$200,MATCH(Graphs!U$1,'Stats 2020'!$D$18:$J$18,0),0) -> 1 | V37: =VLOOKUP($B37,'Stats 2020'!$D$25:$J$200,MATCH(Graphs!V$1,'Stats 2020'!$D$18:$J$18,0),0) -> 1 | X37: =B37 -> 44099 | Y37: =SUM(Q$2:Q36)/COUNTA($P$2:$P36) -> 0.8 | Z37: =SUM(R$2:R36)/COUNTA($P$2:$P36) -> 0.085714286 | AA37: =SUM(S$2:S36)/COUNTA($P$2:$P36) -> 0.85714286 | AB37: =SUM(T$2:T36)/COUNTA($P$2:$P36) -> 0.34285714 | AC37: =SUM(U$2:U36)/COUNTA($P$2:$P36) -> 0.8 | AD37: =SUM(V$2:V36)/COUNTA($P$2:$P36) -> 0.88571429 | AE37: =AVERAGE(Y37:AD37) -> 0.62857143 | AF37: =VLOOKUP($A37,$X$1:$AE$59,MATCH(AF$1,$X$1:$AE$1,0),0) -> #N/A | AG37: =VLOOKUP($A37,$X$1:$AE$59,MATCH(AG$1,$X$1:$AE$1,0),0) -> #N/A | AH37: =VLOOKUP($A37,$X$1:$AE$59,MATCH(AH$1,$X$1:$AE$1,0),0) -> #N/A | AI37: =VLOOKUP($A37,$X$1:$AE$59,MATCH(AI$1,$X$1:$AE$1,0),0) -> #N/A | AJ37: =VLOOKUP($A37,$X$1:$AE$59,MATCH(AJ$1,$X$1:$AE$1,0),0) -> #N/A | AK37: =VLOOKUP($A37,$X$1:$AE$59,MATCH(AK$1,$X$1:$AE$1,0),0) -> #N/A | AL37: =VLOOKUP($A37,$X$1:$AE$59,MATCH(AL$1,$X$1:$AE$1,0),0) -> #N/A
A38: =IF(AND((TODAY()-B38)<7,(TODAY()-B38>=0)),B38,NA()) -> #N/A | B38: =B37+7 -> 44106 | C38: =IF($B38<=TODAY(),SUMIF('Stats 2020'!$M$24:$M$1048576,"<="&Graphs!$B38,'Stats 2020'!O$24:O$1048576),NA()) -> 146.25 | D38: =IF($B38<=TODAY(),MAX($C38,$E38,$G38,$H38)+11+16.5,NA()) -> 173.75 | E38: =IF($B38<=TODAY(),SUMIF('Stats 2020'!$M$24:$M$1048576,"<="&Graphs!$B38,'Stats 2020'!Q$24:Q$1048576),NA()) -> 94 | F38: =IF($B38<=TODAY(),MAX($C38,$E38,$G38,$H38)+11+16.5,NA()) -> 173.75 | G38: =IF($B38<=TODAY(),SUMIF('Stats 2020'!$M$24:$M$1048576,"<="&Graphs!$B38,'Stats 2020'!S$24:S$1048576),NA()) -> 121.5 | H38: =IF($B38<=TODAY(),SUMIF('Stats 2020'!$M$24:$M$1048576,"<="&Graphs!$B38,'Stats 2020'!T$24:T$1048576),NA()) -> 85.75 | I38: =VLOOKUP($A38,$B$1:$H$59,MATCH(I$1,$B$1:$H$1,0),0) -> #N/A | J38: =VLOOKUP($A38,$B$1:$H$59,MATCH(J$1,$B$1:$H$1,0),0) -> #N/A | K38: =VLOOKUP($A38,$B$1:$H$59,MATCH(K$1,$B$1:$H$1,0),0) -> #N/A | L38: =VLOOKUP($A38,$B$1:$H$59,MATCH(L$1,$B$1:$H$1,0),0) -> #N/A | M38: =VLOOKUP($A38,$B$1:$H$59,MATCH(M$1,$B$1:$H$1,0),0) -> #N/A | N38: =VLOOKUP($A38,$B$1:$H$59,MATCH(N$1,$B$1:$H$1,0),0) -> #N/A | P38: =B38 -> 44106 | Q38: =VLOOKUP($B38,'Stats 2020'!$D$25:$J$200,MATCH(Graphs!Q$1,'Stats 2020'!$D$18:$J$18,0),0) -> 1 | R38: =VLOOKUP($B38,'Stats 2020'!$D$25:$J$200,MATCH(Graphs!R$1,'Stats 2020'!$D$18:$J$18,0),0) | S38: =VLOOKUP($B38,'Stats 2020'!$D$25:$J$200,MATCH(Graphs!S$1,'Stats 2020'!$D$18:$J$18,0),0) -> 1 | T38: =VLOOKUP($B38,'Stats 2020'!$D$25:$J$200,MATCH(Graphs!T$1,'Stats 2020'!$D$18:$J$18,0),0) | U38: =VLOOKUP($B38,'Stats 2020'!$D$25:$J$200,MATCH(Graphs!U$1,'Stats 2020'!$D$18:$J$18,0),0) -> 1 | V38: =VLOOKUP($B38,'Stats 2020'!$D$25:$J$200,MATCH(Graphs!V$1,'Stats 2020'!$D$18:$J$18,0),0) -> 1 | X38: =B38 -> 44106 | Y38: =SUM(Q$2:Q38)/COUNTA($P$2:$P38) -> 0.81081081 | Z38: =SUM(R$2:R38)/COUNTA($P$2:$P38) -> 0.081081081 | AA38: =SUM(S$2:S38)/COUNTA($P$2:$P38) -> 0.86486486 | AB38: =SUM(T$2:T38)/COUNTA($P$2:$P38) -> 0.32432432 | AC38: =SUM(U$2:U38)/COUNTA($P$2:$P38) -> 0.81081081 | AD38: =SUM(V$2:V38)/COUNTA($P$2:$P38) -> 0.89189189 | AE38: =AVERAGE(Y38:AD38) -> 0.63063063 | AF38: =VLOOKUP($A38,$X$1:$AE$59,MATCH(AF$1,$X$1:$AE$1,0),0) -> #N/A | AG38: =VLOOKUP($A38,$X$1:$AE$59,MATCH(AG$1,$X$1:$AE$1,0),0) -> #N/A | AH38: =VLOOKUP($A38,$X$1:$AE$59,MATCH(AH$1,$X$1:$AE$1,0),0) -> #N/A | AI38: =VLOOKUP($A38,$X$1:$AE$59,MATCH(AI$1,$X$1:$AE$1,0),0) -> #N/A | AJ38: =VLOOKUP($A38,$X$1:$AE$59,MATCH(AJ$1,$X$1:$AE$1,0),0) -> #N/A | AK38: =VLOOKUP($A38,$X$1:$AE$59,MATCH(AK$1,$X$1:$AE$1,0),0) -> #N/A | AL38: =VLOOKUP($A38,$X$1:$AE$59,MATCH(AL$1,$X$1:$AE$1,0),0) -> #N/A
A39: =IF(AND((TODAY()-B39)<7,(TODAY()-B39>=0)),B39,NA()) -> #N/A | B39: =B38+7 -> 44113 | C39: =IF($B39<=TODAY(),SUMIF('Stats 2020'!$M$24:$M$1048576,"<="&Graphs!$B39,'Stats 2020'!O$24:O$1048576),NA()) -> 149 | D39: =IF($B39<=TODAY(),MAX($C39,$E39,$G39,$H39)+11+16.5,NA()) -> 176.5 | E39: =IF($B39<=TODAY(),SUMIF('Stats 2020'!$M$24:$M$1048576,"<="&Graphs!$B39,'Stats 2020'!Q$24:Q$1048576),NA()) -> 105 | F39: =IF($B39<=TODAY(),MAX($C39,$E39,$G39,$H39)+11+16.5,NA()) -> 176.5 | G39: =IF($B39<=TODAY(),SUMIF('Stats 2020'!$M$24:$M$1048576,"<="&Graphs!$B39,'Stats 2020'!S$24:S$1048576),NA()) -> 121.5 | H39: =IF($B39<=TODAY(),SUMIF('Stats 2020'!$M$24:$M$1048576,"<="&Graphs!$B39,'Stats 2020'!T$24:T$1048576),NA()) -> 85.75 | I39: =VLOOKUP($A39,$B$1:$H$59,MATCH(I$1,$B$1:$H$1,0),0) -> #N/A | J39: =VLOOKUP($A39,$B$1:$H$59,MATCH(J$1,$B$1:$H$1,0),0) -> #N/A | K39: =VLOOKUP($A39,$B$1:$H$59,MATCH(K$1,$B$1:$H$1,0),0) -> #N/A | L39: =VLOOKUP($A39,$B$1:$H$59,MATCH(L$1,$B$1:$H$1,0),0) -> #N/A | M39: =VLOOKUP($A39,$B$1:$H$59,MATCH(M$1,$B$1:$H$1,0),0) -> #N/A | N39: =VLOOKUP($A39,$B$1:$H$59,MATCH(N$1,$B$1:$H$1,0),0) -> #N/A | P39: =B39 -> 44113 | Q39: =VLOOKUP($B39,'Stats 2020'!$D$25:$J$200,MATCH(Graphs!Q$1,'Stats 2020'!$D$18:$J$18,0),0) -> 1 | R39: =VLOOKUP($B39,'Stats 2020'!$D$25:$J$200,MATCH(Graphs!R$1,'Stats 2020'!$D$18:$J$18,0),0) | S39: =VLOOKUP($B39,'Stats 2020'!$D$25:$J$200,MATCH(Graphs!S$1,'Stats 2020'!$D$18:$J$18,0),0) -> 0 | T39: =VLOOKUP($B39,'Stats 2020'!$D$25:$J$200,MATCH(Graphs!T$1,'Stats 2020'!$D$18:$J$18,0),0) | U39: =VLOOKUP($B39,'Stats 2020'!$D$25:$J$200,MATCH(Graphs!U$1,'Stats 2020'!$D$18:$J$18,0),0) -> 1 | V39: =VLOOKUP($B39,'Stats 2020'!$D$25:$J$200,MATCH(Graphs!V$1,'Stats 2020'!$D$18:$J$18,0),0) -> 1 | X39: =B39 -> 44113 | Y39: =SUM(Q$2:Q39)/COUNTA($P$2:$P39) -> 0.81578947 | Z39: =SUM(R$2:R39)/COUNTA($P$2:$P39) -> 0.078947368 | AA39: =SUM(S$2:S39)/COUNTA($P$2:$P39) -> 0.84210526 | AB39: =SUM(T$2:T39)/COUNTA($P$2:$P39) -> 0.31578947 | AC39: =SUM(U$2:U39)/COUNTA($P$2:$P39) -> 0.81578947 | AD39: =SUM(V$2:V39)/COUNTA($P$2:$P39) -> 0.89473684 | AE39: =AVERAGE(Y39:AD39) -> 0.62719298 | AF39: =VLOOKUP($A39,$X$1:$AE$59,MATCH(AF$1,$X$1:$AE$1,0),0) -> #N/A | AG39: =VLOOKUP($A39,$X$1:$AE$59,MATCH(AG$1,$X$1:$AE$1,0),0) -> #N/A | AH39: =VLOOKUP($A39,$X$1:$AE$59,MATCH(AH$1,$X$1:$AE$1,0),0) -> #N/A | AI39: =VLOOKUP($A39,$X$1:$AE$59,MATCH(AI$1,$X$1:$AE$1,0),0) -> #N/A | AJ39: =VLOOKUP($A39,$X$1:$AE$59,MATCH(AJ$1,$X$1:$AE$1,0),0) -> #N/A | AK39: =VLOOKUP($A39,$X$1:$AE$59,MATCH(AK$1,$X$1:$AE$1,0),0) -> #N/A | AL39: =VLOOKUP($A39,$X$1:$AE$59,MATCH(AL$1,$X$1:$AE$1,0),0) -> #N/A
A40: =IF(AND((TODAY()-B40)<7,(TODAY()-B40>=0)),B40,NA()) -> #N/A | B40: =B39+7 -> 44120 | C40: =IF($B40<=TODAY(),SUMIF('Stats 2020'!$M$24:$M$1048576,"<="&Graphs!$B40,'Stats 2020'!O$24:O$1048576),NA()) -> 149 | D40: =IF($B40<=TODAY(),MAX($C40,$E40,$G40,$H40)+11+16.5,NA()) -> 176.5 | E40: =IF($B40<=TODAY(),SUMIF('Stats 2020'!$M$24:$M$1048576,"<="&Graphs!$B40,'Stats 2020'!Q$24:Q$1048576),NA()) -> 105 | F40: =IF($B40<=TODAY(),MAX($C40,$E40,$G40,$H40)+11+16.5,NA()) -> 176.5 | G40: =IF($B40<=TODAY(),SUMIF('Stats 2020'!$M$24:$M$1048576,"<="&Graphs!$B40,'Stats 2020'!S$24:S$1048576),NA()) -> 121.5 | H40: =IF($B40<=TODAY(),SUMIF('Stats 2020'!$M$24:$M$1048576,"<="&Graphs!$B40,'Stats 2020'!T$24:T$1048576),NA()) -> 85.75 | I40: =VLOOKUP($A40,$B$1:$H$59,MATCH(I$1,$B$1:$H$1,0),0) -> #N/A | J40: =VLOOKUP($A40,$B$1:$H$59,MATCH(J$1,$B$1:$H$1,0),0) -> #N/A | K40: =VLOOKUP($A40,$B$1:$H$59,MATCH(K$1,$B$1:$H$1,0),0) -> #N/A | L40: =VLOOKUP($A40,$B$1:$H$59,MATCH(L$1,$B$1:$H$1,0),0) -> #N/A | M40: =VLOOKUP($A40,$B$1:$H$59,MATCH(M$1,$B$1:$H$1,0),0) -> #N/A | N40: =VLOOKUP($A40,$B$1:$H$59,MATCH(N$1,$B$1:$H$1,0),0) -> #N/A | P40: =B40 -> 44120 | Q40: =VLOOKUP($B40,'Stats 2020'!$D$25:$J$200,MATCH(Graphs!Q$1,'Stats 2020'!$D$18:$J$18,0),0) -> 1 | R40: =VLOOKUP($B40,'Stats 2020'!$D$25:$J$200,MATCH(Graphs!R$1,'Stats 2020'!$D$18:$J$18,0),0) | S40: =VLOOKUP($B40,'Stats 2020'!$D$25:$J$200,MATCH(Graphs!S$1,'Stats 2020'!$D$18:$J$18,0),0) -> 1 | T40: =VLOOKUP($B40,'Stats 2020'!$D$25:$J$200,MATCH(Graphs!T$1,'Stats 2020'!$D$18:$J$18,0),0) | U40: =VLOOKUP($B40,'Stats 2020'!$D$25:$J$200,MATCH(Graphs!U$1,'Stats 2020'!$D$18:$J$18,0),0) -> 1 | V40: =VLOOKUP($B40,'Stats 2020'!$D$25:$J$200,MATCH(Graphs!V$1,'Stats 2020'!$D$18:$J$18,0),0) -> 1 | X40: =B40 -> 44120 | Y40: =SUM(Q$2:Q40)/COUNTA($P$2:$P40) -> 0.82051282 | Z40: =SUM(R$2:R40)/COUNTA($P$2:$P40) -> 0.076923077 | AA40: =SUM(S$2:S40)/COUNTA($P$2:$P40) -> 0.84615385 | AB40: =SUM(T$2:T40)/COUNTA($P$2:$P40) -> 0.30769231 | AC40: =SUM(U$2:U40)/COUNTA($P$2:$P40) -> 0.82051282 | AD40: =SUM(V$2:V40)/COUNTA($P$2:$P40) -> 0.8974359 | AE40: =AVERAGE(Y40:AD40) -> 0.62820513 | AF40: =VLOOKUP($A40,$X$1:$AE$59,MATCH(AF$1,$X$1:$AE$1,0),0) -> #N/A | AG40: =VLOOKUP($A40,$X$1:$AE$59,MATCH(AG$1,$X$1:$AE$1,0),0) -> #N/A | AH40: =VLOOKUP($A40,$X$1:$AE$59,MATCH(AH$1,$X$1:$AE$1,0),0) -> #N/A | AI40: =VLOOKUP($A40,$X$1:$AE$59,MATCH(AI$1,$X$1:$AE$1,0),0) -> #N/A | AJ40: =VLOOKUP($A40,$X$1:$AE$59,MATCH(AJ$1,$X$1:$AE$1,0),0) -> #N/A | AK40: =VLOOKUP($A40,$X$1:$AE$59,MATCH(AK$1,$X$1:$AE$1,0),0) -> #N/A | AL40: =VLOOKUP($A40,$X$1:$AE$59,MATCH(AL$1,$X$1:$AE$1,0),0) -> #N/A
A41: =IF(AND((TODAY()-B41)<7,(TODAY()-B41>=0)),B41,NA()) -> #N/A | B41: =B40+7 -> 44127 | C41: =IF($B41<=TODAY(),SUMIF('Stats 2020'!$M$24:$M$1048576,"<="&Graphs!$B41,'Stats 2020'!O$24:O$1048576),NA()) -> 154.5 | D41: =IF($B41<=TODAY(),MAX($C41,$E41,$G41,$H41)+11+16.5,NA()) -> 182 | E41: =IF($B41<=TODAY(),SUMIF('Stats 2020'!$M$24:$M$1048576,"<="&Graphs!$B41,'Stats 2020'!Q$24:Q$1048576),NA()) -> 116 | F41: =IF($B41<=TODAY(),MAX($C41,$E41,$G41,$H41)+11+16.5,NA()) -> 182 | G41: =IF($B41<=TODAY(),SUMIF('Stats 2020'!$M$24:$M$1048576,"<="&Graphs!$B41,'Stats 2020'!S$24:S$1048576),NA()) -> 132.5 | H41: =IF($B41<=TODAY(),SUMIF('Stats 2020'!$M$24:$M$1048576,"<="&Graphs!$B41,'Stats 2020'!T$24:T$1048576),NA()) -> 85.75 | I41: =VLOOKUP($A41,$B$1:$H$59,MATCH(I$1,$B$1:$H$1,0),0) -> #N/A | J41: =VLOOKUP($A41,$B$1:$H$59,MATCH(J$1,$B$1:$H$1,0),0) -> #N/A | K41: =VLOOKUP($A41,$B$1:$H$59,MATCH(K$1,$B$1:$H$1,0),0) -> #N/A | L41: =VLOOKUP($A41,$B$1:$H$59,MATCH(L$1,$B$1:$H$1,0),0) -> #N/A | M41: =VLOOKUP($A41,$B$1:$H$59,MATCH(M$1,$B$1:$H$1,0),0) -> #N/A | N41: =VLOOKUP($A41,$B$1:$H$59,MATCH(N$1,$B$1:$H$1,0),0) -> #N/A | P41: =B41 -> 44127 | Q41: =VLOOKUP($B41,'Stats 2020'!$D$25:$J$200,MATCH(Graphs!Q$1,'Stats 2020'!$D$18:$J$18,0),0) -> 1 | R41: =VLOOKUP($B41,'Stats 2020'!$D$25:$J$200,MATCH(Graphs!R$1,'Stats 2020'!$D$18:$J$18,0),0) -> 1 | S41: =VLOOKUP($B41,'Stats 2020'!$D$25:$J$200,MATCH(Graphs!S$1,'Stats 2020'!$D$18:$J$18,0),0) -> 0 | T41: =VLOOKUP($B41,'Stats 2020'!$D$25:$J$200,MATCH(Graphs!T$1,'Stats 2020'!$D$18:$J$18,0),0) | U41: =VLOOKUP($B41,'Stats 2020'!$D$25:$J$200,MATCH(Graphs!U$1,'Stats 2020'!$D$18:$J$18,0),0) -> 0 | V41: =VLOOKUP($B41,'Stats 2020'!$D$25:$J$200,MATCH(Graphs!V$1,'Stats 2020'!$D$18:$J$18,0),0) -> 1 | X41: =B41 -> 44127 | Y41: =SUM(Q$2:Q41)/COUNTA($P$2:$P41) -> 0.825 | Z41: =SUM(R$2:R41)/COUNTA($P$2:$P41) -> 0.1 | AA41: =SUM(S$2:S41)/COUNTA($P$2:$P41) -> 0.825 | AB41: =SUM(T$2:T41)/COUNTA($P$2:$P41) -> 0.3 | AC41: =SUM(U$2:U41)/COUNTA($P$2:$P41) -> 0.8 | AD41: =SUM(V$2:V41)/COUNTA($P$2:$P41) -> 0.9 | AE41: =AVERAGE(Y41:AD41) -> 0.625 | AF41: =VLOOKUP($A41,$X$1:$AE$59,MATCH(AF$1,$X$1:$AE$1,0),0) -> #N/A | AG41: =VLOOKUP($A41,$X$1:$AE$59,MATCH(AG$1,$X$1:$AE$1,0),0) -> #N/A | AH41: =VLOOKUP($A41,$X$1:$AE$59,MATCH(AH$1,$X$1:$AE$1,0),0) -> #N/A | AI41: =VLOOKUP($A41,$X$1:$AE$59,MATCH(AI$1,$X$1:$AE$1,0),0) -> #N/A | AJ41: =VLOOKUP($A41,$X$1:$AE$59,MATCH(AJ$1,$X$1:$AE$1,0),0) -> #N/A | AK41: =VLOOKUP($A41,$X$1:$AE$59,MATCH(AK$1,$X$1:$AE$1,0),0) -> #N/A | AL41: =VLOOKUP($A41,$X$1:$AE$59,MATCH(AL$1,$X$1:$AE$1,0),0) -> #N/A
A42: =IF(AND((TODAY()-B42)<7,(TODAY()-B42>=0)),B42,NA()) -> #N/A | B42: =B41+7 -> 44134 | C42: =IF($B42<=TODAY(),SUMIF('Stats 2020'!$M$24:$M$1048576,"<="&Graphs!$B42,'Stats 2020'!O$24:O$1048576),NA()) -> 154.5 | D42: =IF($B42<=TODAY(),MAX($C42,$E42,$G42,$H42)+11+16.5,NA()) -> 182 | E42: =IF($B42<=TODAY(),SUMIF('Stats 2020'!$M$24:$M$1048576,"<="&Graphs!$B42,'Stats 2020'!Q$24:Q$1048576),NA()) -> 116 | F42: =IF($B42<=TODAY(),MAX($C42,$E42,$G42,$H42)+11+16.5,NA()) -> 182 | G42: =IF($B42<=TODAY(),SUMIF('Stats 2020'!$M$24:$M$1048576,"<="&Graphs!$B42,'Stats 2020'!S$24:S$1048576),NA()) -> 132.5 | H42: =IF($B42<=TODAY(),SUMIF('Stats 2020'!$M$24:$M$1048576,"<="&Graphs!$B42,'Stats 2020'!T$24:T$1048576),NA()) -> 85.75 | I42: =VLOOKUP($A42,$B$1:$H$59,MATCH(I$1,$B$1:$H$1,0),0) -> #N/A | J42: =VLOOKUP($A42,$B$1:$H$59,MATCH(J$1,$B$1:$H$1,0),0) -> #N/A | K42: =VLOOKUP($A42,$B$1:$H$59,MATCH(K$1,$B$1:$H$1,0),0) -> #N/A | L42: =VLOOKUP($A42,$B$1:$H$59,MATCH(L$1,$B$1:$H$1,0),0) -> #N/A | M42: =VLOOKUP($A42,$B$1:$H$59,MATCH(M$1,$B$1:$H$1,0),0) -> #N/A | N42: =VLOOKUP($A42,$B$1:$H$59,MATCH(N$1,$B$1:$H$1,0),0) -> #N/A | P42: =B42 -> 44134 | Q42: =VLOOKUP($B42,'Stats 2020'!$D$25:$J$200,MATCH(Graphs!Q$1,'Stats 2020'!$D$18:$J$18,0),0) -> 1 | R42: =VLOOKUP($B42,'Stats 2020'!$D$25:$J$200,MATCH(Graphs!R$1,'Stats 2020'!$D$18:$J$18,0),0) -> 1 | S42: =VLOOKUP($B42,'Stats 2020'!$D$25:$J$200,MATCH(Graphs!S$1,'Stats 2020'!$D$18:$J$18,0),0) -> 1 | T42: =VLOOKUP($B42,'Stats 2020'!$D$25:$J$200,MATCH(Graphs!T$1,'Stats 2020'!$D$18:$J$18,0),0) -> 1 | U42: =VLOOKUP($B42,'Stats 2020'!$D$25:$J$200,MATCH(Graphs!U$1,'Stats 2020'!$D$18:$J$18,0),0) -> 1 | V42: =VLOOKUP($B42,'Stats 2020'!$D$25:$J$200,MATCH(Graphs!V$1,'Stats 2020'!$D$18:$J$18,0),0) -> 1 | X42: =B42 -> 44134 | Y42: =SUM(Q$2:Q42)/COUNTA($P$2:$P42) -> 0.82926829 | Z42: =SUM(R$2:R42)/COUNTA($P$2:$P42) -> 0.12195122 | AA42: =SUM(S$2:S42)/COUNTA($P$2:$P42) -> 0.82926829 | AB42: =SUM(T$2:T42)/COUNTA($P$2:$P42) -> 0.31707317 | AC42: =SUM(U$2:U42)/COUNTA($P$2:$P42) -> 0.80487805 | AD42: =SUM(V$2:V42)/COUNTA($P$2:$P42) -> 0.90243902 | AE42: =AVERAGE(Y42:AD42) -> 0.63414634 | AF42: =VLOOKUP($A42,$X$1:$AE$59,MATCH(AF$1,$X$1:$AE$1,0),0) -> #N/A | AG42: =VLOOKUP($A42,$X$1:$AE$59,MATCH(AG$1,$X$1:$AE$1,0),0) -> #N/A | AH42: =VLOOKUP($A42,$X$1:$AE$59,MATCH(AH$1,$X$1:$AE$1,0),0) -> #N/A | AI42: =VLOOKUP($A42,$X$1:$AE$59,MATCH(AI$1,$X$1:$AE$1,0),0) -> #N/A | AJ42: =VLOOKUP($A42,$X$1:$AE$59,MATCH(AJ$1,$X$1:$AE$1,0),0) -> #N/A | AK42: =VLOOKUP($A42,$X$1:$AE$59,MATCH(AK$1,$X$1:$AE$1,0),0) -> #N/A | AL42: =VLOOKUP($A42,$X$1:$AE$59,MATCH(AL$1,$X$1:$AE$1,0),0) -> #N/A
A43: =IF(AND((TODAY()-B43)<7,(TODAY()-B43>=0)),B43,NA()) -> #N/A | B43: =B42+7 -> 44141 | C43: =IF($B43<=TODAY(),SUMIF('Stats 2020'!$M$24:$M$1048576,"<="&Graphs!$B43,'Stats 2020'!O$24:O$1048576),NA()) -> 154.5 | D43: =IF($B43<=TODAY(),MAX($C43,$E43,$G43,$H43)+11+16.5,NA()) -> 182 | E43: =IF($B43<=TODAY(),SUMIF('Stats 2020'!$M$24:$M$1048576,"<="&Graphs!$B43,'Stats 2020'!Q$24:Q$1048576),NA()) -> 127 | F43: =IF($B43<=TODAY(),MAX($C43,$E43,$G43,$H43)+11+16.5,NA()) -> 182 | G43: =IF($B43<=TODAY(),SUMIF('Stats 2020'!$M$24:$M$1048576,"<="&Graphs!$B43,'Stats 2020'!S$24:S$1048576),NA()) -> 132.5 | H43: =IF($B43<=TODAY(),SUMIF('Stats 2020'!$M$24:$M$1048576,"<="&Graphs!$B43,'Stats 2020'!T$24:T$1048576),NA()) -> 85.75 | I43: =VLOOKUP($A43,$B$1:$H$59,MATCH(I$1,$B$1:$H$1,0),0) -> #N/A | J43: =VLOOKUP($A43,$B$1:$H$59,MATCH(J$1,$B$1:$H$1,0),0) -> #N/A | K43: =VLOOKUP($A43,$B$1:$H$59,MATCH(K$1,$B$1:$H$1,0),0) -> #N/A | L43: =VLOOKUP($A43,$B$1:$H$59,MATCH(L$1,$B$1:$H$1,0),0) -> #N/A | M43: =VLOOKUP($A43,$B$1:$H$59,MATCH(M$1,$B$1:$H$1,0),0) -> #N/A | N43: =VLOOKUP($A43,$B$1:$H$59,MATCH(N$1,$B$1:$H$1,0),0) -> #N/A | P43: =B43 -> 44141 | Q43: =VLOOKUP($B43,'Stats 2020'!$D$25:$J$200,MATCH(Graphs!Q$1,'Stats 2020'!$D$18:$J$18,0),0) -> 1 | R43: =VLOOKUP($B43,'Stats 2020'!$D$25:$J$200,MATCH(Graphs!R$1,'Stats 2020'!$D$18:$J$18,0),0) -> 1 | S43: =VLOOKUP($B43,'Stats 2020'!$D$25:$J$200,MATCH(Graphs!S$1,'Stats 2020'!$D$18:$J$18,0),0) -> 0 | T43: =VLOOKUP($B43,'Stats 2020'!$D$25:$J$200,MATCH(Graphs!T$1,'Stats 2020'!$D$18:$J$18,0),0) | U43: =VLOOKUP($B43,'Stats 2020'!$D$25:$J$200,MATCH(Graphs!U$1,'Stats 2020'!$D$18:$J$18,0),0) -> 1 | V43: =VLOOKUP($B43,'Stats 2020'!$D$25:$J$200,MATCH(Graphs!V$1,'Stats 2020'!$D$18:$J$18,0),0) -> 1 | X43: =B43 -> 44141 | Y43: =SUM(Q$2:Q43)/COUNTA($P$2:$P43) -> 0.83333333 | Z43: =SUM(R$2:R43)/COUNTA($P$2:$P43) -> 0.14285714 | AA43: =SUM(S$2:S43)/COUNTA($P$2:$P43) -> 0.80952381 | AB43: =SUM(T$2:T43)/COUNTA($P$2:$P43) -> 0.30952381 | AC43: =SUM(U$2:U43)/COUNTA($P$2:$P43) -> 0.80952381 | AD43: =SUM(V$2:V43)/COUNTA($P$2:$P43) -> 0.9047619 | AE43: =AVERAGE(Y43:AD43) -> 0.63492063 | AF43: =VLOOKUP($A43,$X$1:$AE$59,MATCH(AF$1,$X$1:$AE$1,0),0) -> #N/A | AG43: =VLOOKUP($A43,$X$1:$AE$59,MATCH(AG$1,$X$1:$AE$1,0),0) -> #N/A | AH43: =VLOOKUP($A43,$X$1:$AE$59,MATCH(AH$1,$X$1:$AE$1,0),0) -> #N/A | AI43: =VLOOKUP($A43,$X$1:$AE$59,MATCH(AI$1,$X$1:$AE$1,0),0) -> #N/A | AJ43: =VLOOKUP($A43,$X$1:$AE$59,MATCH(AJ$1,$X$1:$AE$1,0),0) -> #N/A | AK43: =VLOOKUP($A43,$X$1:$AE$59,MATCH(AK$1,$X$1:$AE$1,0),0) -> #N/A | AL43: =VLOOKUP($A43,$X$1:$AE$59,MATCH(AL$1,$X$1:$AE$1,0),0) -> #N/A
A44: =IF(AND((TODAY()-B44)<7,(TODAY()-B44>=0)),B44,NA()) -> #N/A | B44: =B43+7 -> 44148 | C44: =IF($B44<=TODAY(),SUMIF('Stats 2020'!$M$24:$M$1048576,"<="&Graphs!$B44,'Stats 2020'!O$24:O$1048576),NA()) -> 165.5 | D44: =IF($B44<=TODAY(),MAX($C44,$E44,$G44,$H44)+11+16.5,NA()) -> 193 | E44: =IF($B44<=TODAY(),SUMIF('Stats 2020'!$M$24:$M$1048576,"<="&Graphs!$B44,'Stats 2020'!Q$24:Q$1048576),NA()) -> 127 | F44: =IF($B44<=TODAY(),MAX($C44,$E44,$G44,$H44)+11+16.5,NA()) -> 193 | G44: =IF($B44<=TODAY(),SUMIF('Stats 2020'!$M$24:$M$1048576,"<="&Graphs!$B44,'Stats 2020'!S$24:S$1048576),NA()) -> 132.5 | H44: =IF($B44<=TODAY(),SUMIF('Stats 2020'!$M$24:$M$1048576,"<="&Graphs!$B44,'Stats 2020'!T$24:T$1048576),NA()) -> 85.75 | I44: =VLOOKUP($A44,$B$1:$H$59,MATCH(I$1,$B$1:$H$1,0),0) -> #N/A | J44: =VLOOKUP($A44,$B$1:$H$59,MATCH(J$1,$B$1:$H$1,0),0) -> #N/A | K44: =VLOOKUP($A44,$B$1:$H$59,MATCH(K$1,$B$1:$H$1,0),0) -> #N/A | L44: =VLOOKUP($A44,$B$1:$H$59,MATCH(L$1,$B$1:$H$1,0),0) -> #N/A | M44: =VLOOKUP($A44,$B$1:$H$59,MATCH(M$1,$B$1:$H$1,0),0) -> #N/A | N44: =VLOOKUP($A44,$B$1:$H$59,MATCH(N$1,$B$1:$H$1,0),0) -> #N/A | P44: =B44 -> 44148 | Q44: =VLOOKUP($B44,'Stats 2020'!$D$25:$J$200,MATCH(Graphs!Q$1,'Stats 2020'!$D$18:$J$18,0),0) -> 0 | R44: =VLOOKUP($B44,'Stats 2020'!$D$25:$J$200,MATCH(Graphs!R$1,'Stats 2020'!$D$18:$J$18,0),0) -> 1 | S44: =VLOOKUP($B44,'Stats 2020'!$D$25:$J$200,MATCH(Graphs!S$1,'Stats 2020'!$D$18:$J$18,0),0) -> 1 | T44: =VLOOKUP($B44,'Stats 2020'!$D$25:$J$200,MATCH(Graphs!T$1,'Stats 2020'!$D$18:$J$18,0),0) | U44: =VLOOKUP($B44,'Stats 2020'!$D$25:$J$200,MATCH(Graphs!U$1,'Stats 2020'!$D$18:$J$18,0),0) -> 1 | V44: =VLOOKUP($B44,'Stats 2020'!$D$25:$J$200,MATCH(Graphs!V$1,'Stats 2020'!$D$18:$J$18,0),0) -> 1 | X44: =B44 -> 44148 | Y44: =SUM(Q$2:Q44)/COUNTA($P$2:$P44) -> 0.81395349 | Z44: =SUM(R$2:R44)/COUNTA($P$2:$P44) -> 0.1627907 | AA44: =SUM(S$2:S44)/COUNTA($P$2:$P44) -> 0.81395349 | AB44: =SUM(T$2:T44)/COUNTA($P$2:$P44) -> 0.30232558 | AC44: =SUM(U$2:U44)/COUNTA($P$2:$P44) -> 0.81395349 | AD44: =SUM(V$2:V44)/COUNTA($P$2:$P44) -> 0.90697674 | AE44: =AVERAGE(Y44:AD44) -> 0.63565891 | AF44: =VLOOKUP($A44,$X$1:$AE$59,MATCH(AF$1,$X$1:$AE$1,0),0) -> #N/A | AG44: =VLOOKUP($A44,$X$1:$AE$59,MATCH(AG$1,$X$1:$AE$1,0),0) -> #N/A | AH44: =VLOOKUP($A44,$X$1:$AE$59,MATCH(AH$1,$X$1:$AE$1,0),0) -> #N/A | AI44: =VLOOKUP($A44,$X$1:$AE$59,MATCH(AI$1,$X$1:$AE$1,0),0) -> #N/A | AJ44: =VLOOKUP($A44,$X$1:$AE$59,MATCH(AJ$1,$X$1:$AE$1,0),0) -> #N/A | AK44: =VLOOKUP($A44,$X$1:$AE$59,MATCH(AK$1,$X$1:$AE$1,0),0) -> #N/A | AL44: =VLOOKUP($A44,$X$1:$AE$59,MATCH(AL$1,$X$1:$AE$1,0),0) -> #N/A
A45: =IF(AND((TODAY()-B45)<7,(TODAY()-B45>=0)),B45,NA()) -> #N/A | B45: =B44+7 -> 44155 | C45: =IF($B45<=TODAY(),SUMIF('Stats 2020'!$M$24:$M$1048576,"<="&Graphs!$B45,'Stats 2020'!O$24:O$1048576),NA()) -> 165.5 | D45: =IF($B45<=TODAY(),MAX($C45,$E45,$G45,$H45)+11+16.5,NA()) -> 193 | E45: =IF($B45<=TODAY(),SUMIF('Stats 2020'!$M$24:$M$1048576,"<="&Graphs!$B45,'Stats 2020'!Q$24:Q$1048576),NA()) -> 127 | F45: =IF($B45<=TODAY(),MAX($C45,$E45,$G45,$H45)+11+16.5,NA()) -> 193 | G45: =IF($B45<=TODAY(),SUMIF('Stats 2020'!$M$24:$M$1048576,"<="&Graphs!$B45,'Stats 2020'!S$24:S$1048576),NA()) -> 132.5 | H45: =IF($B45<=TODAY(),SUMIF('Stats 2020'!$M$24:$M$1048576,"<="&Graphs!$B45,'Stats 2020'!T$24:T$1048576),NA()) -> 85.75 | I45: =VLOOKUP($A45,$B$1:$H$59,MATCH(I$1,$B$1:$H$1,0),0) -> #N/A | J45: =VLOOKUP($A45,$B$1:$H$59,MATCH(J$1,$B$1:$H$1,0),0) -> #N/A | K45: =VLOOKUP($A45,$B$1:$H$59,MATCH(K$1,$B$1:$H$1,0),0) -> #N/A | L45: =VLOOKUP($A45,$B$1:$H$59,MATCH(L$1,$B$1:$H$1,0),0) -> #N/A | M45: =VLOOKUP($A45,$B$1:$H$59,MATCH(M$1,$B$1:$H$1,0),0) -> #N/A | N45: =VLOOKUP($A45,$B$1:$H$59,MATCH(N$1,$B$1:$H$1,0),0) -> #N/A | P45: =B45 -> 44155 | Q45: =VLOOKUP($B45,'Stats 2020'!$D$25:$J$200,MATCH(Graphs!Q$1,'Stats 2020'!$D$18:$J$18,0),0) -> 1 | R45: =VLOOKUP($B45,'Stats 2020'!$D$25:$J$200,MATCH(Graphs!R$1,'Stats 2020'!$D$18:$J$18,0),0) -> 1 | S45: =VLOOKUP($B45,'Stats 2020'!$D$25:$J$200,MATCH(Graphs!S$1,'Stats 2020'!$D$18:$J$18,0),0) -> 1 | T45: =VLOOKUP($B45,'Stats 2020'!$D$25:$J$200,MATCH(Graphs!T$1,'Stats 2020'!$D$18:$J$18,0),0) -> 1 | U45: =VLOOKUP($B45,'Stats 2020'!$D$25:$J$200,MATCH(Graphs!U$1,'Stats 2020'!$D$18:$J$18,0),0) -> 1 | V45: =VLOOKUP($B45,'Stats 2020'!$D$25:$J$200,MATCH(Graphs!V$1,'Stats 2020'!$D$18:$J$18,0),0) -> 1 | X45: =B45 -> 44155 | Y45: =SUM(Q$2:Q45)/COUNTA($P$2:$P45) -> 0.81818182 | Z45: =SUM(R$2:R45)/COUNTA($P$2:$P45) -> 0.18181818 | AA45: =SUM(S$2:S45)/COUNTA($P$2:$P45) -> 0.81818182 | AB45: =SUM(T$2:T45)/COUNTA($P$2:$P45) -> 0.31818182 | AC45: =SUM(U$2:U45)/COUNTA($P$2:$P45) -> 0.81818182 | AD45: =SUM(V$2:V45)/COUNTA($P$2:$P45) -> 0.90909091 | AE45: =AVERAGE(Y45:AD45) -> 0.64393939 | AF45: =VLOOKUP($A45,$X$1:$AE$59,MATCH(AF$1,$X$1:$AE$1,0),0) -> #N/A | AG45: =VLOOKUP($A45,$X$1:$AE$59,MATCH(AG$1,$X$1:$AE$1,0),0) -> #N/A | AH45: =VLOOKUP($A45,$X$1:$AE$59,MATCH(AH$1,$X$1:$AE$1,0),0) -> #N/A | AI45: =VLOOKUP($A45,$X$1:$AE$59,MATCH(AI$1,$X$1:$AE$1,0),0) -> #N/A | AJ45: =VLOOKUP($A45,$X$1:$AE$59,MATCH(AJ$1,$X$1:$AE$1,0),0) -> #N/A | AK45: =VLOOKUP($A45,$X$1:$AE$59,MATCH(AK$1,$X$1:$AE$1,0),0) -> #N/A | AL45: =VLOOKUP($A45,$X$1:$AE$59,MATCH(AL$1,$X$1:$AE$1,0),0) -> #N/A
A46: =IF(AND((TODAY()-B46)<7,(TODAY()-B46>=0)),B46,NA()) -> #N/A | B46: =B45+7 -> 44162 | C46: =IF($B46<=TODAY(),SUMIF('Stats 2020'!$M$24:$M$1048576,"<="&Graphs!$B46,'Stats 2020'!O$24:O$1048576),NA()) -> 165.5 | D46: =IF($B46<=TODAY(),MAX($C46,$E46,$G46,$H46)+11+16.5,NA()) -> 193 | E46: =IF($B46<=TODAY(),SUMIF('Stats 2020'!$M$24:$M$1048576,"<="&Graphs!$B46,'Stats 2020'!Q$24:Q$1048576),NA()) -> 127 | F46: =IF($B46<=TODAY(),MAX($C46,$E46,$G46,$H46)+11+16.5,NA()) -> 193 | G46: =IF($B46<=TODAY(),SUMIF('Stats 2020'!$M$24:$M$1048576,"<="&Graphs!$B46,'Stats 2020'!S$24:S$1048576),NA()) -> 132.5 | H46: =IF($B46<=TODAY(),SUMIF('Stats 2020'!$M$24:$M$1048576,"<="&Graphs!$B46,'Stats 2020'!T$24:T$1048576),NA()) -> 85.75 | I46: =VLOOKUP($A46,$B$1:$H$59,MATCH(I$1,$B$1:$H$1,0),0) -> #N/A | J46: =VLOOKUP($A46,$B$1:$H$59,MATCH(J$1,$B$1:$H$1,0),0) -> #N/A | K46: =VLOOKUP($A46,$B$1:$H$59,MATCH(K$1,$B$1:$H$1,0),0) -> #N/A | L46: =VLOOKUP($A46,$B$1:$H$59,MATCH(L$1,$B$1:$H$1,0),0) -> #N/A | M46: =VLOOKUP($A46,$B$1:$H$59,MATCH(M$1,$B$1:$H$1,0),0) -> #N/A | N46: =VLOOKUP($A46,$B$1:$H$59,MATCH(N$1,$B$1:$H$1,0),0) -> #N/A | P46: =B46 -> 44162 | Q46: =VLOOKUP($B46,'Stats 2020'!$D$25:$J$200,MATCH(Graphs!Q$1,'Stats 2020'!$D$18:$J$18,0),0) -> 1 | R46: =VLOOKUP($B46,'Stats 2020'!$D$25:$J$200,MATCH(Graphs!R$1,'Stats 2020'!$D$18:$J$18,0),0) | S46: =VLOOKUP($B46,'Stats 2020'!$D$25:$J$200,MATCH(Graphs!S$1,'Stats 2020'!$D$18:$J$18,0),0) -> 1 | T46: =VLOOKUP($B46,'Stats 2020'!$D$25:$J$200,MATCH(Graphs!T$1,'Stats 2020'!$D$18:$J$18,0),0) -> 1 | U46: =VLOOKUP($B46,'Stats 2020'!$D$25:$J$200,MATCH(Graphs!U$1,'Stats 2020'!$D$18:$J$18,0),0) -> 1 | V46: =VLOOKUP($B46,'Stats 2020'!$D$25:$J$200,MATCH(Graphs!V$1,'Stats 2020'!$D$18:$J$18,0),0) -> 1 | X46: =B46 -> 44162 | Y46: =SUM(Q$2:Q46)/COUNTA($P$2:$P46) -> 0.82222222 | Z46: =SUM(R$2:R46)/COUNTA($P$2:$P46) -> 0.17777778 | AA46: =SUM(S$2:S46)/COUNTA($P$2:$P46) -> 0.82222222 | AB46: =SUM(T$2:T46)/COUNTA($P$2:$P46) -> 0.33333333 | AC46: =SUM(U$2:U46)/COUNTA($P$2:$P46) -> 0.82222222 | AD46: =SUM(V$2:V46)/COUNTA($P$2:$P46) -> 0.91111111 | AE46: =AVERAGE(Y46:AD46) -> 0.64814815 | AF46: =VLOOKUP($A46,$X$1:$AE$59,MATCH(AF$1,$X$1:$AE$1,0),0) -> #N/A | AG46: =VLOOKUP($A46,$X$1:$AE$59,MATCH(AG$1,$X$1:$AE$1,0),0) -> #N/A | AH46: =VLOOKUP($A46,$X$1:$AE$59,MATCH(AH$1,$X$1:$AE$1,0),0) -> #N/A | AI46: =VLOOKUP($A46,$X$1:$AE$59,MATCH(AI$1,$X$1:$AE$1,0),0) -> #N/A | AJ46: =VLOOKUP($A46,$X$1:$AE$59,MATCH(AJ$1,$X$1:$AE$1,0),0) -> #N/A | AK46: =VLOOKUP($A46,$X$1:$AE$59,MATCH(AK$1,$X$1:$AE$1,0),0) -> #N/A | AL46: =VLOOKUP($A46,$X$1:$AE$59,MATCH(AL$1,$X$1:$AE$1,0),0) -> #N/A
A47: =IF(AND((TODAY()-B47)<7,(TODAY()-B47>=0)),B47,NA()) -> #N/A | B47: =B46+7 -> 44169 | C47: =IF($B47<=TODAY(),SUMIF('Stats 2020'!$M$24:$M$1048576,"<="&Graphs!$B47,'Stats 2020'!O$24:O$1048576),NA()) -> 176.5 | D47: =IF($B47<=TODAY(),MAX($C47,$E47,$G47,$H47)+11+16.5,NA()) -> 204 | E47: =IF($B47<=TODAY(),SUMIF('Stats 2020'!$M$24:$M$1048576,"<="&Graphs!$B47,'Stats 2020'!Q$24:Q$1048576),NA()) -> 127 | F47: =IF($B47<=TODAY(),MAX($C47,$E47,$G47,$H47)+11+16.5,NA()) -> 204 | G47: =IF($B47<=TODAY(),SUMIF('Stats 2020'!$M$24:$M$1048576,"<="&Graphs!$B47,'Stats 2020'!S$24:S$1048576),NA()) -> 132.5 | H47: =IF($B47<=TODAY(),SUMIF('Stats 2020'!$M$24:$M$1048576,"<="&Graphs!$B47,'Stats 2020'!T$24:T$1048576),NA()) -> 85.75 | I47: =VLOOKUP($A47,$B$1:$H$59,MATCH(I$1,$B$1:$H$1,0),0) -> #N/A | J47: =VLOOKUP($A47,$B$1:$H$59,MATCH(J$1,$B$1:$H$1,0),0) -> #N/A | K47: =VLOOKUP($A47,$B$1:$H$59,MATCH(K$1,$B$1:$H$1,0),0) -> #N/A | L47: =VLOOKUP($A47,$B$1:$H$59,MATCH(L$1,$B$1:$H$1,0),0) -> #N/A | M47: =VLOOKUP($A47,$B$1:$H$59,MATCH(M$1,$B$1:$H$1,0),0) -> #N/A | N47: =VLOOKUP($A47,$B$1:$H$59,MATCH(N$1,$B$1:$H$1,0),0) -> #N/A | P47: =B47 -> 44169 | Q47: =VLOOKUP($B47,'Stats 2020'!$D$25:$J$200,MATCH(Graphs!Q$1,'Stats 2020'!$D$18:$J$18,0),0) -> 0 | R47: =VLOOKUP($B47,'Stats 2020'!$D$25:$J$200,MATCH(Graphs!R$1,'Stats 2020'!$D$18:$J$18,0),0) -> 1 | S47: =VLOOKUP($B47,'Stats 2020'!$D$25:$J$200,MATCH(Graphs!S$1,'Stats 2020'!$D$18:$J$18,0),0) -> 1 | T47: =VLOOKUP($B47,'Stats 2020'!$D$25:$J$200,MATCH(Graphs!T$1,'Stats 2020'!$D$18:$J$18,0),0) | U47: =VLOOKUP($B47,'Stats 2020'!$D$25:$J$200,MATCH(Graphs!U$1,'Stats 2020'!$D$18:$J$18,0),0) -> 1 | V47: =VLOOKUP($B47,'Stats 2020'!$D$25:$J$200,MATCH(Graphs!V$1,'Stats 2020'!$D$18:$J$18,0),0) -> 1 | X47: =B47 -> 44169 | Y47: =SUM(Q$2:Q47)/COUNTA($P$2:$P47) -> 0.80434783 | Z47: =SUM(R$2:R47)/COUNTA($P$2:$P47) -> 0.19565217 | AA47: =SUM(S$2:S47)/COUNTA($P$2:$P47) -> 0.82608696 | AB47: =SUM(T$2:T47)/COUNTA($P$2:$P47) -> 0.32608696 | AC47: =SUM(U$2:U47)/COUNTA($P$2:$P47) -> 0.82608696 | AD47: =SUM(V$2:V47)/COUNTA($P$2:$P47) -> 0.91304348 | AE47: =AVERAGE(Y47:AD47) -> 0.64855072 | AF47: =VLOOKUP($A47,$X$1:$AE$59,MATCH(AF$1,$X$1:$AE$1,0),0) -> #N/A | AG47: =VLOOKUP($A47,$X$1:$AE$59,MATCH(AG$1,$X$1:$AE$1,0),0) -> #N/A | AH47: =VLOOKUP($A47,$X$1:$AE$59,MATCH(AH$1,$X$1:$AE$1,0),0) -> #N/A | AI47: =VLOOKUP($A47,$X$1:$AE$59,MATCH(AI$1,$X$1:$AE$1,0),0) -> #N/A | AJ47: =VLOOKUP($A47,$X$1:$AE$59,MATCH(AJ$1,$X$1:$AE$1,0),0) -> #N/A | AK47: =VLOOKUP($A47,$X$1:$AE$59,MATCH(AK$1,$X$1:$AE$1,0),0) -> #N/A | AL47: =VLOOKUP($A47,$X$1:$AE$59,MATCH(AL$1,$X$1:$AE$1,0),0) -> #N/A
A48: =IF(AND((TODAY()-B48)<7,(TODAY()-B48>=0)),B48,NA()) -> #N/A | B48: =B47+7 -> 44176 | C48: =IF($B48<=TODAY(),SUMIF('Stats 2020'!$M$24:$M$1048576,"<="&Graphs!$B48,'Stats 2020'!O$24:O$1048576),NA()) -> 179.25 | D48: =IF($B48<=TODAY(),MAX($C48,$E48,$G48,$H48)+11+16.5,NA()) -> 206.75 | E48: =IF($B48<=TODAY(),SUMIF('Stats 2020'!$M$24:$M$1048576,"<="&Graphs!$B48,'Stats 2020'!Q$24:Q$1048576),NA()) -> 127 | F48: =IF($B48<=TODAY(),MAX($C48,$E48,$G48,$H48)+11+16.5,NA()) -> 206.75 | G48: =IF($B48<=TODAY(),SUMIF('Stats 2020'!$M$24:$M$1048576,"<="&Graphs!$B48,'Stats 2020'!S$24:S$1048576),NA()) -> 132.5 | H48: =IF($B48<=TODAY(),SUMIF('Stats 2020'!$M$24:$M$1048576,"<="&Graphs!$B48,'Stats 2020'!T$24:T$1048576),NA()) -> 85.75 | I48: =VLOOKUP($A48,$B$1:$H$59,MATCH(I$1,$B$1:$H$1,0),0) -> #N/A | J48: =VLOOKUP($A48,$B$1:$H$59,MATCH(J$1,$B$1:$H$1,0),0) -> #N/A | K48: =VLOOKUP($A48,$B$1:$H$59,MATCH(K$1,$B$1:$H$1,0),0) -> #N/A | L48: =VLOOKUP($A48,$B$1:$H$59,MATCH(L$1,$B$1:$H$1,0),0) -> #N/A | M48: =VLOOKUP($A48,$B$1:$H$59,MATCH(M$1,$B$1:$H$1,0),0) -> #N/A | N48: =VLOOKUP($A48,$B$1:$H$59,MATCH(N$1,$B$1:$H$1,0),0) -> #N/A | P48: =B48 -> 44176 | Q48: =VLOOKUP($B48,'Stats 2020'!$D$25:$J$200,MATCH(Graphs!Q$1,'Stats 2020'!$D$18:$J$18,0),0) -> 1 | R48: =VLOOKUP($B48,'Stats 2020'!$D$25:$J$200,MATCH(Graphs!R$1,'Stats 2020'!$D$18:$J$18,0),0) -> 1 | S48: =VLOOKUP($B48,'Stats 2020'!$D$25:$J$200,MATCH(Graphs!S$1,'Stats 2020'!$D$18:$J$18,0),0) -> 1 | T48: =VLOOKUP($B48,'Stats 2020'!$D$25:$J$200,MATCH(Graphs!T$1,'Stats 2020'!$D$18:$J$18,0),0) | U48: =VLOOKUP($B48,'Stats 2020'!$D$25:$J$200,MATCH(Graphs!U$1,'Stats 2020'!$D$18:$J$18,0),0) -> 1 | V48: =VLOOKUP($B48,'Stats 2020'!$D$25:$J$200,MATCH(Graphs!V$1,'Stats 2020'!$D$18:$J$18,0),0) -> 1 | X48: =B48 -> 44176 | Y48: =SUM(Q$2:Q48)/COUNTA($P$2:$P48) -> 0.80851064 | Z48: =SUM(R$2:R48)/COUNTA($P$2:$P48) -> 0.21276596 | AA48: =SUM(S$2:S48)/COUNTA($P$2:$P48) -> 0.82978723 | AB48: =SUM(T$2:T48)/COUNTA($P$2:$P48) -> 0.31914894 | AC48: =SUM(U$2:U48)/COUNTA($P$2:$P48) -> 0.82978723 | AD48: =SUM(V$2:V48)/COUNTA($P$2:$P48) -> 0.91489362 | AE48: =AVERAGE(Y48:AD48) -> 0.65248227 | AF48: =VLOOKUP($A48,$X$1:$AE$59,MATCH(AF$1,$X$1:$AE$1,0),0) -> #N/A | AG48: =VLOOKUP($A48,$X$1:$AE$59,MATCH(AG$1,$X$1:$AE$1,0),0) -> #N/A | AH48: =VLOOKUP($A48,$X$1:$AE$59,MATCH(AH$1,$X$1:$AE$1,0),0) -> #N/A | AI48: =VLOOKUP($A48,$X$1:$AE$59,MATCH(AI$1,$X$1:$AE$1,0),0) -> #N/A | AJ48: =VLOOKUP($A48,$X$1:$AE$59,MATCH(AJ$1,$X$1:$AE$1,0),0) -> #N/A | AK48: =VLOOKUP($A48,$X$1:$AE$59,MATCH(AK$1,$X$1:$AE$1,0),0) -> #N/A | AL48: =VLOOKUP($A48,$X$1:$AE$59,MATCH(AL$1,$X$1:$AE$1,0),0) -> #N/A
A49: =IF(AND((TODAY()-B49)<7,(TODAY()-B49>=0)),B49,NA()) -> #N/A | B49: =B48+7 -> 44183 | C49: =IF($B49<=TODAY(),SUMIF('Stats 2020'!$M$24:$M$1048576,"<="&Graphs!$B49,'Stats 2020'!O$24:O$1048576),NA()) -> 179.25 | D49: =IF($B49<=TODAY(),MAX($C49,$E49,$G49,$H49)+11+16.5,NA()) -> 206.75 | E49: =IF($B49<=TODAY(),SUMIF('Stats 2020'!$M$24:$M$1048576,"<="&Graphs!$B49,'Stats 2020'!Q$24:Q$1048576),NA()) -> 138 | F49: =IF($B49<=TODAY(),MAX($C49,$E49,$G49,$H49)+11+16.5,NA()) -> 206.75 | G49: =IF($B49<=TODAY(),SUMIF('Stats 2020'!$M$24:$M$1048576,"<="&Graphs!$B49,'Stats 2020'!S$24:S$1048576),NA()) -> 143.5 | H49: =IF($B49<=TODAY(),SUMIF('Stats 2020'!$M$24:$M$1048576,"<="&Graphs!$B49,'Stats 2020'!T$24:T$1048576),NA()) -> 85.75 | I49: =VLOOKUP($A49,$B$1:$H$59,MATCH(I$1,$B$1:$H$1,0),0) -> #N/A | J49: =VLOOKUP($A49,$B$1:$H$59,MATCH(J$1,$B$1:$H$1,0),0) -> #N/A | K49: =VLOOKUP($A49,$B$1:$H$59,MATCH(K$1,$B$1:$H$1,0),0) -> #N/A | L49: =VLOOKUP($A49,$B$1:$H$59,MATCH(L$1,$B$1:$H$1,0),0) -> #N/A | M49: =VLOOKUP($A49,$B$1:$H$59,MATCH(M$1,$B$1:$H$1,0),0) -> #N/A | N49: =VLOOKUP($A49,$B$1:$H$59,MATCH(N$1,$B$1:$H$1,0),0) -> #N/A | P49: =B49 -> 44183 | Q49: =VLOOKUP($B49,'Stats 2020'!$D$25:$J$200,MATCH(Graphs!Q$1,'Stats 2020'!$D$18:$J$18,0),0) -> 1 | R49: =VLOOKUP($B49,'Stats 2020'!$D$25:$J$200,MATCH(Graphs!R$1,'Stats 2020'!$D$18:$J$18,0),0) -> 1 | S49: =VLOOKUP($B49,'Stats 2020'!$D$25:$J$200,MATCH(Graphs!S$1,'Stats 2020'!$D$18:$J$18,0),0) -> 0 | T49: =VLOOKUP($B49,'Stats 2020'!$D$25:$J$200,MATCH(Graphs!T$1,'Stats 2020'!$D$18:$J$18,0),0) -> 1 | U49: =VLOOKUP($B49,'Stats 2020'!$D$25:$J$200,MATCH(Graphs!U$1,'Stats 2020'!$D$18:$J$18,0),0) -> 0 | V49: =VLOOKUP($B49,'Stats 2020'!$D$25:$J$200,MATCH(Graphs!V$1,'Stats 2020'!$D$18:$J$18,0),0) -> 1 | X49: =B49 -> 44183 | Y49: =SUM(Q$2:Q48)/COUNTA($P$2:$P48) -> 0.80851064 | Z49: =SUM(R$2:R48)/COUNTA($P$2:$P48) -> 0.21276596 | AA49: =SUM(S$2:S48)/COUNTA($P$2:$P48) -> 0.82978723 | AB49: =SUM(T$2:T48)/COUNTA($P$2:$P48) -> 0.31914894 | AC49: =SUM(U$2:U48)/COUNTA($P$2:$P48) -> 0.82978723 | AD49: =SUM(V$2:V48)/COUNTA($P$2:$P48) -> 0.91489362 | AE49: =AVERAGE(Y49:AD49) -> 0.65248227 | AF49: =VLOOKUP($A49,$X$1:$AE$59,MATCH(AF$1,$X$1:$AE$1,0),0) -> #N/A | AG49: =VLOOKUP($A49,$X$1:$AE$59,MATCH(AG$1,$X$1:$AE$1,0),0) -> #N/A | AH49: =VLOOKUP($A49,$X$1:$AE$59,MATCH(AH$1,$X$1:$AE$1,0),0) -> #N/A | AI49: =VLOOKUP($A49,$X$1:$AE$59,MATCH(AI$1,$X$1:$AE$1,0),0) -> #N/A | AJ49: =VLOOKUP($A49,$X$1:$AE$59,MATCH(AJ$1,$X$1:$AE$1,0),0) -> #N/A | AK49: =VLOOKUP($A49,$X$1:$AE$59,MATCH(AK$1,$X$1:$AE$1,0),0) -> #N/A | AL49: =VLOOKUP($A49,$X$1:$AE$59,MATCH(AL$1,$X$1:$AE$1,0),0) -> #N/A
A50: =IF(AND((TODAY()-B50)<7,(TODAY()-B50>=0)),B50,NA()) -> #N/A | B50: =B49+7 -> 44190 | C50: =IF($B50<=TODAY(),SUMIF('Stats 2020'!$M$24:$M$1048576,"<="&Graphs!$B50,'Stats 2020'!O$24:O$1048576),NA()) -> 179.25 | D50: =IF($B50<=TODAY(),MAX($C50,$E50,$G50,$H50)+11+16.5,NA()) -> 206.75 | E50: =IF($B50<=TODAY(),SUMIF('Stats 2020'!$M$24:$M$1048576,"<="&Graphs!$B50,'Stats 2020'!Q$24:Q$1048576),NA()) -> 138 | F50: =IF($B50<=TODAY(),MAX($C50,$E50,$G50,$H50)+11+16.5,NA()) -> 206.75 | G50: =IF($B50<=TODAY(),SUMIF('Stats 2020'!$M$24:$M$1048576,"<="&Graphs!$B50,'Stats 2020'!S$24:S$1048576),NA()) -> 143.5 | H50: =IF($B50<=TODAY(),SUMIF('Stats 2020'!$M$24:$M$1048576,"<="&Graphs!$B50,'Stats 2020'!T$24:T$1048576),NA()) -> 85.75 | I50: =VLOOKUP($A50,$B$1:$H$59,MATCH(I$1,$B$1:$H$1,0),0) -> #N/A | J50: =VLOOKUP($A50,$B$1:$H$59,MATCH(J$1,$B$1:$H$1,0),0) -> #N/A | K50: =VLOOKUP($A50,$B$1:$H$59,MATCH(K$1,$B$1:$H$1,0),0) -> #N/A | L50: =VLOOKUP($A50,$B$1:$H$59,MATCH(L$1,$B$1:$H$1,0),0) -> #N/A | M50: =VLOOKUP($A50,$B$1:$H$59,MATCH(M$1,$B$1:$H$1,0),0) -> #N/A | N50: =VLOOKUP($A50,$B$1:$H$59,MATCH(N$1,$B$1:$H$1,0),0) -> #N/A | P50: =B50 -> 44190 | X50: =B50 -> 44190 | Y50: =SUM(Q$2:Q50)/COUNTA($P$2:$P50) -> 0.79591837 | Z50: =SUM(R$2:R50)/COUNTA($P$2:$P50) -> 0.2244898 | AA50: =SUM(S$2:S50)/COUNTA($P$2:$P50) -> 0.79591837 | AB50: =SUM(T$2:T50)/COUNTA($P$2:$P50) -> 0.32653061 | AC50: =SUM(U$2:U50)/COUNTA($P$2:$P50) -> 0.79591837 | AD50: =SUM(V$2:V50)/COUNTA($P$2:$P50) -> 0.89795918 | AE50: =AVERAGE(Y50:AD50) -> 0.63945578 | AF50: =VLOOKUP($A50,$X$1:$AE$59,MATCH(AF$1,$X$1:$AE$1,0),0) -> #N/A | AG50: =VLOOKUP($A50,$X$1:$AE$59,MATCH(AG$1,$X$1:$AE$1,0),0) -> #N/A | AH50: =VLOOKUP($A50,$X$1:$AE$59,MATCH(AH$1,$X$1:$AE$1,0),0) -> #N/A | AI50: =VLOOKUP($A50,$X$1:$AE$59,MATCH(AI$1,$X$1:$AE$1,0),0) -> #N/A | AJ50: =VLOOKUP($A50,$X$1:$AE$59,MATCH(AJ$1,$X$1:$AE$1,0),0) -> #N/A | AK50: =VLOOKUP($A50,$X$1:$AE$59,MATCH(AK$1,$X$1:$AE$1,0),0) -> #N/A | AL50: =VLOOKUP($A50,$X$1:$AE$59,MATCH(AL$1,$X$1:$AE$1,0),0) -> #N/A
A51: =IF(AND((TODAY()-B51)<7,(TODAY()-B51>=0)),B51,NA()) -> #N/A | B51: =B50+7 -> 44197 | C51: =IF($B51<=TODAY(),SUMIF('Stats 2020'!$M$24:$M$1048576,"<="&Graphs!$B51,'Stats 2020'!O$24:O$1048576),NA()) -> 179.25 | D51: =IF($B51<=TODAY(),MAX($C51,$E51,$G51,$H51)+11+16.5,NA()) -> 206.75 | E51: =IF($B51<=TODAY(),SUMIF('Stats 2020'!$M$24:$M$1048576,"<="&Graphs!$B51,'Stats 2020'!Q$24:Q$1048576),NA()) -> 138 | F51: =IF($B51<=TODAY(),MAX($C51,$E51,$G51,$H51)+11+16.5,NA()) -> 206.75 | G51: =IF($B51<=TODAY(),SUMIF('Stats 2020'!$M$24:$M$1048576,"<="&Graphs!$B51,'Stats 2020'!S$24:S$1048576),NA()) -> 143.5 | H51: =IF($B51<=TODAY(),SUMIF('Stats 2020'!$M$24:$M$1048576,"<="&Graphs!$B51,'Stats 2020'!T$24:T$1048576),NA()) -> 85.75 | I51: =VLOOKUP($A51,$B$1:$H$59,MATCH(I$1,$B$1:$H$1,0),0) -> #N/A | J51: =VLOOKUP($A51,$B$1:$H$59,MATCH(J$1,$B$1:$H$1,0),0) -> #N/A | K51: =VLOOKUP($A51,$B$1:$H$59,MATCH(K$1,$B$1:$H$1,0),0) -> #N/A | L51: =VLOOKUP($A51,$B$1:$H$59,MATCH(L$1,$B$1:$H$1,0),0) -> #N/A | M51: =VLOOKUP($A51,$B$1:$H$59,MATCH(M$1,$B$1:$H$1,0),0) -> #N/A | N51: =VLOOKUP($A51,$B$1:$H$59,MATCH(N$1,$B$1:$H$1,0),0) -> #N/A | P51: =B51 -> 44197 | X51: =B51 -> 44197 | Y51: =SUM(Q$2:Q50)/COUNTA($P$2:$P50) -> 0.79591837 | Z51: =SUM(R$2:R50)/COUNTA($P$2:$P50) -> 0.2244898 | AA51: =SUM(S$2:S50)/COUNTA($P$2:$P50) -> 0.79591837 | AB51: =SUM(T$2:T50)/COUNTA($P$2:$P50) -> 0.32653061 | AC51: =SUM(U$2:U50)/COUNTA($P$2:$P50) -> 0.79591837 | AD51: =SUM(V$2:V50)/COUNTA($P$2:$P50) -> 0.89795918 | AE51: =AVERAGE(Y51:AD51) -> 0.63945578 | AF51: =VLOOKUP($A51,$X$1:$AE$59,MATCH(AF$1,$X$1:$AE$1,0),0) -> #N/A | AG51: =VLOOKUP($A51,$X$1:$AE$59,MATCH(AG$1,$X$1:$AE$1,0),0) -> #N/A | AH51: =VLOOKUP($A51,$X$1:$AE$59,MATCH(AH$1,$X$1:$AE$1,0),0) -> #N/A | AI51: =VLOOKUP($A51,$X$1:$AE$59,MATCH(AI$1,$X$1:$AE$1,0),0) -> #N/A | AJ51: =VLOOKUP($A51,$X$1:$AE$59,MATCH(AJ$1,$X$1:$AE$1,0),0) -> #N/A | AK51: =VLOOKUP($A51,$X$1:$AE$59,MATCH(AK$1,$X$1:$AE$1,0),0) -> #N/A | AL51: =VLOOKUP($A51,$X$1:$AE$59,MATCH(AL$1,$X$1:$AE$1,0),0) -> #N/A
A52: =IF(AND((TODAY()-B52)<7,(TODAY()-B52>=0)),B52,NA()) -> #N/A | B52: =B51+7 -> 44204 | C52: =IF($B52<=TODAY(),SUMIF('Stats 2020'!$M$24:$M$1048576,"<="&Graphs!$B52,'Stats 2020'!O$24:O$1048576),NA()) -> 179.25 | D52: =IF($B52<=TODAY(),MAX($C52,$E52,$G52,$H52)+11+16.5,NA()) -> 206.75 | E52: =IF($B52<=TODAY(),SUMIF('Stats 2020'!$M$24:$M$1048576,"<="&Graphs!$B52,'Stats 2020'!Q$24:Q$1048576),NA()) -> 149 | F52: =IF($B52<=TODAY(),MAX($C52,$E52,$G52,$H52)+11+16.5,NA()) -> 206.75 | G52: =IF($B52<=TODAY(),SUMIF('Stats 2020'!$M$24:$M$1048576,"<="&Graphs!$B52,'Stats 2020'!S$24:S$1048576),NA()) -> 154.5 | H52: =IF($B52<=TODAY(),SUMIF('Stats 2020'!$M$24:$M$1048576,"<="&Graphs!$B52,'Stats 2020'!T$24:T$1048576),NA()) -> 85.75 | I52: =VLOOKUP($A52,$B$1:$H$59,MATCH(I$1,$B$1:$H$1,0),0) -> #N/A | J52: =VLOOKUP($A52,$B$1:$H$59,MATCH(J$1,$B$1:$H$1,0),0) -> #N/A | K52: =VLOOKUP($A52,$B$1:$H$59,MATCH(K$1,$B$1:$H$1,0),0) -> #N/A | L52: =VLOOKUP($A52,$B$1:$H$59,MATCH(L$1,$B$1:$H$1,0),0) -> #N/A | M52: =VLOOKUP($A52,$B$1:$H$59,MATCH(M$1,$B$1:$H$1,0),0) -> #N/A | N52: =VLOOKUP($A52,$B$1:$H$59,MATCH(N$1,$B$1:$H$1,0),0) -> #N/A | P52: =B52 -> 44204 | Q52: =VLOOKUP($B52,'Stats 2020'!$D$25:$J$200,MATCH(Graphs!Q$1,'Stats 2020'!$D$18:$J$18,0),0) -> 1 | R52: =VLOOKUP($B52,'Stats 2020'!$D$25:$J$200,MATCH(Graphs!R$1,'Stats 2020'!$D$18:$J$18,0),0) | S52: =VLOOKUP($B52,'Stats 2020'!$D$25:$J$200,MATCH(Graphs!S$1,'Stats 2020'!$D$18:$J$18,0),0) -> 0 | T52: =VLOOKUP($B52,'Stats 2020'!$D$25:$J$200,MATCH(Graphs!T$1,'Stats 2020'!$D$18:$J$18,0),0) | U52: =VLOOKUP($B52,'Stats 2020'!$D$25:$J$200,MATCH(Graphs!U$1,'Stats 2020'!$D$18:$J$18,0),0) -> 0 | V52: =VLOOKUP($B52,'Stats 2020'!$D$25:$J$200,MATCH(Graphs!V$1,'Stats 2020'!$D$18:$J$18,0),0) -> 1 | X52: =B52 -> 44204 | Y52: =SUM(Q$2:Q52)/COUNTA($P$2:$P52) -> 0.78431373 | Z52: =SUM(R$2:R52)/COUNTA($P$2:$P52) -> 0.21568627 | AA52: =SUM(S$2:S52)/COUNTA($P$2:$P52) -> 0.76470588 | AB52: =SUM(T$2:T52)/COUNTA($P$2:$P52) -> 0.31372549 | AC52: =SUM(U$2:U52)/COUNTA($P$2:$P52) -> 0.76470588 | AD52: =SUM(V$2:V52)/COUNTA($P$2:$P52) -> 0.88235294 | AE52: =AVERAGE(Y52:AD52) -> 0.62091503 | AF52: =VLOOKUP($A52,$X$1:$AE$59,MATCH(AF$1,$X$1:$AE$1,0),0) -> #N/A | AG52: =VLOOKUP($A52,$X$1:$AE$59,MATCH(AG$1,$X$1:$AE$1,0),0) -> #N/A | AH52: =VLOOKUP($A52,$X$1:$AE$59,MATCH(AH$1,$X$1:$AE$1,0),0) -> #N/A | AI52: =VLOOKUP($A52,$X$1:$AE$59,MATCH(AI$1,$X$1:$AE$1,0),0) -> #N/A | AJ52: =VLOOKUP($A52,$X$1:$AE$59,MATCH(AJ$1,$X$1:$AE$1,0),0) -> #N/A | AK52: =VLOOKUP($A52,$X$1:$AE$59,MATCH(AK$1,$X$1:$AE$1,0),0) -> #N/A | AL52: =VLOOKUP($A52,$X$1:$AE$59,MATCH(AL$1,$X$1:$AE$1,0),0) -> #N/A
A53: =IF(AND((TODAY()-B53)<7,(TODAY()-B53>=0)),B53,NA()) -> #N/A | B53: =B52+7 -> 44211 | C53: =IF($B53<=TODAY(),SUMIF('Stats 2020'!$M$24:$M$1048576,"<="&Graphs!$B53,'Stats 2020'!O$24:O$1048576),NA()) -> 190.25 | D53: =IF($B53<=TODAY(),MAX($C53,$E53,$G53,$H53)+11+16.5,NA()) -> 217.75 | E53: =IF($B53<=TODAY(),SUMIF('Stats 2020'!$M$24:$M$1048576,"<="&Graphs!$B53,'Stats 2020'!Q$24:Q$1048576),NA()) -> 160 | F53: =IF($B53<=TODAY(),MAX($C53,$E53,$G53,$H53)+11+16.5,NA()) -> 217.75 | G53: =IF($B53<=TODAY(),SUMIF('Stats 2020'!$M$24:$M$1048576,"<="&Graphs!$B53,'Stats 2020'!S$24:S$1048576),NA()) -> 165.5 | H53: =IF($B53<=TODAY(),SUMIF('Stats 2020'!$M$24:$M$1048576,"<="&Graphs!$B53,'Stats 2020'!T$24:T$1048576),NA()) -> 90.75 | I53: =VLOOKUP($A53,$B$1:$H$59,MATCH(I$1,$B$1:$H$1,0),0) -> #N/A | J53: =VLOOKUP($A53,$B$1:$H$59,MATCH(J$1,$B$1:$H$1,0),0) -> #N/A | K53: =VLOOKUP($A53,$B$1:$H$59,MATCH(K$1,$B$1:$H$1,0),0) -> #N/A | L53: =VLOOKUP($A53,$B$1:$H$59,MATCH(L$1,$B$1:$H$1,0),0) -> #N/A | M53: =VLOOKUP($A53,$B$1:$H$59,MATCH(M$1,$B$1:$H$1,0),0) -> #N/A | N53: =VLOOKUP($A53,$B$1:$H$59,MATCH(N$1,$B$1:$H$1,0),0) -> #N/A | P53: =B53 -> 44211 | Q53: =VLOOKUP($B53,'Stats 2020'!$D$25:$J$200,MATCH(Graphs!Q$1,'Stats 2020'!$D$18:$J$18,0),0) -> 0 | R53: =VLOOKUP($B53,'Stats 2020'!$D$25:$J$200,MATCH(Graphs!R$1,'Stats 2020'!$D$18:$J$18,0),0) -> 1 | S53: =VLOOKUP($B53,'Stats 2020'!$D$25:$J$200,MATCH(Graphs!S$1,'Stats 2020'!$D$18:$J$18,0),0) -> 0 | T53: =VLOOKUP($B53,'Stats 2020'!$D$25:$J$200,MATCH(Graphs!T$1,'Stats 2020'!$D$18:$J$18,0),0) -> 1 | U53: =VLOOKUP($B53,'Stats 2020'!$D$25:$J$200,MATCH(Graphs!U$1,'Stats 2020'!$D$18:$J$18,0),0) -> 0 | V53: =VLOOKUP($B53,'Stats 2020'!$D$25:$J$200,MATCH(Graphs!V$1,'Stats 2020'!$D$18:$J$18,0),0) -> 1 | X53: =B53 -> 44211 | Y53: =SUM(Q$2:Q52)/COUNTA($P$2:$P52) -> 0.78431373 | Z53: =SUM(R$2:R52)/COUNTA($P$2:$P52) -> 0.21568627 | AA53: =SUM(S$2:S52)/COUNTA($P$2:$P52) -> 0.76470588 | AB53: =SUM(T$2:T52)/COUNTA($P$2:$P52) -> 0.31372549 | AC53: =SUM(U$2:U52)/COUNTA($P$2:$P52) -> 0.76470588 | AD53: =SUM(V$2:V52)/COUNTA($P$2:$P52) -> 0.88235294 | AE53: =AVERAGE(Y53:AD53) -> 0.62091503 | AF53: =VLOOKUP($A53,$X$1:$AE$59,MATCH(AF$1,$X$1:$AE$1,0),0) -> #N/A | AG53: =VLOOKUP($A53,$X$1:$AE$59,MATCH(AG$1,$X$1:$AE$1,0),0) -> #N/A | AH53: =VLOOKUP($A53,$X$1:$AE$59,MATCH(AH$1,$X$1:$AE$1,0),0) -> #N/A | AI53: =VLOOKUP($A53,$X$1:$AE$59,MATCH(AI$1,$X$1:$AE$1,0),0) -> #N/A | AJ53: =VLOOKUP($A53,$X$1:$AE$59,MATCH(AJ$1,$X$1:$AE$1,0),0) -> #N/A | AK53: =VLOOKUP($A53,$X$1:$AE$59,MATCH(AK$1,$X$1:$AE$1,0),0) -> #N/A | AL53: =VLOOKUP($A53,$X$1:$AE$59,MATCH(AL$1,$X$1:$AE$1,0),0) -> #N/A
A54: =IF(AND((TODAY()-B54)<7,(TODAY()-B54>=0)),B54,NA()) -> #N/A | B54: =B53+7 -> 44218 | C54: =IF($B54<=TODAY(),SUMIF('Stats 2020'!$M$24:$M$1048576,"<="&Graphs!$B54,'Stats 2020'!O$24:O$1048576),NA()) -> 190.25 | D54: =IF($B54<=TODAY(),MAX($C54,$E54,$G54,$H54)+11+16.5,NA()) -> 217.75 | E54: =IF($B54<=TODAY(),SUMIF('Stats 2020'!$M$24:$M$1048576,"<="&Graphs!$B54,'Stats 2020'!Q$24:Q$1048576),NA()) -> 160 | F54: =IF($B54<=TODAY(),MAX($C54,$E54,$G54,$H54)+11+16.5,NA()) -> 217.75 | G54: =IF($B54<=TODAY(),SUMIF('Stats 2020'!$M$24:$M$1048576,"<="&Graphs!$B54,'Stats 2020'!S$24:S$1048576),NA()) -> 165.5 | H54: =IF($B54<=TODAY(),SUMIF('Stats 2020'!$M$24:$M$1048576,"<="&Graphs!$B54,'Stats 2020'!T$24:T$1048576),NA()) -> 90.75 | I54: =VLOOKUP($A54,$B$1:$H$59,MATCH(I$1,$B$1:$H$1,0),0) -> #N/A | J54: =VLOOKUP($A54,$B$1:$H$59,MATCH(J$1,$B$1:$H$1,0),0) -> #N/A | K54: =VLOOKUP($A54,$B$1:$H$59,MATCH(K$1,$B$1:$H$1,0),0) -> #N/A | L54: =VLOOKUP($A54,$B$1:$H$59,MATCH(L$1,$B$1:$H$1,0),0) -> #N/A | M54: =VLOOKUP($A54,$B$1:$H$59,MATCH(M$1,$B$1:$H$1,0),0) -> #N/A | N54: =VLOOKUP($A54,$B$1:$H$59,MATCH(N$1,$B$1:$H$1,0),0) -> #N/A | P54: =B54 -> 44218 | Q54: =VLOOKUP($B54,'Stats 2020'!$D$25:$J$200,MATCH(Graphs!Q$1,'Stats 2020'!$D$18:$J$18,0),0) -> 1 | R54: =VLOOKUP($B54,'Stats 2020'!$D$25:$J$200,MATCH(Graphs!R$1,'Stats 2020'!$D$18:$J$18,0),0) -> 1 | S54: =VLOOKUP($B54,'Stats 2020'!$D$25:$J$200,MATCH(Graphs!S$1,'Stats 2020'!$D$18:$J$18,0),0) -> 1 | T54: =VLOOKUP($B54,'Stats 2020'!$D$25:$J$200,MATCH(Graphs!T$1,'Stats 2020'!$D$18:$J$18,0),0) -> 1 | U54: =VLOOKUP($B54,'Stats 2020'!$D$25:$J$200,MATCH(Graphs!U$1,'Stats 2020'!$D$18:$J$18,0),0) -> 1 | V54: =VLOOKUP($B54,'Stats 2020'!$D$25:$J$200,MATCH(Graphs!V$1,'Stats 2020'!$D$18:$J$18,0),0) -> 1 | X54: =B54 -> 44218 | Y54: =SUM(Q$2:Q54)/COUNTA($P$2:$P54) -> 0.77358491 | Z54: =SUM(R$2:R54)/COUNTA($P$2:$P54) -> 0.24528302 | AA54: =SUM(S$2:S54)/COUNTA($P$2:$P54) -> 0.75471698 | AB54: =SUM(T$2:T54)/COUNTA($P$2:$P54) -> 0.33962264 | AC54: =SUM(U$2:U54)/COUNTA($P$2:$P54) -> 0.75471698 | AD54: =SUM(V$2:V54)/COUNTA($P$2:$P54) -> 0.88679245 | AE54: =AVERAGE(Y54:AD54) -> 0.62578616 | AF54: =VLOOKUP($A54,$X$1:$AE$59,MATCH(AF$1,$X$1:$AE$1,0),0) -> #N/A | AG54: =VLOOKUP($A54,$X$1:$AE$59,MATCH(AG$1,$X$1:$AE$1,0),0) -> #N/A | AH54: =VLOOKUP($A54,$X$1:$AE$59,MATCH(AH$1,$X$1:$AE$1,0),0) -> #N/A | AI54: =VLOOKUP($A54,$X$1:$AE$59,MATCH(AI$1,$X$1:$AE$1,0),0) -> #N/A | AJ54: =VLOOKUP($A54,$X$1:$AE$59,MATCH(AJ$1,$X$1:$AE$1,0),0) -> #N/A | AK54: =VLOOKUP($A54,$X$1:$AE$59,MATCH(AK$1,$X$1:$AE$1,0),0) -> #N/A | AL54: =VLOOKUP($A54,$X$1:$AE$59,MATCH(AL$1,$X$1:$AE$1,0),0) -> #N/A
A55: =IF(AND((TODAY()-B55)<7,(TODAY()-B55>=0)),B55,NA()) -> #N/A | B55: =B54+7 -> 44225 | C55: =IF($B55<=TODAY(),SUMIF('Stats 2020'!$M$24:$M$1048576,"<="&Graphs!$B55,'Stats 2020'!O$24:O$1048576),NA()) -> 201.25 | D55: =IF($B55<=TODAY(),MAX($C55,$E55,$G55,$H55)+11+16.5,NA()) -> 228.75 | E55: =IF($B55<=TODAY(),SUMIF('Stats 2020'!$M$24:$M$1048576,"<="&Graphs!$B55,'Stats 2020'!Q$24:Q$1048576),NA()) -> 160 | F55: =IF($B55<=TODAY(),MAX($C55,$E55,$G55,$H55)+11+16.5,NA()) -> 228.75 | G55: =IF($B55<=TODAY(),SUMIF('Stats 2020'!$M$24:$M$1048576,"<="&Graphs!$B55,'Stats 2020'!S$24:S$1048576),NA()) -> 165.5 | H55: =IF($B55<=TODAY(),SUMIF('Stats 2020'!$M$24:$M$1048576,"<="&Graphs!$B55,'Stats 2020'!T$24:T$1048576),NA()) -> 101.75 | I55: =VLOOKUP($A55,$B$1:$H$59,MATCH(I$1,$B$1:$H$1,0),0) -> #N/A | J55: =VLOOKUP($A55,$B$1:$H$59,MATCH(J$1,$B$1:$H$1,0),0) -> #N/A | K55: =VLOOKUP($A55,$B$1:$H$59,MATCH(K$1,$B$1:$H$1,0),0) -> #N/A | L55: =VLOOKUP($A55,$B$1:$H$59,MATCH(L$1,$B$1:$H$1,0),0) -> #N/A | M55: =VLOOKUP($A55,$B$1:$H$59,MATCH(M$1,$B$1:$H$1,0),0) -> #N/A | N55: =VLOOKUP($A55,$B$1:$H$59,MATCH(N$1,$B$1:$H$1,0),0) -> #N/A | P55: =B55 -> 44225 | Q55: =VLOOKUP($B55,'Stats 2020'!$D$25:$J$200,MATCH(Graphs!Q$1,'Stats 2020'!$D$18:$J$18,0),0) -> 0 | R55: =VLOOKUP($B55,'Stats 2020'!$D$25:$J$200,MATCH(Graphs!R$1,'Stats 2020'!$D$18:$J$18,0),0) | S55: =VLOOKUP($B55,'Stats 2020'!$D$25:$J$200,MATCH(Graphs!S$1,'Stats 2020'!$D$18:$J$18,0),0) -> 1 | T55: =VLOOKUP($B55,'Stats 2020'!$D$25:$J$200,MATCH(Graphs!T$1,'Stats 2020'!$D$18:$J$18,0),0) | U55: =VLOOKUP($B55,'Stats 2020'!$D$25:$J$200,MATCH(Graphs!U$1,'Stats 2020'!$D$18:$J$18,0),0) -> 1 | V55: =VLOOKUP($B55,'Stats 2020'!$D$25:$J$200,MATCH(Graphs!V$1,'Stats 2020'!$D$18:$J$18,0),0) -> 0 | X55: =B55 -> 44225 | Y55: =SUM(Q$2:Q54)/COUNTA($P$2:$P54) -> 0.77358491 | Z55: =SUM(R$2:R54)/COUNTA($P$2:$P54) -> 0.24528302 | AA55: =SUM(S$2:S54)/COUNTA($P$2:$P54) -> 0.75471698 | AB55: =SUM(T$2:T54)/COUNTA($P$2:$P54) -> 0.33962264 | AC55: =SUM(U$2:U54)/COUNTA($P$2:$P54) -> 0.75471698 | AD55: =SUM(V$2:V54)/COUNTA($P$2:$P54) -> 0.88679245 | AE55: =AVERAGE(Y55:AD55) -> 0.62578616 | AF55: =VLOOKUP($A55,$X$1:$AE$59,MATCH(AF$1,$X$1:$AE$1,0),0) -> #N/A | AG55: =VLOOKUP($A55,$X$1:$AE$59,MATCH(AG$1,$X$1:$AE$1,0),0) -> #N/A | AH55: =VLOOKUP($A55,$X$1:$AE$59,MATCH(AH$1,$X$1:$AE$1,0),0) -> #N/A | AI55: =VLOOKUP($A55,$X$1:$AE$59,MATCH(AI$1,$X$1:$AE$1,0),0) -> #N/A | AJ55: =VLOOKUP($A55,$X$1:$AE$59,MATCH(AJ$1,$X$1:$AE$1,0),0) -> #N/A | AK55: =VLOOKUP($A55,$X$1:$AE$59,MATCH(AK$1,$X$1:$AE$1,0),0) -> #N/A | AL55: =VLOOKUP($A55,$X$1:$AE$59,MATCH(AL$1,$X$1:$AE$1,0),0) -> #N/A
A56: =IF(AND((TODAY()-B56)<7,(TODAY()-B56>=0)),B56,NA()) -> #N/A | B56: =B55+7 -> 44232 | C56: =IF($B56<=TODAY(),SUMIF('Stats 2020'!$M$24:$M$1048576,"<="&Graphs!$B56,'Stats 2020'!O$24:O$1048576),NA()) -> 201.25 | D56: =IF($B56<=TODAY(),MAX($C56,$E56,$G56,$H56)+11+16.5,NA()) -> 228.75 | E56: =IF($B56<=TODAY(),SUMIF('Stats 2020'!$M$24:$M$1048576,"<="&Graphs!$B56,'Stats 2020'!Q$24:Q$1048576),NA()) -> 160 | F56: =IF($B56<=TODAY(),MAX($C56,$E56,$G56,$H56)+11+16.5,NA()) -> 228.75 | G56: =IF($B56<=TODAY(),SUMIF('Stats 2020'!$M$24:$M$1048576,"<="&Graphs!$B56,'Stats 2020'!S$24:S$1048576),NA()) -> 165.5 | H56: =IF($B56<=TODAY(),SUMIF('Stats 2020'!$M$24:$M$1048576,"<="&Graphs!$B56,'Stats 2020'!T$24:T$1048576),NA()) -> 101.75 | I56: =VLOOKUP($A56,$B$1:$H$59,MATCH(I$1,$B$1:$H$1,0),0) -> #N/A | J56: =VLOOKUP($A56,$B$1:$H$59,MATCH(J$1,$B$1:$H$1,0),0) -> #N/A | K56: =VLOOKUP($A56,$B$1:$H$59,MATCH(K$1,$B$1:$H$1,0),0) -> #N/A | L56: =VLOOKUP($A56,$B$1:$H$59,MATCH(L$1,$B$1:$H$1,0),0) -> #N/A | M56: =VLOOKUP($A56,$B$1:$H$59,MATCH(M$1,$B$1:$H$1,0),0) -> #N/A | N56: =VLOOKUP($A56,$B$1:$H$59,MATCH(N$1,$B$1:$H$1,0),0) -> #N/A | P56: =B56 -> 44232 | Q56: =VLOOKUP($B56,'Stats 2020'!$D$25:$J$200,MATCH(Graphs!Q$1,'Stats 2020'!$D$18:$J$18,0),0) -> 1 | R56: =VLOOKUP($B56,'Stats 2020'!$D$25:$J$200,MATCH(Graphs!R$1,'Stats 2020'!$D$18:$J$18,0),0) -> 1 | S56: =VLOOKUP($B56,'Stats 2020'!$D$25:$J$200,MATCH(Graphs!S$1,'Stats 2020'!$D$18:$J$18,0),0) -> 1 | T56: =VLOOKUP($B56,'Stats 2020'!$D$25:$J$200,MATCH(Graphs!T$1,'Stats 2020'!$D$18:$J$18,0),0) -> 1 | U56: =VLOOKUP($B56,'Stats 2020'!$D$25:$J$200,MATCH(Graphs!U$1,'Stats 2020'!$D$18:$J$18,0),0) -> 1 | V56: =VLOOKUP($B56,'Stats 2020'!$D$25:$J$200,MATCH(Graphs!V$1,'Stats 2020'!$D$18:$J$18,0),0) -> 1 | X56: =B56 -> 44232 | Y56: =SUM(Q$2:Q56)/COUNTA($P$2:$P56) -> 0.76363636 | Z56: =SUM(R$2:R56)/COUNTA($P$2:$P56) -> 0.25454545 | AA56: =SUM(S$2:S56)/COUNTA($P$2:$P56) -> 0.76363636 | AB56: =SUM(T$2:T56)/COUNTA($P$2:$P56) -> 0.34545455 | AC56: =SUM(U$2:U56)/COUNTA($P$2:$P56) -> 0.76363636 | AD56: =SUM(V$2:V56)/COUNTA($P$2:$P56) -> 0.87272727 | AE56: =AVERAGE(Y56:AD56) -> 0.62727273 | AF56: =VLOOKUP($A56,$X$1:$AE$59,MATCH(AF$1,$X$1:$AE$1,0),0) -> #N/A | AG56: =VLOOKUP($A56,$X$1:$AE$59,MATCH(AG$1,$X$1:$AE$1,0),0) -> #N/A | AH56: =VLOOKUP($A56,$X$1:$AE$59,MATCH(AH$1,$X$1:$AE$1,0),0) -> #N/A | AI56: =VLOOKUP($A56,$X$1:$AE$59,MATCH(AI$1,$X$1:$AE$1,0),0) -> #N/A | AJ56: =VLOOKUP($A56,$X$1:$AE$59,MATCH(AJ$1,$X$1:$AE$1,0),0) -> #N/A | AK56: =VLOOKUP($A56,$X$1:$AE$59,MATCH(AK$1,$X$1:$AE$1,0),0) -> #N/A | AL56: =VLOOKUP($A56,$X$1:$AE$59,MATCH(AL$1,$X$1:$AE$1,0),0) -> #N/A
A57: =IF(AND((TODAY()-B57)<7,(TODAY()-B57>=0)),B57,NA()) -> #N/A | B57: =B56+7 -> 44239 | C57: =IF($B57<=TODAY(),SUMIF('Stats 2020'!$M$24:$M$1048576,"<="&Graphs!$B57,'Stats 2020'!O$24:O$1048576),NA()) -> 201.25 | D57: =IF($B57<=TODAY(),MAX($C57,$E57,$G57,$H57)+11+16.5,NA()) -> 228.75 | E57: =IF($B57<=TODAY(),SUMIF('Stats 2020'!$M$24:$M$1048576,"<="&Graphs!$B57,'Stats 2020'!Q$24:Q$1048576),NA()) -> 160 | F57: =IF($B57<=TODAY(),MAX($C57,$E57,$G57,$H57)+11+16.5,NA()) -> 228.75 | G57: =IF($B57<=TODAY(),SUMIF('Stats 2020'!$M$24:$M$1048576,"<="&Graphs!$B57,'Stats 2020'!S$24:S$1048576),NA()) -> 165.5 | H57: =IF($B57<=TODAY(),SUMIF('Stats 2020'!$M$24:$M$1048576,"<="&Graphs!$B57,'Stats 2020'!T$24:T$1048576),NA()) -> 101.75 | I57: =VLOOKUP($A57,$B$1:$H$59,MATCH(I$1,$B$1:$H$1,0),0) -> #N/A | J57: =VLOOKUP($A57,$B$1:$H$59,MATCH(J$1,$B$1:$H$1,0),0) -> #N/A | K57: =VLOOKUP($A57,$B$1:$H$59,MATCH(K$1,$B$1:$H$1,0),0) -> #N/A | L57: =VLOOKUP($A57,$B$1:$H$59,MATCH(L$1,$B$1:$H$1,0),0) -> #N/A | M57: =VLOOKUP($A57,$B$1:$H$59,MATCH(M$1,$B$1:$H$1,0),0) -> #N/A | N57: =VLOOKUP($A57,$B$1:$H$59,MATCH(N$1,$B$1:$H$1,0),0) -> #N/A | P57: =B57 -> 44239 | Q57: =VLOOKUP($B57,'Stats 2020'!$D$25:$J$200,MATCH(Graphs!Q$1,'Stats 2020'!$D$18:$J$18,0),0) -> 1 | R57: =VLOOKUP($B57,'Stats 2020'!$D$25:$J$200,MATCH(Graphs!R$1,'Stats 2020'!$D$18:$J$18,0),0) -> 1 | S57: =VLOOKUP($B57,'Stats 2020'!$D$25:$J$200,MATCH(Graphs!S$1,'Stats 2020'!$D$18:$J$18,0),0) -> 1 | T57: =VLOOKUP($B57,'Stats 2020'!$D$25:$J$200,MATCH(Graphs!T$1,'Stats 2020'!$D$18:$J$18,0),0) | U57: =VLOOKUP($B57,'Stats 2020'!$D$25:$J$200,MATCH(Graphs!U$1,'Stats 2020'!$D$18:$J$18,0),0) -> 1 | V57: =VLOOKUP($B57,'Stats 2020'!$D$25:$J$200,MATCH(Graphs!V$1,'Stats 2020'!$D$18:$J$18,0),0) -> 1 | X57: =B57 -> 44239 | Y57: =SUM(Q$2:Q56)/COUNTA($P$2:$P56) -> 0.76363636 | Z57: =SUM(R$2:R56)/COUNTA($P$2:$P56) -> 0.25454545 | AA57: =SUM(S$2:S56)/COUNTA($P$2:$P56) -> 0.76363636 | AB57: =SUM(T$2:T56)/COUNTA($P$2:$P56) -> 0.34545455 | AC57: =SUM(U$2:U56)/COUNTA($P$2:$P56) -> 0.76363636 | AD57: =SUM(V$2:V56)/COUNTA($P$2:$P56) -> 0.87272727 | AE57: =AVERAGE(Y57:AD57) -> 0.62727273 | AF57: =VLOOKUP($A57,$X$1:$AE$59,MATCH(AF$1,$X$1:$AE$1,0),0) -> #N/A | AG57: =VLOOKUP($A57,$X$1:$AE$59,MATCH(AG$1,$X$1:$AE$1,0),0) -> #N/A | AH57: =VLOOKUP($A57,$X$1:$AE$59,MATCH(AH$1,$X$1:$AE$1,0),0) -> #N/A | AI57: =VLOOKUP($A57,$X$1:$AE$59,MATCH(AI$1,$X$1:$AE$1,0),0) -> #N/A | AJ57: =VLOOKUP($A57,$X$1:$AE$59,MATCH(AJ$1,$X$1:$AE$1,0),0) -> #N/A | AK57: =VLOOKUP($A57,$X$1:$AE$59,MATCH(AK$1,$X$1:$AE$1,0),0) -> #N/A | AL57: =VLOOKUP($A57,$X$1:$AE$59,MATCH(AL$1,$X$1:$AE$1,0),0) -> #N/A
A58: =IF(AND((TODAY()-B58)<7,(TODAY()-B58>=0)),B58,NA()) -> #N/A | B58: =B57+7 -> 44246 | C58: =IF($B58<=TODAY(),SUMIF('Stats 2020'!$M$24:$M$1048576,"<="&Graphs!$B58,'Stats 2020'!O$24:O$1048576),NA()) -> 201.25 | D58: =IF($B58<=TODAY(),MAX($C58,$E58,$G58,$H58)+11+16.5,NA()) -> 228.75 | E58: =IF($B58<=TODAY(),SUMIF('Stats 2020'!$M$24:$M$1048576,"<="&Graphs!$B58,'Stats 2020'!Q$24:Q$1048576),NA()) -> 171 | F58: =IF($B58<=TODAY(),MAX($C58,$E58,$G58,$H58)+11+16.5,NA()) -> 228.75 | G58: =IF($B58<=TODAY(),SUMIF('Stats 2020'!$M$24:$M$1048576,"<="&Graphs!$B58,'Stats 2020'!S$24:S$1048576),NA()) -> 176.5 | H58: =IF($B58<=TODAY(),SUMIF('Stats 2020'!$M$24:$M$1048576,"<="&Graphs!$B58,'Stats 2020'!T$24:T$1048576),NA()) -> 101.75 | I58: =VLOOKUP($A58,$B$1:$H$59,MATCH(I$1,$B$1:$H$1,0),0) -> #N/A | J58: =VLOOKUP($A58,$B$1:$H$59,MATCH(J$1,$B$1:$H$1,0),0) -> #N/A | K58: =VLOOKUP($A58,$B$1:$H$59,MATCH(K$1,$B$1:$H$1,0),0) -> #N/A | L58: =VLOOKUP($A58,$B$1:$H$59,MATCH(L$1,$B$1:$H$1,0),0) -> #N/A | M58: =VLOOKUP($A58,$B$1:$H$59,MATCH(M$1,$B$1:$H$1,0),0) -> #N/A | N58: =VLOOKUP($A58,$B$1:$H$59,MATCH(N$1,$B$1:$H$1,0),0) -> #N/A | P58: =B58 -> 44246 | Q58: =VLOOKUP($B58,'Stats 2020'!$D$25:$J$200,MATCH(Graphs!Q$1,'Stats 2020'!$D$18:$J$18,0),0) -> 1 | R58: =VLOOKUP($B58,'Stats 2020'!$D$25:$J$200,MATCH(Graphs!R$1,'Stats 2020'!$D$18:$J$18,0),0) -> 1 | S58: =VLOOKUP($B58,'Stats 2020'!$D$25:$J$200,MATCH(Graphs!S$1,'Stats 2020'!$D$18:$J$18,0),0) -> 0 | T58: =VLOOKUP($B58,'Stats 2020'!$D$25:$J$200,MATCH(Graphs!T$1,'Stats 2020'!$D$18:$J$18,0),0) | U58: =VLOOKUP($B58,'Stats 2020'!$D$25:$J$200,MATCH(Graphs!U$1,'Stats 2020'!$D$18:$J$18,0),0) -> 0 | V58: =VLOOKUP($B58,'Stats 2020'!$D$25:$J$200,MATCH(Graphs!V$1,'Stats 2020'!$D$18:$J$18,0),0) -> 1 | X58: =B58 -> 44246 | Y58: =SUM(Q$2:Q58)/COUNTA($P$2:$P58) -> 0.77192982 | Z58: =SUM(R$2:R58)/COUNTA($P$2:$P58) -> 0.28070175 | AA58: =SUM(S$2:S58)/COUNTA($P$2:$P58) -> 0.75438596 | AB58: =SUM(T$2:T58)/COUNTA($P$2:$P58) -> 0.33333333 | AC58: =SUM(U$2:U58)/COUNTA($P$2:$P58) -> 0.75438596 | AD58: =SUM(V$2:V58)/COUNTA($P$2:$P58) -> 0.87719298 | AE58: =AVERAGE(Y58:AD58) -> 0.62865497 | AF58: =VLOOKUP($A58,$X$1:$AE$59,MATCH(AF$1,$X$1:$AE$1,0),0) -> #N/A | AG58: =VLOOKUP($A58,$X$1:$AE$59,MATCH(AG$1,$X$1:$AE$1,0),0) -> #N/A | AH58: =VLOOKUP($A58,$X$1:$AE$59,MATCH(AH$1,$X$1:$AE$1,0),0) -> #N/A | AI58: =VLOOKUP($A58,$X$1:$AE$59,MATCH(AI$1,$X$1:$AE$1,0),0) -> #N/A | AJ58: =VLOOKUP($A58,$X$1:$AE$59,MATCH(AJ$1,$X$1:$AE$1,0),0) -> #N/A | AK58: =VLOOKUP($A58,$X$1:$AE$59,MATCH(AK$1,$X$1:$AE$1,0),0) -> #N/A | AL58: =VLOOKUP($A58,$X$1:$AE$59,MATCH(AL$1,$X$1:$AE$1,0),0) -> #N/A
A59: =IF(AND((TODAY()-B59)<7,(TODAY()-B59>=0)),B59,NA()) -> #N/A | B59: =B58+7 -> 44253 | C59: =IF($B59<=TODAY(),SUMIF('Stats 2020'!$M$24:$M$1048576,"<="&Graphs!$B59,'Stats 2020'!O$24:O$1048576),NA()) -> 201.25 | D59: =IF($B59<=TODAY(),MAX($C59,$E59,$G59,$H59)+11+16.5,NA()) -> 228.75 | E59: =IF($B59<=TODAY(),SUMIF('Stats 2020'!$M$24:$M$1048576,"<="&Graphs!$B59,'Stats 2020'!Q$24:Q$1048576),NA()) -> 171 | F59: =IF($B59<=TODAY(),MAX($C59,$E59,$G59,$H59)+11+16.5,NA()) -> 228.75 | G59: =IF($B59<=TODAY(),SUMIF('Stats 2020'!$M$24:$M$1048576,"<="&Graphs!$B59,'Stats 2020'!S$24:S$1048576),NA()) -> 176.5 | H59: =IF($B59<=TODAY(),SUMIF('Stats 2020'!$M$24:$M$1048576,"<="&Graphs!$B59,'Stats 2020'!T$24:T$1048576),NA()) -> 112.75 | I59: =VLOOKUP($A59,$B$1:$H$59,MATCH(I$1,$B$1:$H$1,0),0) -> #N/A | J59: =VLOOKUP($A59,$B$1:$H$59,MATCH(J$1,$B$1:$H$1,0),0) -> #N/A | K59: =VLOOKUP($A59,$B$1:$H$59,MATCH(K$1,$B$1:$H$1,0),0) -> #N/A | L59: =VLOOKUP($A59,$B$1:$H$59,MATCH(L$1,$B$1:$H$1,0),0) -> #N/A | M59: =VLOOKUP($A59,$B$1:$H$59,MATCH(M$1,$B$1:$H$1,0),0) -> #N/A | N59: =VLOOKUP($A59,$B$1:$H$59,MATCH(N$1,$B$1:$H$1,0),0) -> #N/A | P59: =B59 -> 44253 | Q59: =VLOOKUP($B59,'Stats 2020'!$D$25:$J$200,MATCH(Graphs!Q$1,'Stats 2020'!$D$18:$J$18,0),0) -> 1 | R59: =VLOOKUP($B59,'Stats 2020'!$D$25:$J$200,MATCH(Graphs!R$1,'Stats 2020'!$D$18:$J$18,0),0) -> 1 | S59: =VLOOKUP($B59,'Stats 2020'!$D$25:$J$200,MATCH(Graphs!S$1,'Stats 2020'!$D$18:$J$18,0),0) -> 1 | T59: =VLOOKUP($B59,'Stats 2020'!$D$25:$J$200,MATCH(Graphs!T$1,'Stats 2020'!$D$18:$J$18,0),0) -> 1 | U59: =VLOOKUP($B59,'Stats 2020'!$D$25:$J$200,MATCH(Graphs!U$1,'Stats 2020'!$D$18:$J$18,0),0) -> 1 | V59: =VLOOKUP($B59,'Stats 2020'!$D$25:$J$200,MATCH(Graphs!V$1,'Stats 2020'!$D$18:$J$18,0),0) -> 0 | X59: =B59 -> 44253 | Y59: =SUM(Q$2:Q58)/COUNTA($P$2:$P58) -> 0.77192982 | Z59: =SUM(R$2:R58)/COUNTA($P$2:$P58) -> 0.28070175 | AA59: =SUM(S$2:S58)/COUNTA($P$2:$P58) -> 0.75438596 | AB59: =SUM(T$2:T58)/COUNTA($P$2:$P58) -> 0.33333333 | AC59: =SUM(U$2:U58)/COUNTA($P$2:$P58) -> 0.75438596 | AD59: =SUM(V$2:V58)/COUNTA($P$2:$P58) -> 0.87719298 | AE59: =AVERAGE(Y59:AD59) -> 0.62865497 | AF59: =VLOOKUP($A59,$X$1:$AE$59,MATCH(AF$1,$X$1:$AE$1,0),0) -> #N/A | AG59: =VLOOKUP($A59,$X$1:$AE$59,MATCH(AG$1,$X$1:$AE$1,0),0) -> #N/A | AH59: =VLOOKUP($A59,$X$1:$AE$59,MATCH(AH$1,$X$1:$AE$1,0),0) -> #N/A | AI59: =VLOOKUP($A59,$X$1:$AE$59,MATCH(AI$1,$X$1:$AE$1,0),0) -> #N/A | AJ59: =VLOOKUP($A59,$X$1:$AE$59,MATCH(AJ$1,$X$1:$AE$1,0),0) -> #N/A | AK59: =VLOOKUP($A59,$X$1:$AE$59,MATCH(AK$1,$X$1:$AE$1,0),0) -> #N/A | AL59: =VLOOKUP($A59,$X$1:$AE$59,MATCH(AL$1,$X$1:$AE$1,0),0) -> #N/A
A60: =IF(AND((TODAY()-B60)<7,(TODAY()-B60>=0)),B60,NA()) -> #N/A | B60: =B59+7 -> 44260 | C60: =IF($B60<=TODAY(),SUMIF('Stats 2020'!$M$24:$M$1048576,"<="&Graphs!$B60,'Stats 2020'!O$24:O$1048576),NA()) -> 212.25 | D60: =IF($B60<=TODAY(),MAX($C60,$E60,$G60,$H60)+11+16.5,NA()) -> 239.75 | E60: =IF($B60<=TODAY(),SUMIF('Stats 2020'!$M$24:$M$1048576,"<="&Graphs!$B60,'Stats 2020'!Q$24:Q$1048576),NA()) -> 171 | F60: =IF($B60<=TODAY(),MAX($C60,$E60,$G60,$H60)+11+16.5,NA()) -> 239.75 | G60: =IF($B60<=TODAY(),SUMIF('Stats 2020'!$M$24:$M$1048576,"<="&Graphs!$B60,'Stats 2020'!S$24:S$1048576),NA()) -> 176.5 | H60: =IF($B60<=TODAY(),SUMIF('Stats 2020'!$M$24:$M$1048576,"<="&Graphs!$B60,'Stats 2020'!T$24:T$1048576),NA()) -> 112.75 | I60: =VLOOKUP($A60,$B$1:$H$59,MATCH(I$1,$B$1:$H$1,0),0) -> #N/A | J60: =VLOOKUP($A60,$B$1:$H$59,MATCH(J$1,$B$1:$H$1,0),0) -> #N/A | K60: =VLOOKUP($A60,$B$1:$H$59,MATCH(K$1,$B$1:$H$1,0),0) -> #N/A | L60: =VLOOKUP($A60,$B$1:$H$59,MATCH(L$1,$B$1:$H$1,0),0) -> #N/A | M60: =VLOOKUP($A60,$B$1:$H$59,MATCH(M$1,$B$1:$H$1,0),0) -> #N/A | N60: =VLOOKUP($A60,$B$1:$H$59,MATCH(N$1,$B$1:$H$1,0),0) -> #N/A | P60: =B61 -> 44267 | Q60: =VLOOKUP($B60,'Stats 2020'!$D$25:$J$200,MATCH(Graphs!Q$1,'Stats 2020'!$D$18:$J$18,0),0) -> 0 | R60: =VLOOKUP($B60,'Stats 2020'!$D$25:$J$200,MATCH(Graphs!R$1,'Stats 2020'!$D$18:$J$18,0),0) -> 1 | S60: =VLOOKUP($B60,'Stats 2020'!$D$25:$J$200,MATCH(Graphs!S$1,'Stats 2020'!$D$18:$J$18,0),0) -> 1 | T60: =VLOOKUP($B60,'Stats 2020'!$D$25:$J$200,MATCH(Graphs!T$1,'Stats 2020'!$D$18:$J$18,0),0) | U60: =VLOOKUP($B60,'Stats 2020'!$D$25:$J$200,MATCH(Graphs!U$1,'Stats 2020'!$D$18:$J$18,0),0) -> 1 | V60: =VLOOKUP($B60,'Stats 2020'!$D$25:$J$200,MATCH(Graphs!V$1,'Stats 2020'!$D$18:$J$18,0),0) -> 1 | X60: =B60 -> 44260 | Y60: =SUM(Q$2:Q60)/COUNTA($P$2:$P60) -> 0.76271186 | Z60: =SUM(R$2:R60)/COUNTA($P$2:$P60) -> 0.30508475 | AA60: =SUM(S$2:S60)/COUNTA($P$2:$P60) -> 0.76271186 | AB60: =SUM(T$2:T60)/COUNTA($P$2:$P60) -> 0.33898305 | AC60: =SUM(U$2:U60)/COUNTA($P$2:$P60) -> 0.76271186 | AD60: =SUM(V$2:V60)/COUNTA($P$2:$P60) -> 0.86440678 | AE60: =AVERAGE(Y60:AD60) -> 0.63276836 | AF60: =VLOOKUP($A60,$X$1:$AE$59,MATCH(AF$1,$X$1:$AE$1,0),0) -> #N/A | AG60: =VLOOKUP($A60,$X$1:$AE$59,MATCH(AG$1,$X$1:$AE$1,0),0) -> #N/A | AH60: =VLOOKUP($A60,$X$1:$AE$59,MATCH(AH$1,$X$1:$AE$1,0),0) -> #N/A | AI60: =VLOOKUP($A60,$X$1:$AE$59,MATCH(AI$1,$X$1:$AE$1,0),0) -> #N/A | AJ60: =VLOOKUP($A60,$X$1:$AE$59,MATCH(AJ$1,$X$1:$AE$1,0),0) -> #N/A | AK60: =VLOOKUP($A60,$X$1:$AE$59,MATCH(AK$1,$X$1:$AE$1,0),0) -> #N/A | AL60: =VLOOKUP($A60,$X$1:$AE$59,MATCH(AL$1,$X$1:$AE$1,0),0) -> #N/A
A61: =IF(AND((TODAY()-B61)<7,(TODAY()-B61>=0)),B61,NA()) -> #N/A | B61: =B60+7 -> 44267 | C61: =IF($B61<=TODAY(),SUMIF('Stats 2020'!$M$24:$M$1048576,"<="&Graphs!$B61,'Stats 2020'!O$24:O$1048576),NA()) -> 212.25 | D61: =IF($B61<=TODAY(),MAX($C61,$E61,$G61,$H61)+11+16.5,NA()) -> 239.75 | E61: =IF($B61<=TODAY(),SUMIF('Stats 2020'!$M$24:$M$1048576,"<="&Graphs!$B61,'Stats 2020'!Q$24:Q$1048576),NA()) -> 171 | F61: =IF($B61<=TODAY(),MAX($C61,$E61,$G61,$H61)+11+16.5,NA()) -> 239.75 | G61: =IF($B61<=TODAY(),SUMIF('Stats 2020'!$M$24:$M$1048576,"<="&Graphs!$B61,'Stats 2020'!S$24:S$1048576),NA()) -> 176.5 | H61: =IF($B61<=TODAY(),SUMIF('Stats 2020'!$M$24:$M$1048576,"<="&Graphs!$B61,'Stats 2020'!T$24:T$1048576),NA()) -> 112.75 | I61: =VLOOKUP($A61,$B$1:$H$59,MATCH(I$1,$B$1:$H$1,0),0) -> #N/A | J61: =VLOOKUP($A61,$B$1:$H$59,MATCH(J$1,$B$1:$H$1,0),0) -> #N/A | K61: =VLOOKUP($A61,$B$1:$H$59,MATCH(K$1,$B$1:$H$1,0),0) -> #N/A | L61: =VLOOKUP($A61,$B$1:$H$59,MATCH(L$1,$B$1:$H$1,0),0) -> #N/A | M61: =VLOOKUP($A61,$B$1:$H$59,MATCH(M$1,$B$1:$H$1,0),0) -> #N/A | N61: =VLOOKUP($A61,$B$1:$H$59,MATCH(N$1,$B$1:$H$1,0),0) -> #N/A | Q61: =VLOOKUP($B61,'Stats 2020'!$D$25:$J$200,MATCH(Graphs!Q$1,'Stats 2020'!$D$18:$J$18,0),0) -> 1 | R61: =VLOOKUP($B61,'Stats 2020'!$D$25:$J$200,MATCH(Graphs!R$1,'Stats 2020'!$D$18:$J$18,0),0) -> 1 | S61: =VLOOKUP($B61,'Stats 2020'!$D$25:$J$200,MATCH(Graphs!S$1,'Stats 2020'!$D$18:$J$18,0),0) -> 1 | T61: =VLOOKUP($B61,'Stats 2020'!$D$25:$J$200,MATCH(Graphs!T$1,'Stats 2020'!$D$18:$J$18,0),0) -> 1 | U61: =VLOOKUP($B61,'Stats 2020'!$D$25:$J$200,MATCH(Graphs!U$1,'Stats 2020'!$D$18:$J$18,0),0) -> 1 | V61: =VLOOKUP($B61,'Stats 2020'!$D$25:$J$200,MATCH(Graphs!V$1,'Stats 2020'!$D$18:$J$18,0),0) -> 1 | X61: =B61 -> 44267 | Y61: =SUM(Q$2:Q60)/COUNTA($P$2:$P60) -> 0.76271186 | Z61: =SUM(R$2:R60)/COUNTA($P$2:$P60) -> 0.30508475 | AA61: =SUM(S$2:S60)/COUNTA($P$2:$P60) -> 0.76271186 | AB61: =SUM(T$2:T60)/COUNTA($P$2:$P60) -> 0.33898305 | AC61: =SUM(U$2:U60)/COUNTA($P$2:$P60) -> 0.76271186 | AD61: =SUM(V$2:V60)/COUNTA($P$2:$P60) -> 0.86440678 | AE61: =AVERAGE(Y61:AD61) -> 0.63276836 | AF61: =VLOOKUP($A61,$X$1:$AE$59,MATCH(AF$1,$X$1:$AE$1,0),0) -> #N/A | AG61: =VLOOKUP($A61,$X$1:$AE$59,MATCH(AG$1,$X$1:$AE$1,0),0) -> #N/A | AH61: =VLOOKUP($A61,$X$1:$AE$59,MATCH(AH$1,$X$1:$AE$1,0),0) -> #N/A | AI61: =VLOOKUP($A61,$X$1:$AE$59,MATCH(AI$1,$X$1:$AE$1,0),0) -> #N/A | AJ61: =VLOOKUP($A61,$X$1:$AE$59,MATCH(AJ$1,$X$1:$AE$1,0),0) -> #N/A | AK61: =VLOOKUP($A61,$X$1:$AE$59,MATCH(AK$1,$X$1:$AE$1,0),0) -> #N/A | AL61: =VLOOKUP($A61,$X$1:$AE$59,MATCH(AL$1,$X$1:$AE$1,0),0) -> #N/A
A62: =IF(AND((TODAY()-B62)<7,(TODAY()-B62>=0)),B62,NA()) -> #N/A | B62: =B61+7 -> 44274 | C62: =IF($B62<=TODAY(),SUMIF('Stats 2020'!$M$24:$M$1048576,"<="&Graphs!$B62,'Stats 2020'!O$24:O$1048576),NA()) -> 212.25 | D62: =IF($B62<=TODAY(),MAX($C62,$E62,$G62,$H62)+11+16.5,NA()) -> 239.75 | E62: =IF($B62<=TODAY(),SUMIF('Stats 2020'!$M$24:$M$1048576,"<="&Graphs!$B62,'Stats 2020'!Q$24:Q$1048576),NA()) -> 171 | F62: =IF($B62<=TODAY(),MAX($C62,$E62,$G62,$H62)+11+16.5,NA()) -> 239.75 | G62: =IF($B62<=TODAY(),SUMIF('Stats 2020'!$M$24:$M$1048576,"<="&Graphs!$B62,'Stats 2020'!S$24:S$1048576),NA()) -> 176.5 | H62: =IF($B62<=TODAY(),SUMIF('Stats 2020'!$M$24:$M$1048576,"<="&Graphs!$B62,'Stats 2020'!T$24:T$1048576),NA()) -> 112.75 | I62: =VLOOKUP($A62,$B$1:$H$59,MATCH(I$1,$B$1:$H$1,0),0) -> #N/A | J62: =VLOOKUP($A62,$B$1:$H$59,MATCH(J$1,$B$1:$H$1,0),0) -> #N/A | K62: =VLOOKUP($A62,$B$1:$H$59,MATCH(K$1,$B$1:$H$1,0),0) -> #N/A | L62: =VLOOKUP($A62,$B$1:$H$59,MATCH(L$1,$B$1:$H$1,0),0) -> #N/A | M62: =VLOOKUP($A62,$B$1:$H$59,MATCH(M$1,$B$1:$H$1,0),0) -> #N/A | N62: =VLOOKUP($A62,$B$1:$H$59,MATCH(N$1,$B$1:$H$1,0),0) -> #N/A | P62: =B63 -> 44281 | Q62: =VLOOKUP($B62,'Stats 2020'!$D$25:$J$200,MATCH(Graphs!Q$1,'Stats 2020'!$D$18:$J$18,0),0) -> 1 | R62: =VLOOKUP($B62,'Stats 2020'!$D$25:$J$200,MATCH(Graphs!R$1,'Stats 2020'!$D$18:$J$18,0),0) | S62: =VLOOKUP($B62,'Stats 2020'!$D$25:$J$200,MATCH(Graphs!S$1,'Stats 2020'!$D$18:$J$18,0),0) -> 1 | T62: =VLOOKUP($B62,'Stats 2020'!$D$25:$J$200,MATCH(Graphs!T$1,'Stats 2020'!$D$18:$J$18,0),0) -> 1 | U62: =VLOOKUP($B62,'Stats 2020'!$D$25:$J$200,MATCH(Graphs!U$1,'Stats 2020'!$D$18:$J$18,0),0) -> 1 | V62: =VLOOKUP($B62,'Stats 2020'!$D$25:$J$200,MATCH(Graphs!V$1,'Stats 2020'!$D$18:$J$18,0),0) -> 1 | X62: =B62 -> 44274 | Y62: =SUM(Q$2:Q62)/COUNTA($P$2:$P62) -> 0.78333333 | Z62: =SUM(R$2:R62)/COUNTA($P$2:$P62) -> 0.31666667 | AA62: =SUM(S$2:S62)/COUNTA($P$2:$P62) -> 0.78333333 | AB62: =SUM(T$2:T62)/COUNTA($P$2:$P62) -> 0.36666667 | AC62: =SUM(U$2:U62)/COUNTA($P$2:$P62) -> 0.78333333 | AD62: =SUM(V$2:V62)/COUNTA($P$2:$P62) -> 0.88333333 | AE62: =AVERAGE(Y62:AD62) -> 0.65277778 | AF62: =VLOOKUP($A62,$X$1:$AE$59,MATCH(AF$1,$X$1:$AE$1,0),0) -> #N/A | AG62: =VLOOKUP($A62,$X$1:$AE$59,MATCH(AG$1,$X$1:$AE$1,0),0) -> #N/A | AH62: =VLOOKUP($A62,$X$1:$AE$59,MATCH(AH$1,$X$1:$AE$1,0),0) -> #N/A | AI62: =VLOOKUP($A62,$X$1:$AE$59,MATCH(AI$1,$X$1:$AE$1,0),0) -> #N/A | AJ62: =VLOOKUP($A62,$X$1:$AE$59,MATCH(AJ$1,$X$1:$AE$1,0),0) -> #N/A | AK62: =VLOOKUP($A62,$X$1:$AE$59,MATCH(AK$1,$X$1:$AE$1,0),0) -> #N/A | AL62: =VLOOKUP($A62,$X$1:$AE$59,MATCH(AL$1,$X$1:$AE$1,0),0) -> #N/A
A63: =IF(AND((TODAY()-B63)<7,(TODAY()-B63>=0)),B63,NA()) -> #N/A | B63: =B62+7 -> 44281 | C63: =IF($B63<=TODAY(),SUMIF('Stats 2020'!$M$24:$M$1048576,"<="&Graphs!$B63,'Stats 2020'!O$24:O$1048576),NA()) -> 212.25 | D63: =IF($B63<=TODAY(),MAX($C63,$E63,$G63,$H63)+11+16.5,NA()) -> 239.75 | E63: =IF($B63<=TODAY(),SUMIF('Stats 2020'!$M$24:$M$1048576,"<="&Graphs!$B63,'Stats 2020'!Q$24:Q$1048576),NA()) -> 171 | F63: =IF($B63<=TODAY(),MAX($C63,$E63,$G63,$H63)+11+16.5,NA()) -> 239.75 | G63: =IF($B63<=TODAY(),SUMIF('Stats 2020'!$M$24:$M$1048576,"<="&Graphs!$B63,'Stats 2020'!S$24:S$1048576),NA()) -> 176.5 | H63: =IF($B63<=TODAY(),SUMIF('Stats 2020'!$M$24:$M$1048576,"<="&Graphs!$B63,'Stats 2020'!T$24:T$1048576),NA()) -> 123.75 | I63: =VLOOKUP($A63,$B$1:$H$59,MATCH(I$1,$B$1:$H$1,0),0) -> #N/A | J63: =VLOOKUP($A63,$B$1:$H$59,MATCH(J$1,$B$1:$H$1,0),0) -> #N/A | K63: =VLOOKUP($A63,$B$1:$H$59,MATCH(K$1,$B$1:$H$1,0),0) -> #N/A | L63: =VLOOKUP($A63,$B$1:$H$59,MATCH(L$1,$B$1:$H$1,0),0) -> #N/A | M63: =VLOOKUP($A63,$B$1:$H$59,MATCH(M$1,$B$1:$H$1,0),0) -> #N/A | N63: =VLOOKUP($A63,$B$1:$H$59,MATCH(N$1,$B$1:$H$1,0),0) -> #N/A | P63: =B64 -> 44288 | Q63: =VLOOKUP($B63,'Stats 2020'!$D$25:$J$200,MATCH(Graphs!Q$1,'Stats 2020'!$D$18:$J$18,0),0) -> 1 | R63: =VLOOKUP($B63,'Stats 2020'!$D$25:$J$200,MATCH(Graphs!R$1,'Stats 2020'!$D$18:$J$18,0),0) -> 1 | S63: =VLOOKUP($B63,'Stats 2020'!$D$25:$J$200,MATCH(Graphs!S$1,'Stats 2020'!$D$18:$J$18,0),0) -> 1 | T63: =VLOOKUP($B63,'Stats 2020'!$D$25:$J$200,MATCH(Graphs!T$1,'Stats 2020'!$D$18:$J$18,0),0) | U63: =VLOOKUP($B63,'Stats 2020'!$D$25:$J$200,MATCH(Graphs!U$1,'Stats 2020'!$D$18:$J$18,0),0) -> 1 | V63: =VLOOKUP($B63,'Stats 2020'!$D$25:$J$200,MATCH(Graphs!V$1,'Stats 2020'!$D$18:$J$18,0),0) -> 0 | X63: =B63 -> 44281 | Y63: =SUM(Q$2:Q62)/COUNTA($P$2:$P62) -> 0.78333333 | Z63: =SUM(R$2:R62)/COUNTA($P$2:$P62) -> 0.31666667 | AA63: =SUM(S$2:S62)/COUNTA($P$2:$P62) -> 0.78333333 | AB63: =SUM(T$2:T62)/COUNTA($P$2:$P62) -> 0.36666667 | AC63: =SUM(U$2:U62)/COUNTA($P$2:$P62) -> 0.78333333 | AD63: =SUM(V$2:V62)/COUNTA($P$2:$P62) -> 0.88333333 | AE63: =AVERAGE(Y63:AD63) -> 0.65277778 | AF63: =VLOOKUP($A63,$X$1:$AE$59,MATCH(AF$1,$X$1:$AE$1,0),0) -> #N/A | AG63: =VLOOKUP($A63,$X$1:$AE$59,MATCH(AG$1,$X$1:$AE$1,0),0) -> #N/A | AH63: =VLOOKUP($A63,$X$1:$AE$59,MATCH(AH$1,$X$1:$AE$1,0),0) -> #N/A | AI63: =VLOOKUP($A63,$X$1:$AE$59,MATCH(AI$1,$X$1:$AE$1,0),0) -> #N/A | AJ63: =VLOOKUP($A63,$X$1:$AE$59,MATCH(AJ$1,$X$1:$AE$1,0),0) -> #N/A | AK63: =VLOOKUP($A63,$X$1:$AE$59,MATCH(AK$1,$X$1:$AE$1,0),0) -> #N/A | AL63: =VLOOKUP($A63,$X$1:$AE$59,MATCH(AL$1,$X$1:$AE$1,0),0) -> #N/A
A64: =IF(AND((TODAY()-B64)<7,(TODAY()-B64>=0)),B64,NA()) -> #N/A | B64: =B63+7 -> 44288 | C64: =IF($B64<=TODAY(),SUMIF('Stats 2020'!$M$24:$M$1048576,"<="&Graphs!$B64,'Stats 2020'!O$24:O$1048576),NA()) -> 212.25 | D64: =IF($B64<=TODAY(),MAX($C64,$E64,$G64,$H64)+11+16.5,NA()) -> 239.75 | E64: =IF($B64<=TODAY(),SUMIF('Stats 2020'!$M$24:$M$1048576,"<="&Graphs!$B64,'Stats 2020'!Q$24:Q$1048576),NA()) -> 171 | F64: =IF($B64<=TODAY(),MAX($C64,$E64,$G64,$H64)+11+16.5,NA()) -> 239.75 | G64: =IF($B64<=TODAY(),SUMIF('Stats 2020'!$M$24:$M$1048576,"<="&Graphs!$B64,'Stats 2020'!S$24:S$1048576),NA()) -> 176.5 | H64: =IF($B64<=TODAY(),SUMIF('Stats 2020'!$M$24:$M$1048576,"<="&Graphs!$B64,'Stats 2020'!T$24:T$1048576),NA()) -> 123.75 | I64: =VLOOKUP($A64,$B$1:$H$59,MATCH(I$1,$B$1:$H$1,0),0) -> #N/A | J64: =VLOOKUP($A64,$B$1:$H$59,MATCH(J$1,$B$1:$H$1,0),0) -> #N/A | K64: =VLOOKUP($A64,$B$1:$H$59,MATCH(K$1,$B$1:$H$1,0),0) -> #N/A | L64: =VLOOKUP($A64,$B$1:$H$59,MATCH(L$1,$B$1:$H$1,0),0) -> #N/A | M64: =VLOOKUP($A64,$B$1:$H$59,MATCH(M$1,$B$1:$H$1,0),0) -> #N/A | N64: =VLOOKUP($A64,$B$1:$H$59,MATCH(N$1,$B$1:$H$1,0),0) -> #N/A | X64: =B64 -> 44288 | Y64: =SUM(Q$2:Q64)/COUNTA($P$2:$P64) -> 0.78688525 | Z64: =SUM(R$2:R64)/COUNTA($P$2:$P64) -> 0.32786885 | AA64: =SUM(S$2:S64)/COUNTA($P$2:$P64) -> 0.78688525 | AB64: =SUM(T$2:T64)/COUNTA($P$2:$P64) -> 0.36065574 | AC64: =SUM(U$2:U64)/COUNTA($P$2:$P64) -> 0.78688525 | AD64: =SUM(V$2:V64)/COUNTA($P$2:$P64) -> 0.86885246 | AE64: =AVERAGE(Y64:AD64) -> 0.65300546 | AF64: =VLOOKUP($A64,$X$1:$AE$59,MATCH(AF$1,$X$1:$AE$1,0),0) -> #N/A | AG64: =VLOOKUP($A64,$X$1:$AE$59,MATCH(AG$1,$X$1:$AE$1,0),0) -> #N/A | AH64: =VLOOKUP($A64,$X$1:$AE$59,MATCH(AH$1,$X$1:$AE$1,0),0) -> #N/A | AI64: =VLOOKUP($A64,$X$1:$AE$59,MATCH(AI$1,$X$1:$AE$1,0),0) -> #N/A | AJ64: =VLOOKUP($A64,$X$1:$AE$59,MATCH(AJ$1,$X$1:$AE$1,0),0) -> #N/A | AK64: =VLOOKUP($A64,$X$1:$AE$59,MATCH(AK$1,$X$1:$AE$1,0),0) -> #N/A | AL64: =VLOOKUP($A64,$X$1:$AE$59,MATCH(AL$1,$X$1:$AE$1,0),0) -> #N/A
A65: =IF(AND((TODAY()-B65)<7,(TODAY()-B65>=0)),B65,NA()) -> #N/A | B65: =B64+7 -> 44295 | C65: =IF($B65<=TODAY(),SUMIF('Stats 2020'!$M$24:$M$1048576,"<="&Graphs!$B65,'Stats 2020'!O$24:O$1048576),NA()) -> 212.25 | D65: =IF($B65<=TODAY(),MAX($C65,$E65,$G65,$H65)+11+16.5,NA()) -> 239.75 | E65: =IF($B65<=TODAY(),SUMIF('Stats 2020'!$M$24:$M$1048576,"<="&Graphs!$B65,'Stats 2020'!Q$24:Q$1048576),NA()) -> 171 | F65: =IF($B65<=TODAY(),MAX($C65,$E65,$G65,$H65)+11+16.5,NA()) -> 239.75 | G65: =IF($B65<=TODAY(),SUMIF('Stats 2020'!$M$24:$M$1048576,"<="&Graphs!$B65,'Stats 2020'!S$24:S$1048576),NA()) -> 176.5 | H65: =IF($B65<=TODAY(),SUMIF('Stats 2020'!$M$24:$M$1048576,"<="&Graphs!$B65,'Stats 2020'!T$24:T$1048576),NA()) -> 123.75 | I65: =VLOOKUP($A65,$B$1:$H$59,MATCH(I$1,$B$1:$H$1,0),0) -> #N/A | J65: =VLOOKUP($A65,$B$1:$H$59,MATCH(J$1,$B$1:$H$1,0),0) -> #N/A | K65: =VLOOKUP($A65,$B$1:$H$59,MATCH(K$1,$B$1:$H$1,0),0) -> #N/A | L65: =VLOOKUP($A65,$B$1:$H$59,MATCH(L$1,$B$1:$H$1,0),0) -> #N/A | M65: =VLOOKUP($A65,$B$1:$H$59,MATCH(M$1,$B$1:$H$1,0),0) -> #N/A | N65: =VLOOKUP($A65,$B$1:$H$59,MATCH(N$1,$B$1:$H$1,0),0) -> #N/A | Q65: =VLOOKUP($B65,'Stats 2020'!$D$25:$J$200,MATCH(Graphs!Q$1,'Stats 2020'!$D$18:$J$18,0),0) -> 1 | R65: =VLOOKUP($B65,'Stats 2020'!$D$25:$J$200,MATCH(Graphs!R$1,'Stats 2020'!$D$18:$J$18,0),0) -> 1 | S65: =VLOOKUP($B65,'Stats 2020'!$D$25:$J$200,MATCH(Graphs!S$1,'Stats 2020'!$D$18:$J$18,0),0) -> 1 | T65: =VLOOKUP($B65,'Stats 2020'!$D$25:$J$200,MATCH(Graphs!T$1,'Stats 2020'!$D$18:$J$18,0),0) -> 1 | U65: =VLOOKUP($B65,'Stats 2020'!$D$25:$J$200,MATCH(Graphs!U$1,'Stats 2020'!$D$18:$J$18,0),0) -> 1 | V65: =VLOOKUP($B65,'Stats 2020'!$D$25:$J$200,MATCH(Graphs!V$1,'Stats 2020'!$D$18:$J$18,0),0) -> 1 | X65: =B65 -> 44295 | Y65: =SUM(Q$2:Q65)/COUNTA($P$2:$P65) -> 0.80327869 | Z65: =SUM(R$2:R65)/COUNTA($P$2:$P65) -> 0.3442623 | AA65: =SUM(S$2:S65)/COUNTA($P$2:$P65) -> 0.80327869 | AB65: =SUM(T$2:T65)/COUNTA($P$2:$P65) -> 0.37704918 | AC65: =SUM(U$2:U65)/COUNTA($P$2:$P65) -> 0.80327869 | AD65: =SUM(V$2:V65)/COUNTA($P$2:$P65) -> 0.8852459 | AE65: =AVERAGE(Y65:AD65) -> 0.66939891 | AF65: =VLOOKUP($A65,$X$1:$AE$59,MATCH(AF$1,$X$1:$AE$1,0),0) -> #N/A | AG65: =VLOOKUP($A65,$X$1:$AE$59,MATCH(AG$1,$X$1:$AE$1,0),0) -> #N/A | AH65: =VLOOKUP($A65,$X$1:$AE$59,MATCH(AH$1,$X$1:$AE$1,0),0) -> #N/A | AI65: =VLOOKUP($A65,$X$1:$AE$59,MATCH(AI$1,$X$1:$AE$1,0),0) -> #N/A | AJ65: =VLOOKUP($A65,$X$1:$AE$59,MATCH(AJ$1,$X$1:$AE$1,0),0) -> #N/A | AK65: =VLOOKUP($A65,$X$1:$AE$59,MATCH(AK$1,$X$1:$AE$1,0),0) -> #N/A | AL65: =VLOOKUP($A65,$X$1:$AE$59,MATCH(AL$1,$X$1:$AE$1,0),0) -> #N/A
A66: =IF(AND((TODAY()-B66)<7,(TODAY()-B66>=0)),B66,NA()) -> #N/A | B66: =B65+7 -> 44302 | C66: =IF($B66<=TODAY(),SUMIF('Stats 2020'!$M$24:$M$1048576,"<="&Graphs!$B66,'Stats 2020'!O$24:O$1048576),NA()) -> 212.25 | D66: =IF($B66<=TODAY(),MAX($C66,$E66,$G66,$H66)+11+16.5,NA()) -> 239.75 | E66: =IF($B66<=TODAY(),SUMIF('Stats 2020'!$M$24:$M$1048576,"<="&Graphs!$B66,'Stats 2020'!Q$24:Q$1048576),NA()) -> 171 | F66: =IF($B66<=TODAY(),MAX($C66,$E66,$G66,$H66)+11+16.5,NA()) -> 239.75 | G66: =IF($B66<=TODAY(),SUMIF('Stats 2020'!$M$24:$M$1048576,"<="&Graphs!$B66,'Stats 2020'!S$24:S$1048576),NA()) -> 176.5 | H66: =IF($B66<=TODAY(),SUMIF('Stats 2020'!$M$24:$M$1048576,"<="&Graphs!$B66,'Stats 2020'!T$24:T$1048576),NA()) -> 123.75 | I66: =VLOOKUP($A66,$B$1:$H$59,MATCH(I$1,$B$1:$H$1,0),0) -> #N/A | J66: =VLOOKUP($A66,$B$1:$H$59,MATCH(J$1,$B$1:$H$1,0),0) -> #N/A | K66: =VLOOKUP($A66,$B$1:$H$59,MATCH(K$1,$B$1:$H$1,0),0) -> #N/A | L66: =VLOOKUP($A66,$B$1:$H$59,MATCH(L$1,$B$1:$H$1,0),0) -> #N/A | M66: =VLOOKUP($A66,$B$1:$H$59,MATCH(M$1,$B$1:$H$1,0),0) -> #N/A | N66: =VLOOKUP($A66,$B$1:$H$59,MATCH(N$1,$B$1:$H$1,0),0) -> #N/A | P66: =B67 -> 44309 | Q66: =VLOOKUP($B67,'Stats 2020'!$D$25:$J$89,MATCH(Graphs!Q$1,'Stats 2020'!$D$18:$J$18,0),0) -> #N/A | R66: =VLOOKUP($B67,'Stats 2020'!$D$25:$J$89,MATCH(Graphs!R$1,'Stats 2020'!$D$18:$J$18,0),0) -> #N/A | S66: =VLOOKUP($B67,'Stats 2020'!$D$25:$J$89,MATCH(Graphs!S$1,'Stats 2020'!$D$18:$J$18,0),0) -> #N/A | T66: =VLOOKUP($B67,'Stats 2020'!$D$25:$J$89,MATCH(Graphs!T$1,'Stats 2020'!$D$18:$J$18,0),0) -> #N/A | U66: =VLOOKUP($B67,'Stats 2020'!$D$25:$J$89,MATCH(Graphs!U$1,'Stats 2020'!$D$18:$J$18,0),0) -> #N/A | V66: =VLOOKUP($B67,'Stats 2020'!$D$25:$J$89,MATCH(Graphs!V$1,'Stats 2020'!$D$18:$J$18,0),0) -> #N/A | X66: =B66 -> 44302 | Y66: =SUM(Q$2:Q66)/COUNTA($P$2:$P66) -> #N/A | Z66: =SUM(R$2:R66)/COUNTA($P$2:$P66) -> #N/A | AA66: =SUM(S$2:S66)/COUNTA($P$2:$P66) -> #N/A | AB66: =SUM(T$2:T66)/COUNTA($P$2:$P66) -> #N/A | AC66: =SUM(U$2:U66)/COUNTA($P$2:$P66) -> #N/A | AD66: =SUM(V$2:V66)/COUNTA($P$2:$P66) -> #N/A | AE66: =AVERAGE(Y66:AD66) -> #N/A | AF66: =VLOOKUP($A66,$X$1:$AE$59,MATCH(AF$1,$X$1:$AE$1,0),0) -> #N/A | AG66: =VLOOKUP($A66,$X$1:$AE$59,MATCH(AG$1,$X$1:$AE$1,0),0) -> #N/A | AH66: =VLOOKUP($A66,$X$1:$AE$59,MATCH(AH$1,$X$1:$AE$1,0),0) -> #N/A | AI66: =VLOOKUP($A66,$X$1:$AE$59,MATCH(AI$1,$X$1:$AE$1,0),0) -> #N/A | AJ66: =VLOOKUP($A66,$X$1:$AE$59,MATCH(AJ$1,$X$1:$AE$1,0),0) -> #N/A | AK66: =VLOOKUP($A66,$X$1:$AE$59,MATCH(AK$1,$X$1:$AE$1,0),0) -> #N/A | AL66: =VLOOKUP($A66,$X$1:$AE$59,MATCH(AL$1,$X$1:$AE$1,0),0) -> #N/A
A67: =IF(AND((TODAY()-B67)<7,(TODAY()-B67>=0)),B67,NA()) -> #N/A | B67: =B66+7 -> 44309 | C67: =IF($B67<=TODAY(),SUMIF('Stats 2020'!$M$24:$M$1048576,"<="&Graphs!$B67,'Stats 2020'!O$24:O$1048576),NA()) -> 212.25 | D67: =IF($B67<=TODAY(),MAX($C67,$E67,$G67,$H67)+11+16.5,NA()) -> 239.75 | E67: =IF($B67<=TODAY(),SUMIF('Stats 2020'!$M$24:$M$1048576,"<="&Graphs!$B67,'Stats 2020'!Q$24:Q$1048576),NA()) -> 171 | F67: =IF($B67<=TODAY(),MAX($C67,$E67,$G67,$H67)+11+16.5,NA()) -> 239.75 | G67: =IF($B67<=TODAY(),SUMIF('Stats 2020'!$M$24:$M$1048576,"<="&Graphs!$B67,'Stats 2020'!S$24:S$1048576),NA()) -> 176.5 | H67: =IF($B67<=TODAY(),SUMIF('Stats 2020'!$M$24:$M$1048576,"<="&Graphs!$B67,'Stats 2020'!T$24:T$1048576),NA()) -> 123.75 | I67: =VLOOKUP($A67,$B$1:$H$59,MATCH(I$1,$B$1:$H$1,0),0) -> #N/A | J67: =VLOOKUP($A67,$B$1:$H$59,MATCH(J$1,$B$1:$H$1,0),0) -> #N/A | K67: =VLOOKUP($A67,$B$1:$H$59,MATCH(K$1,$B$1:$H$1,0),0) -> #N/A | L67: =VLOOKUP($A67,$B$1:$H$59,MATCH(L$1,$B$1:$H$1,0),0) -> #N/A | M67: =VLOOKUP($A67,$B$1:$H$59,MATCH(M$1,$B$1:$H$1,0),0) -> #N/A | N67: =VLOOKUP($A67,$B$1:$H$59,MATCH(N$1,$B$1:$H$1,0),0) -> #N/A | X67: =B67 -> 44309 | Y67: =SUM(Q$2:Q67)/COUNTA($P$2:$P67) -> #N/A | Z67: =SUM(R$2:R67)/COUNTA($P$2:$P67) -> #N/A | AA67: =SUM(S$2:S67)/COUNTA($P$2:$P67) -> #N/A | AB67: =SUM(T$2:T67)/COUNTA($P$2:$P67) -> #N/A | AC67: =SUM(U$2:U67)/COUNTA($P$2:$P67) -> #N/A | AD67: =SUM(V$2:V67)/COUNTA($P$2:$P67) -> #N/A | AE67: =AVERAGE(Y67:AD67) -> #N/A | AF67: =VLOOKUP($A67,$X$1:$AE$59,MATCH(AF$1,$X$1:$AE$1,0),0) -> #N/A | AG67: =VLOOKUP($A67,$X$1:$AE$59,MATCH(AG$1,$X$1:$AE$1,0),0) -> #N/A | AH67: =VLOOKUP($A67,$X$1:$AE$59,MATCH(AH$1,$X$1:$AE$1,0),0) -> #N/A | AI67: =VLOOKUP($A67,$X$1:$AE$59,MATCH(AI$1,$X$1:$AE$1,0),0) -> #N/A | AJ67: =VLOOKUP($A67,$X$1:$AE$59,MATCH(AJ$1,$X$1:$AE$1,0),0) -> #N/A | AK67: =VLOOKUP($A67,$X$1:$AE$59,MATCH(AK$1,$X$1:$AE$1,0),0) -> #N/A | AL67: =VLOOKUP($A67,$X$1:$AE$59,MATCH(AL$1,$X$1:$AE$1,0),0) -> #N/A
A68: =IF(AND((TODAY()-B68)<7,(TODAY()-B68>=0)),B68,NA()) -> #N/A | B68: =B67+7 -> 44316 | C68: =IF($B68<=TODAY(),SUMIF('Stats 2020'!$M$24:$M$1048576,"<="&Graphs!$B68,'Stats 2020'!O$24:O$1048576),NA()) -> 212.25 | D68: =IF($B68<=TODAY(),MAX($C68,$E68,$G68,$H68)+11+16.5,NA()) -> 239.75 | E68: =IF($B68<=TODAY(),SUMIF('Stats 2020'!$M$24:$M$1048576,"<="&Graphs!$B68,'Stats 2020'!Q$24:Q$1048576),NA()) -> 182 | F68: =IF($B68<=TODAY(),MAX($C68,$E68,$G68,$H68)+11+16.5,NA()) -> 239.75 | G68: =IF($B68<=TODAY(),SUMIF('Stats 2020'!$M$24:$M$1048576,"<="&Graphs!$B68,'Stats 2020'!S$24:S$1048576),NA()) -> 176.5 | H68: =IF($B68<=TODAY(),SUMIF('Stats 2020'!$M$24:$M$1048576,"<="&Graphs!$B68,'Stats 2020'!T$24:T$1048576),NA()) -> 123.75 | I68: =VLOOKUP($A68,$B$1:$H$59,MATCH(I$1,$B$1:$H$1,0),0) -> #N/A | J68: =VLOOKUP($A68,$B$1:$H$59,MATCH(J$1,$B$1:$H$1,0),0) -> #N/A | K68: =VLOOKUP($A68,$B$1:$H$59,MATCH(K$1,$B$1:$H$1,0),0) -> #N/A | L68: =VLOOKUP($A68,$B$1:$H$59,MATCH(L$1,$B$1:$H$1,0),0) -> #N/A | M68: =VLOOKUP($A68,$B$1:$H$59,MATCH(M$1,$B$1:$H$1,0),0) -> #N/A | N68: =VLOOKUP($A68,$B$1:$H$59,MATCH(N$1,$B$1:$H$1,0),0) -> #N/A | P68: =B69 -> 44323 | Q68: =VLOOKUP($B69,'Stats 2020'!$D$25:$J$89,MATCH(Graphs!Q$1,'Stats 2020'!$D$18:$J$18,0),0) -> #N/A | R68: =VLOOKUP($B69,'Stats 2020'!$D$25:$J$89,MATCH(Graphs!R$1,'Stats 2020'!$D$18:$J$18,0),0) -> #N/A | S68: =VLOOKUP($B69,'Stats 2020'!$D$25:$J$89,MATCH(Graphs!S$1,'Stats 2020'!$D$18:$J$18,0),0) -> #N/A | T68: =VLOOKUP($B69,'Stats 2020'!$D$25:$J$89,MATCH(Graphs!T$1,'Stats 2020'!$D$18:$J$18,0),0) -> #N/A | U68: =VLOOKUP($B69,'Stats 2020'!$D$25:$J$89,MATCH(Graphs!U$1,'Stats 2020'!$D$18:$J$18,0),0) -> #N/A | V68: =VLOOKUP($B69,'Stats 2020'!$D$25:$J$89,MATCH(Graphs!V$1,'Stats 2020'!$D$18:$J$18,0),0) -> #N/A | X68: =B68 -> 44316 | Y68: =SUM(Q$2:Q68)/COUNTA($P$2:$P68) -> #N/A | Z68: =SUM(R$2:R68)/COUNTA($P$2:$P68) -> #N/A | AA68: =SUM(S$2:S68)/COUNTA($P$2:$P68) -> #N/A | AB68: =SUM(T$2:T68)/COUNTA($P$2:$P68) -> #N/A | AC68: =SUM(U$2:U68)/COUNTA($P$2:$P68) -> #N/A | AD68: =SUM(V$2:V68)/COUNTA($P$2:$P68) -> #N/A | AE68: =AVERAGE(Y68:AD68) -> #N/A | AF68: =VLOOKUP($A68,$X$1:$AE$59,MATCH(AF$1,$X$1:$AE$1,0),0) -> #N/A | AG68: =VLOOKUP($A68,$X$1:$AE$59,MATCH(AG$1,$X$1:$AE$1,0),0) -> #N/A | AH68: =VLOOKUP($A68,$X$1:$AE$59,MATCH(AH$1,$X$1:$AE$1,0),0) -> #N/A | AI68: =VLOOKUP($A68,$X$1:$AE$59,MATCH(AI$1,$X$1:$AE$1,0),0) -> #N/A | AJ68: =VLOOKUP($A68,$X$1:$AE$59,MATCH(AJ$1,$X$1:$AE$1,0),0) -> #N/A | AK68: =VLOOKUP($A68,$X$1:$AE$59,MATCH(AK$1,$X$1:$AE$1,0),0) -> #N/A | AL68: =VLOOKUP($A68,$X$1:$AE$59,MATCH(AL$1,$X$1:$AE$1,0),0) -> #N/A
A69: =IF(AND((TODAY()-B69)<7,(TODAY()-B69>=0)),B69,NA()) -> #N/A | B69: =B68+7 -> 44323 | C69: =IF($B69<=TODAY(),SUMIF('Stats 2020'!$M$24:$M$1048576,"<="&Graphs!$B69,'Stats 2020'!O$24:O$1048576),NA()) -> 212.25 | D69: =IF($B69<=TODAY(),MAX($C69,$E69,$G69,$H69)+11+16.5,NA()) -> 239.75 | E69: =IF($B69<=TODAY(),SUMIF('Stats 2020'!$M$24:$M$1048576,"<="&Graphs!$B69,'Stats 2020'!Q$24:Q$1048576),NA()) -> 182 | F69: =IF($B69<=TODAY(),MAX($C69,$E69,$G69,$H69)+11+16.5,NA()) -> 239.75 | G69: =IF($B69<=TODAY(),SUMIF('Stats 2020'!$M$24:$M$1048576,"<="&Graphs!$B69,'Stats 2020'!S$24:S$1048576),NA()) -> 187.5 | H69: =IF($B69<=TODAY(),SUMIF('Stats 2020'!$M$24:$M$1048576,"<="&Graphs!$B69,'Stats 2020'!T$24:T$1048576),NA()) -> 123.75 | I69: =VLOOKUP($A69,$B$1:$H$59,MATCH(I$1,$B$1:$H$1,0),0) -> #N/A | J69: =VLOOKUP($A69,$B$1:$H$59,MATCH(J$1,$B$1:$H$1,0),0) -> #N/A | K69: =VLOOKUP($A69,$B$1:$H$59,MATCH(K$1,$B$1:$H$1,0),0) -> #N/A | L69: =VLOOKUP($A69,$B$1:$H$59,MATCH(L$1,$B$1:$H$1,0),0) -> #N/A | M69: =VLOOKUP($A69,$B$1:$H$59,MATCH(M$1,$B$1:$H$1,0),0) -> #N/A | N69: =VLOOKUP($A69,$B$1:$H$59,MATCH(N$1,$B$1:$H$1,0),0) -> #N/A | X69: =B69 -> 44323 | Y69: =SUM(Q$2:Q69)/COUNTA($P$2:$P69) -> #N/A | Z69: =SUM(R$2:R69)/COUNTA($P$2:$P69) -> #N/A | AA69: =SUM(S$2:S69)/COUNTA($P$2:$P69) -> #N/A | AB69: =SUM(T$2:T69)/COUNTA($P$2:$P69) -> #N/A | AC69: =SUM(U$2:U69)/COUNTA($P$2:$P69) -> #N/A | AD69: =SUM(V$2:V69)/COUNTA($P$2:$P69) -> #N/A | AE69: =AVERAGE(Y69:AD69) -> #N/A | AF69: =VLOOKUP($A69,$X$1:$AE$59,MATCH(AF$1,$X$1:$AE$1,0),0) -> #N/A | AG69: =VLOOKUP($A69,$X$1:$AE$59,MATCH(AG$1,$X$1:$AE$1,0),0) -> #N/A | AH69: =VLOOKUP($A69,$X$1:$AE$59,MATCH(AH$1,$X$1:$AE$1,0),0) -> #N/A | AI69: =VLOOKUP($A69,$X$1:$AE$59,MATCH(AI$1,$X$1:$AE$1,0),0) -> #N/A | AJ69: =VLOOKUP($A69,$X$1:$AE$59,MATCH(AJ$1,$X$1:$AE$1,0),0) -> #N/A | AK69: =VLOOKUP($A69,$X$1:$AE$59,MATCH(AK$1,$X$1:$AE$1,0),0) -> #N/A | AL69: =VLOOKUP($A69,$X$1:$AE$59,MATCH(AL$1,$X$1:$AE$1,0),0) -> #N/A
A70: =IF(AND((TODAY()-B70)<7,(TODAY()-B70>=0)),B70,NA()) -> #N/A | B70: =B69+7 -> 44330 | C70: =IF($B70<=TODAY(),SUMIF('Stats 2020'!$M$24:$M$1048576,"<="&Graphs!$B70,'Stats 2020'!O$24:O$1048576),NA()) -> 215 | D70: =IF($B70<=TODAY(),MAX($C70,$E70,$G70,$H70)+11+16.5,NA()) -> 242.5 | E70: =IF($B70<=TODAY(),SUMIF('Stats 2020'!$M$24:$M$1048576,"<="&Graphs!$B70,'Stats 2020'!Q$24:Q$1048576),NA()) -> 182 | F70: =IF($B70<=TODAY(),MAX($C70,$E70,$G70,$H70)+11+16.5,NA()) -> 242.5 | G70: =IF($B70<=TODAY(),SUMIF('Stats 2020'!$M$24:$M$1048576,"<="&Graphs!$B70,'Stats 2020'!S$24:S$1048576),NA()) -> 187.5 | H70: =IF($B70<=TODAY(),SUMIF('Stats 2020'!$M$24:$M$1048576,"<="&Graphs!$B70,'Stats 2020'!T$24:T$1048576),NA()) -> 123.75 | I70: =VLOOKUP($A70,$B$1:$H$59,MATCH(I$1,$B$1:$H$1,0),0) -> #N/A | J70: =VLOOKUP($A70,$B$1:$H$59,MATCH(J$1,$B$1:$H$1,0),0) -> #N/A | K70: =VLOOKUP($A70,$B$1:$H$59,MATCH(K$1,$B$1:$H$1,0),0) -> #N/A | L70: =VLOOKUP($A70,$B$1:$H$59,MATCH(L$1,$B$1:$H$1,0),0) -> #N/A | M70: =VLOOKUP($A70,$B$1:$H$59,MATCH(M$1,$B$1:$H$1,0),0) -> #N/A | N70: =VLOOKUP($A70,$B$1:$H$59,MATCH(N$1,$B$1:$H$1,0),0) -> #N/A | P70: =B71 -> 44337 | Q70: =VLOOKUP($B71,'Stats 2020'!$D$25:$J$89,MATCH(Graphs!Q$1,'Stats 2020'!$D$18:$J$18,0),0) -> #N/A | R70: =VLOOKUP($B71,'Stats 2020'!$D$25:$J$89,MATCH(Graphs!R$1,'Stats 2020'!$D$18:$J$18,0),0) -> #N/A | S70: =VLOOKUP($B71,'Stats 2020'!$D$25:$J$89,MATCH(Graphs!S$1,'Stats 2020'!$D$18:$J$18,0),0) -> #N/A | T70: =VLOOKUP($B71,'Stats 2020'!$D$25:$J$89,MATCH(Graphs!T$1,'Stats 2020'!$D$18:$J$18,0),0) -> #N/A | U70: =VLOOKUP($B71,'Stats 2020'!$D$25:$J$89,MATCH(Graphs!U$1,'Stats 2020'!$D$18:$J$18,0),0) -> #N/A | V70: =VLOOKUP($B71,'Stats 2020'!$D$25:$J$89,MATCH(Graphs!V$1,'Stats 2020'!$D$18:$J$18,0),0) -> #N/A | X70: =B70 -> 44330 | Y70: =SUM(Q$2:Q70)/COUNTA($P$2:$P70) -> #N/A | Z70: =SUM(R$2:R70)/COUNTA($P$2:$P70) -> #N/A | AA70: =SUM(S$2:S70)/COUNTA($P$2:$P70) -> #N/A | AB70: =SUM(T$2:T70)/COUNTA($P$2:$P70) -> #N/A | AC70: =SUM(U$2:U70)/COUNTA($P$2:$P70) -> #N/A | AD70: =SUM(V$2:V70)/COUNTA($P$2:$P70) -> #N/A | AE70: =AVERAGE(Y70:AD70) -> #N/A | AF70: =VLOOKUP($A70,$X$1:$AE$59,MATCH(AF$1,$X$1:$AE$1,0),0) -> #N/A | AG70: =VLOOKUP($A70,$X$1:$AE$59,MATCH(AG$1,$X$1:$AE$1,0),0) -> #N/A | AH70: =VLOOKUP($A70,$X$1:$AE$59,MATCH(AH$1,$X$1:$AE$1,0),0) -> #N/A | AI70: =VLOOKUP($A70,$X$1:$AE$59,MATCH(AI$1,$X$1:$AE$1,0),0) -> #N/A | AJ70: =VLOOKUP($A70,$X$1:$AE$59,MATCH(AJ$1,$X$1:$AE$1,0),0) -> #N/A | AK70: =VLOOKUP($A70,$X$1:$AE$59,MATCH(AK$1,$X$1:$AE$1,0),0) -> #N/A | AL70: =VLOOKUP($A70,$X$1:$AE$59,MATCH(AL$1,$X$1:$AE$1,0),0) -> #N/A
A71: =IF(AND((TODAY()-B71)<7,(TODAY()-B71>=0)),B71,NA()) -> #N/A | B71: =B70+7 -> 44337 | C71: =IF($B71<=TODAY(),SUMIF('Stats 2020'!$M$24:$M$1048576,"<="&Graphs!$B71,'Stats 2020'!O$24:O$1048576),NA()) -> 215 | D71: =IF($B71<=TODAY(),MAX($C71,$E71,$G71,$H71)+11+16.5,NA()) -> 242.5 | E71: =IF($B71<=TODAY(),SUMIF('Stats 2020'!$M$24:$M$1048576,"<="&Graphs!$B71,'Stats 2020'!Q$24:Q$1048576),NA()) -> 193 | F71: =IF($B71<=TODAY(),MAX($C71,$E71,$G71,$H71)+11+16.5,NA()) -> 242.5 | G71: =IF($B71<=TODAY(),SUMIF('Stats 2020'!$M$24:$M$1048576,"<="&Graphs!$B71,'Stats 2020'!S$24:S$1048576),NA()) -> 187.5 | H71: =IF($B71<=TODAY(),SUMIF('Stats 2020'!$M$24:$M$1048576,"<="&Graphs!$B71,'Stats 2020'!T$24:T$1048576),NA()) -> 123.75 | I71: =VLOOKUP($A71,$B$1:$H$59,MATCH(I$1,$B$1:$H$1,0),0) -> #N/A | J71: =VLOOKUP($A71,$B$1:$H$59,MATCH(J$1,$B$1:$H$1,0),0) -> #N/A | K71: =VLOOKUP($A71,$B$1:$H$59,MATCH(K$1,$B$1:$H$1,0),0) -> #N/A | L71: =VLOOKUP($A71,$B$1:$H$59,MATCH(L$1,$B$1:$H$1,0),0) -> #N/A | M71: =VLOOKUP($A71,$B$1:$H$59,MATCH(M$1,$B$1:$H$1,0),0) -> #N/A | N71: =VLOOKUP($A71,$B$1:$H$59,MATCH(N$1,$B$1:$H$1,0),0) -> #N/A | X71: =B71 -> 44337 | Y71: =SUM(Q$2:Q71)/COUNTA($P$2:$P71) -> #N/A | Z71: =SUM(R$2:R71)/COUNTA($P$2:$P71) -> #N/A | AA71: =SUM(S$2:S71)/COUNTA($P$2:$P71) -> #N/A | AB71: =SUM(T$2:T71)/COUNTA($P$2:$P71) -> #N/A | AC71: =SUM(U$2:U71)/COUNTA($P$2:$P71) -> #N/A | AD71: =SUM(V$2:V71)/COUNTA($P$2:$P71) -> #N/A | AE71: =AVERAGE(Y71:AD71) -> #N/A | AF71: =VLOOKUP($A71,$X$1:$AE$59,MATCH(AF$1,$X$1:$AE$1,0),0) -> #N/A | AG71: =VLOOKUP($A71,$X$1:$AE$59,MATCH(AG$1,$X$1:$AE$1,0),0) -> #N/A | AH71: =VLOOKUP($A71,$X$1:$AE$59,MATCH(AH$1,$X$1:$AE$1,0),0) -> #N/A | AI71: =VLOOKUP($A71,$X$1:$AE$59,MATCH(AI$1,$X$1:$AE$1,0),0) -> #N/A | AJ71: =VLOOKUP($A71,$X$1:$AE$59,MATCH(AJ$1,$X$1:$AE$1,0),0) -> #N/A | AK71: =VLOOKUP($A71,$X$1:$AE$59,MATCH(AK$1,$X$1:$AE$1,0),0) -> #N/A | AL71: =VLOOKUP($A71,$X$1:$AE$59,MATCH(AL$1,$X$1:$AE$1,0),0) -> #N/A
A72: =IF(AND((TODAY()-B72)<7,(TODAY()-B72>=0)),B72,NA()) -> #N/A | B72: =B71+7 -> 44344 | C72: =IF($B72<=TODAY(),SUMIF('Stats 2020'!$M$24:$M$1048576,"<="&Graphs!$B72,'Stats 2020'!O$24:O$1048576),NA()) -> 215 | D72: =IF($B72<=TODAY(),MAX($C72,$E72,$G72,$H72)+11+16.5,NA()) -> 242.5 | E72: =IF($B72<=TODAY(),SUMIF('Stats 2020'!$M$24:$M$1048576,"<="&Graphs!$B72,'Stats 2020'!Q$24:Q$1048576),NA()) -> 193 | F72: =IF($B72<=TODAY(),MAX($C72,$E72,$G72,$H72)+11+16.5,NA()) -> 242.5 | G72: =IF($B72<=TODAY(),SUMIF('Stats 2020'!$M$24:$M$1048576,"<="&Graphs!$B72,'Stats 2020'!S$24:S$1048576),NA()) -> 187.5 | H72: =IF($B72<=TODAY(),SUMIF('Stats 2020'!$M$24:$M$1048576,"<="&Graphs!$B72,'Stats 2020'!T$24:T$1048576),NA()) -> 123.75 | I72: =VLOOKUP($A72,$B$1:$H$59,MATCH(I$1,$B$1:$H$1,0),0) -> #N/A | J72: =VLOOKUP($A72,$B$1:$H$59,MATCH(J$1,$B$1:$H$1,0),0) -> #N/A | K72: =VLOOKUP($A72,$B$1:$H$59,MATCH(K$1,$B$1:$H$1,0),0) -> #N/A | L72: =VLOOKUP($A72,$B$1:$H$59,MATCH(L$1,$B$1:$H$1,0),0) -> #N/A | M72: =VLOOKUP($A72,$B$1:$H$59,MATCH(M$1,$B$1:$H$1,0),0) -> #N/A | N72: =VLOOKUP($A72,$B$1:$H$59,MATCH(N$1,$B$1:$H$1,0),0) -> #N/A | P72: =B73 -> 44351 | Q72: =VLOOKUP($B73,'Stats 2020'!$D$25:$J$89,MATCH(Graphs!Q$1,'Stats 2020'!$D$18:$J$18,0),0) -> #N/A | R72: =VLOOKUP($B73,'Stats 2020'!$D$25:$J$89,MATCH(Graphs!R$1,'Stats 2020'!$D$18:$J$18,0),0) -> #N/A | S72: =VLOOKUP($B73,'Stats 2020'!$D$25:$J$89,MATCH(Graphs!S$1,'Stats 2020'!$D$18:$J$18,0),0) -> #N/A | T72: =VLOOKUP($B73,'Stats 2020'!$D$25:$J$89,MATCH(Graphs!T$1,'Stats 2020'!$D$18:$J$18,0),0) -> #N/A | U72: =VLOOKUP($B73,'Stats 2020'!$D$25:$J$89,MATCH(Graphs!U$1,'Stats 2020'!$D$18:$J$18,0),0) -> #N/A | V72: =VLOOKUP($B73,'Stats 2020'!$D$25:$J$89,MATCH(Graphs!V$1,'Stats 2020'!$D$18:$J$18,0),0) -> #N/A | X72: =B72 -> 44344 | Y72: =SUM(Q$2:Q72)/COUNTA($P$2:$P72) -> #N/A | Z72: =SUM(R$2:R72)/COUNTA($P$2:$P72) -> #N/A | AA72: =SUM(S$2:S72)/COUNTA($P$2:$P72) -> #N/A | AB72: =SUM(T$2:T72)/COUNTA($P$2:$P72) -> #N/A | AC72: =SUM(U$2:U72)/COUNTA($P$2:$P72) -> #N/A | AD72: =SUM(V$2:V72)/COUNTA($P$2:$P72) -> #N/A | AE72: =AVERAGE(Y72:AD72) -> #N/A | AF72: =VLOOKUP($A72,$X$1:$AE$59,MATCH(AF$1,$X$1:$AE$1,0),0) -> #N/A | AG72: =VLOOKUP($A72,$X$1:$AE$59,MATCH(AG$1,$X$1:$AE$1,0),0) -> #N/A | AH72: =VLOOKUP($A72,$X$1:$AE$59,MATCH(AH$1,$X$1:$AE$1,0),0) -> #N/A | AI72: =VLOOKUP($A72,$X$1:$AE$59,MATCH(AI$1,$X$1:$AE$1,0),0) -> #N/A | AJ72: =VLOOKUP($A72,$X$1:$AE$59,MATCH(AJ$1,$X$1:$AE$1,0),0) -> #N/A | AK72: =VLOOKUP($A72,$X$1:$AE$59,MATCH(AK$1,$X$1:$AE$1,0),0) -> #N/A | AL72: =VLOOKUP($A72,$X$1:$AE$59,MATCH(AL$1,$X$1:$AE$1,0),0) -> #N/A
A73: =IF(AND((TODAY()-B73)<7,(TODAY()-B73>=0)),B73,NA()) -> #N/A | B73: =B72+7 -> 44351 | C73: =IF($B73<=TODAY(),SUMIF('Stats 2020'!$M$24:$M$1048576,"<="&Graphs!$B73,'Stats 2020'!O$24:O$1048576),NA()) -> 215 | D73: =IF($B73<=TODAY(),MAX($C73,$E73,$G73,$H73)+11+16.5,NA()) -> 242.5 | E73: =IF($B73<=TODAY(),SUMIF('Stats 2020'!$M$24:$M$1048576,"<="&Graphs!$B73,'Stats 2020'!Q$24:Q$1048576),NA()) -> 193 | F73: =IF($B73<=TODAY(),MAX($C73,$E73,$G73,$H73)+11+16.5,NA()) -> 242.5 | G73: =IF($B73<=TODAY(),SUMIF('Stats 2020'!$M$24:$M$1048576,"<="&Graphs!$B73,'Stats 2020'!S$24:S$1048576),NA()) -> 187.5 | H73: =IF($B73<=TODAY(),SUMIF('Stats 2020'!$M$24:$M$1048576,"<="&Graphs!$B73,'Stats 2020'!T$24:T$1048576),NA()) -> 123.75 | I73: =VLOOKUP($A73,$B$1:$H$59,MATCH(I$1,$B$1:$H$1,0),0) -> #N/A | J73: =VLOOKUP($A73,$B$1:$H$59,MATCH(J$1,$B$1:$H$1,0),0) -> #N/A | K73: =VLOOKUP($A73,$B$1:$H$59,MATCH(K$1,$B$1:$H$1,0),0) -> #N/A | L73: =VLOOKUP($A73,$B$1:$H$59,MATCH(L$1,$B$1:$H$1,0),0) -> #N/A | M73: =VLOOKUP($A73,$B$1:$H$59,MATCH(M$1,$B$1:$H$1,0),0) -> #N/A | N73: =VLOOKUP($A73,$B$1:$H$59,MATCH(N$1,$B$1:$H$1,0),0) -> #N/A | X73: =B73 -> 44351 | Y73: =SUM(Q$2:Q72)/COUNTA($P$2:$P72) -> #N/A | Z73: =SUM(R$2:R72)/COUNTA($P$2:$P72) -> #N/A | AA73: =SUM(S$2:S72)/COUNTA($P$2:$P72) -> #N/A | AB73: =SUM(T$2:T72)/COUNTA($P$2:$P72) -> #N/A | AC73: =SUM(U$2:U72)/COUNTA($P$2:$P72) -> #N/A | AD73: =SUM(V$2:V72)/COUNTA($P$2:$P72) -> #N/A | AE73: =AVERAGE(Y73:AD73) -> #N/A | AF73: =VLOOKUP($A73,$X$1:$AE$59,MATCH(AF$1,$X$1:$AE$1,0),0) -> #N/A | AG73: =VLOOKUP($A73,$X$1:$AE$59,MATCH(AG$1,$X$1:$AE$1,0),0) -> #N/A | AH73: =VLOOKUP($A73,$X$1:$AE$59,MATCH(AH$1,$X$1:$AE$1,0),0) -> #N/A | AI73: =VLOOKUP($A73,$X$1:$AE$59,MATCH(AI$1,$X$1:$AE$1,0),0) -> #N/A | AJ73: =VLOOKUP($A73,$X$1:$AE$59,MATCH(AJ$1,$X$1:$AE$1,0),0) -> #N/A | AK73: =VLOOKUP($A73,$X$1:$AE$59,MATCH(AK$1,$X$1:$AE$1,0),0) -> #N/A | AL73: =VLOOKUP($A73,$X$1:$AE$59,MATCH(AL$1,$X$1:$AE$1,0),0) -> #N/A
A74: =IF(AND((TODAY()-B74)<7,(TODAY()-B74>=0)),B74,NA()) -> #N/A | B74: =B73+7 -> 44358 | C74: =IF($B74<=TODAY(),SUMIF('Stats 2020'!$M$24:$M$1048576,"<="&Graphs!$B74,'Stats 2020'!O$24:O$1048576),NA()) -> 215 | D74: =IF($B74<=TODAY(),MAX($C74,$E74,$G74,$H74)+11+16.5,NA()) -> 242.5 | E74: =IF($B74<=TODAY(),SUMIF('Stats 2020'!$M$24:$M$1048576,"<="&Graphs!$B74,'Stats 2020'!Q$24:Q$1048576),NA()) -> 193 | F74: =IF($B74<=TODAY(),MAX($C74,$E74,$G74,$H74)+11+16.5,NA()) -> 242.5 | G74: =IF($B74<=TODAY(),SUMIF('Stats 2020'!$M$24:$M$1048576,"<="&Graphs!$B74,'Stats 2020'!S$24:S$1048576),NA()) -> 187.5 | H74: =IF($B74<=TODAY(),SUMIF('Stats 2020'!$M$24:$M$1048576,"<="&Graphs!$B74,'Stats 2020'!T$24:T$1048576),NA()) -> 123.75 | I74: =VLOOKUP($A74,$B$1:$H$59,MATCH(I$1,$B$1:$H$1,0),0) -> #N/A | J74: =VLOOKUP($A74,$B$1:$H$59,MATCH(J$1,$B$1:$H$1,0),0) -> #N/A | K74: =VLOOKUP($A74,$B$1:$H$59,MATCH(K$1,$B$1:$H$1,0),0) -> #N/A | L74: =VLOOKUP($A74,$B$1:$H$59,MATCH(L$1,$B$1:$H$1,0),0) -> #N/A | M74: =VLOOKUP($A74,$B$1:$H$59,MATCH(M$1,$B$1:$H$1,0),0) -> #N/A | N74: =VLOOKUP($A74,$B$1:$H$59,MATCH(N$1,$B$1:$H$1,0),0) -> #N/A | P74: =B75 -> 44365 | Q74: =VLOOKUP($B75,'Stats 2020'!$D$25:$J$89,MATCH(Graphs!Q$1,'Stats 2020'!$D$18:$J$18,0),0) -> #N/A | R74: =VLOOKUP($B75,'Stats 2020'!$D$25:$J$89,MATCH(Graphs!R$1,'Stats 2020'!$D$18:$J$18,0),0) -> #N/A | S74: =VLOOKUP($B75,'Stats 2020'!$D$25:$J$89,MATCH(Graphs!S$1,'Stats 2020'!$D$18:$J$18,0),0) -> #N/A | T74: =VLOOKUP($B75,'Stats 2020'!$D$25:$J$89,MATCH(Graphs!T$1,'Stats 2020'!$D$18:$J$18,0),0) -> #N/A | U74: =VLOOKUP($B75,'Stats 2020'!$D$25:$J$89,MATCH(Graphs!U$1,'Stats 2020'!$D$18:$J$18,0),0) -> #N/A | V74: =VLOOKUP($B75,'Stats 2020'!$D$25:$J$89,MATCH(Graphs!V$1,'Stats 2020'!$D$18:$J$18,0),0) -> #N/A | X74: =B74 -> 44358 | Y74: =SUM(Q$2:Q74)/COUNTA($P$2:$P74) -> #N/A | Z74: =SUM(R$2:R74)/COUNTA($P$2:$P74) -> #N/A | AA74: =SUM(S$2:S74)/COUNTA($P$2:$P74) -> #N/A | AB74: =SUM(T$2:T74)/COUNTA($P$2:$P74) -> #N/A | AC74: =SUM(U$2:U74)/COUNTA($P$2:$P74) -> #N/A | AD74: =SUM(V$2:V74)/COUNTA($P$2:$P74) -> #N/A | AE74: =AVERAGE(Y74:AD74) -> #N/A | AF74: =VLOOKUP($A74,$X$1:$AE$59,MATCH(AF$1,$X$1:$AE$1,0),0) -> #N/A | AG74: =VLOOKUP($A74,$X$1:$AE$59,MATCH(AG$1,$X$1:$AE$1,0),0) -> #N/A | AH74: =VLOOKUP($A74,$X$1:$AE$59,MATCH(AH$1,$X$1:$AE$1,0),0) -> #N/A | AI74: =VLOOKUP($A74,$X$1:$AE$59,MATCH(AI$1,$X$1:$AE$1,0),0) -> #N/A | AJ74: =VLOOKUP($A74,$X$1:$AE$59,MATCH(AJ$1,$X$1:$AE$1,0),0) -> #N/A | AK74: =VLOOKUP($A74,$X$1:$AE$59,MATCH(AK$1,$X$1:$AE$1,0),0) -> #N/A | AL74: =VLOOKUP($A74,$X$1:$AE$59,MATCH(AL$1,$X$1:$AE$1,0),0) -> #N/A
A75: =IF(AND((TODAY()-B75)<7,(TODAY()-B75>=0)),B75,NA()) -> #N/A | B75: =B74+7 -> 44365 | C75: =IF($B75<=TODAY(),SUMIF('Stats 2020'!$M$24:$M$1048576,"<="&Graphs!$B75,'Stats 2020'!O$24:O$1048576),NA()) -> 215 | D75: =IF($B75<=TODAY(),MAX($C75,$E75,$G75,$H75)+11+16.5,NA()) -> 242.5 | E75: =IF($B75<=TODAY(),SUMIF('Stats 2020'!$M$24:$M$1048576,"<="&Graphs!$B75,'Stats 2020'!Q$24:Q$1048576),NA()) -> 193 | F75: =IF($B75<=TODAY(),MAX($C75,$E75,$G75,$H75)+11+16.5,NA()) -> 242.5 | G75: =IF($B75<=TODAY(),SUMIF('Stats 2020'!$M$24:$M$1048576,"<="&Graphs!$B75,'Stats 2020'!S$24:S$1048576),NA()) -> 187.5 | H75: =IF($B75<=TODAY(),SUMIF('Stats 2020'!$M$24:$M$1048576,"<="&Graphs!$B75,'Stats 2020'!T$24:T$1048576),NA()) -> 123.75 | I75: =VLOOKUP($A75,$B$1:$H$59,MATCH(I$1,$B$1:$H$1,0),0) -> #N/A | J75: =VLOOKUP($A75,$B$1:$H$59,MATCH(J$1,$B$1:$H$1,0),0) -> #N/A | K75: =VLOOKUP($A75,$B$1:$H$59,MATCH(K$1,$B$1:$H$1,0),0) -> #N/A | L75: =VLOOKUP($A75,$B$1:$H$59,MATCH(L$1,$B$1:$H$1,0),0) -> #N/A | M75: =VLOOKUP($A75,$B$1:$H$59,MATCH(M$1,$B$1:$H$1,0),0) -> #N/A | N75: =VLOOKUP($A75,$B$1:$H$59,MATCH(N$1,$B$1:$H$1,0),0) -> #N/A | X75: =B75 -> 44365 | Y75: =SUM(Q$2:Q75)/COUNTA($P$2:$P75) -> #N/A | Z75: =SUM(R$2:R75)/COUNTA($P$2:$P75) -> #N/A | AA75: =SUM(S$2:S75)/COUNTA($P$2:$P75) -> #N/A | AB75: =SUM(T$2:T75)/COUNTA($P$2:$P75) -> #N/A | AC75: =SUM(U$2:U75)/COUNTA($P$2:$P75) -> #N/A | AD75: =SUM(V$2:V75)/COUNTA($P$2:$P75) -> #N/A | AE75: =AVERAGE(Y75:AD75) -> #N/A | AF75: =VLOOKUP($A75,$X$1:$AE$59,MATCH(AF$1,$X$1:$AE$1,0),0) -> #N/A | AG75: =VLOOKUP($A75,$X$1:$AE$59,MATCH(AG$1,$X$1:$AE$1,0),0) -> #N/A | AH75: =VLOOKUP($A75,$X$1:$AE$59,MATCH(AH$1,$X$1:$AE$1,0),0) -> #N/A | AI75: =VLOOKUP($A75,$X$1:$AE$59,MATCH(AI$1,$X$1:$AE$1,0),0) -> #N/A | AJ75: =VLOOKUP($A75,$X$1:$AE$59,MATCH(AJ$1,$X$1:$AE$1,0),0) -> #N/A | AK75: =VLOOKUP($A75,$X$1:$AE$59,MATCH(AK$1,$X$1:$AE$1,0),0) -> #N/A | AL75: =VLOOKUP($A75,$X$1:$AE$59,MATCH(AL$1,$X$1:$AE$1,0),0) -> #N/A
A76: =IF(AND((TODAY()-B76)<7,(TODAY()-B76>=0)),B76,NA()) -> #N/A | B76: =B75+7 -> 44372 | C76: =IF($B76<=TODAY(),SUMIF('Stats 2020'!$M$24:$M$1048576,"<="&Graphs!$B76,'Stats 2020'!O$24:O$1048576),NA()) -> 215 | D76: =IF($B76<=TODAY(),MAX($C76,$E76,$G76,$H76)+11+16.5,NA()) -> 242.5 | E76: =IF($B76<=TODAY(),SUMIF('Stats 2020'!$M$24:$M$1048576,"<="&Graphs!$B76,'Stats 2020'!Q$24:Q$1048576),NA()) -> 193 | F76: =IF($B76<=TODAY(),MAX($C76,$E76,$G76,$H76)+11+16.5,NA()) -> 242.5 | G76: =IF($B76<=TODAY(),SUMIF('Stats 2020'!$M$24:$M$1048576,"<="&Graphs!$B76,'Stats 2020'!S$24:S$1048576),NA()) -> 187.5 | H76: =IF($B76<=TODAY(),SUMIF('Stats 2020'!$M$24:$M$1048576,"<="&Graphs!$B76,'Stats 2020'!T$24:T$1048576),NA()) -> 123.75 | I76: =VLOOKUP($A76,$B$1:$H$59,MATCH(I$1,$B$1:$H$1,0),0) -> #N/A | J76: =VLOOKUP($A76,$B$1:$H$59,MATCH(J$1,$B$1:$H$1,0),0) -> #N/A | K76: =VLOOKUP($A76,$B$1:$H$59,MATCH(K$1,$B$1:$H$1,0),0) -> #N/A | L76: =VLOOKUP($A76,$B$1:$H$59,MATCH(L$1,$B$1:$H$1,0),0) -> #N/A | M76: =VLOOKUP($A76,$B$1:$H$59,MATCH(M$1,$B$1:$H$1,0),0) -> #N/A | N76: =VLOOKUP($A76,$B$1:$H$59,MATCH(N$1,$B$1:$H$1,0),0) -> #N/A | P76: =B77 -> 44379 | Q76: =VLOOKUP($B77,'Stats 2020'!$D$25:$J$89,MATCH(Graphs!Q$1,'Stats 2020'!$D$18:$J$18,0),0) -> #N/A | R76: =VLOOKUP($B77,'Stats 2020'!$D$25:$J$89,MATCH(Graphs!R$1,'Stats 2020'!$D$18:$J$18,0),0) -> #N/A | S76: =VLOOKUP($B77,'Stats 2020'!$D$25:$J$89,MATCH(Graphs!S$1,'Stats 2020'!$D$18:$J$18,0),0) -> #N/A | T76: =VLOOKUP($B77,'Stats 2020'!$D$25:$J$89,MATCH(Graphs!T$1,'Stats 2020'!$D$18:$J$18,0),0) -> #N/A | U76: =VLOOKUP($B77,'Stats 2020'!$D$25:$J$89,MATCH(Graphs!U$1,'Stats 2020'!$D$18:$J$18,0),0) -> #N/A | V76: =VLOOKUP($B77,'Stats 2020'!$D$25:$J$89,MATCH(Graphs!V$1,'Stats 2020'!$D$18:$J$18,0),0) -> #N/A | X76: =B76 -> 44372 | Y76: =SUM(Q$2:Q76)/COUNTA($P$2:$P76) -> #N/A | Z76: =SUM(R$2:R76)/COUNTA($P$2:$P76) -> #N/A | AA76: =SUM(S$2:S76)/COUNTA($P$2:$P76) -> #N/A | AB76: =SUM(T$2:T76)/COUNTA($P$2:$P76) -> #N/A | AC76: =SUM(U$2:U76)/COUNTA($P$2:$P76) -> #N/A | AD76: =SUM(V$2:V76)/COUNTA($P$2:$P76) -> #N/A | AE76: =AVERAGE(Y76:AD76) -> #N/A | AF76: =VLOOKUP($A76,$X$1:$AE$59,MATCH(AF$1,$X$1:$AE$1,0),0) -> #N/A | AG76: =VLOOKUP($A76,$X$1:$AE$59,MATCH(AG$1,$X$1:$AE$1,0),0) -> #N/A | AH76: =VLOOKUP($A76,$X$1:$AE$59,MATCH(AH$1,$X$1:$AE$1,0),0) -> #N/A | AI76: =VLOOKUP($A76,$X$1:$AE$59,MATCH(AI$1,$X$1:$AE$1,0),0) -> #N/A | AJ76: =VLOOKUP($A76,$X$1:$AE$59,MATCH(AJ$1,$X$1:$AE$1,0),0) -> #N/A | AK76: =VLOOKUP($A76,$X$1:$AE$59,MATCH(AK$1,$X$1:$AE$1,0),0) -> #N/A | AL76: =VLOOKUP($A76,$X$1:$AE$59,MATCH(AL$1,$X$1:$AE$1,0),0) -> #N/A
A77: =IF(AND((TODAY()-B77)<7,(TODAY()-B77>=0)),B77,NA()) -> #N/A | B77: =B76+7 -> 44379 | C77: =IF($B77<=TODAY(),SUMIF('Stats 2020'!$M$24:$M$1048576,"<="&Graphs!$B77,'Stats 2020'!O$24:O$1048576),NA()) -> 215 | D77: =IF($B77<=TODAY(),MAX($C77,$E77,$G77,$H77)+11+16.5,NA()) -> 242.5 | E77: =IF($B77<=TODAY(),SUMIF('Stats 2020'!$M$24:$M$1048576,"<="&Graphs!$B77,'Stats 2020'!Q$24:Q$1048576),NA()) -> 193 | F77: =IF($B77<=TODAY(),MAX($C77,$E77,$G77,$H77)+11+16.5,NA()) -> 242.5 | G77: =IF($B77<=TODAY(),SUMIF('Stats 2020'!$M$24:$M$1048576,"<="&Graphs!$B77,'Stats 2020'!S$24:S$1048576),NA()) -> 187.5 | H77: =IF($B77<=TODAY(),SUMIF('Stats 2020'!$M$24:$M$1048576,"<="&Graphs!$B77,'Stats 2020'!T$24:T$1048576),NA()) -> 123.75 | I77: =VLOOKUP($A77,$B$1:$H$59,MATCH(I$1,$B$1:$H$1,0),0) -> #N/A | J77: =VLOOKUP($A77,$B$1:$H$59,MATCH(J$1,$B$1:$H$1,0),0) -> #N/A | K77: =VLOOKUP($A77,$B$1:$H$59,MATCH(K$1,$B$1:$H$1,0),0) -> #N/A | L77: =VLOOKUP($A77,$B$1:$H$59,MATCH(L$1,$B$1:$H$1,0),0) -> #N/A | M77: =VLOOKUP($A77,$B$1:$H$59,MATCH(M$1,$B$1:$H$1,0),0) -> #N/A | N77: =VLOOKUP($A77,$B$1:$H$59,MATCH(N$1,$B$1:$H$1,0),0) -> #N/A | X77: =B77 -> 44379 | Y77: =SUM(Q$2:Q77)/COUNTA($P$2:$P77) -> #N/A | Z77: =SUM(R$2:R77)/COUNTA($P$2:$P77) -> #N/A | AA77: =SUM(S$2:S77)/COUNTA($P$2:$P77) -> #N/A | AB77: =SUM(T$2:T77)/COUNTA($P$2:$P77) -> #N/A | AC77: =SUM(U$2:U77)/COUNTA($P$2:$P77) -> #N/A | AD77: =SUM(V$2:V77)/COUNTA($P$2:$P77) -> #N/A | AE77: =AVERAGE(Y77:AD77) -> #N/A | AF77: =VLOOKUP($A77,$X$1:$AE$59,MATCH(AF$1,$X$1:$AE$1,0),0) -> #N/A | AG77: =VLOOKUP($A77,$X$1:$AE$59,MATCH(AG$1,$X$1:$AE$1,0),0) -> #N/A | AH77: =VLOOKUP($A77,$X$1:$AE$59,MATCH(AH$1,$X$1:$AE$1,0),0) -> #N/A | AI77: =VLOOKUP($A77,$X$1:$AE$59,MATCH(AI$1,$X$1:$AE$1,0),0) -> #N/A | AJ77: =VLOOKUP($A77,$X$1:$AE$59,MATCH(AJ$1,$X$1:$AE$1,0),0) -> #N/A | AK77: =VLOOKUP($A77,$X$1:$AE$59,MATCH(AK$1,$X$1:$AE$1,0),0) -> #N/A | AL77: =VLOOKUP($A77,$X$1:$AE$59,MATCH(AL$1,$X$1:$AE$1,0),0) -> #N/A
A78: =IF(AND((TODAY()-B78)<7,(TODAY()-B78>=0)),B78,NA()) -> #N/A | B78: =B77+7 -> 44386 | C78: =IF($B78<=TODAY(),SUMIF('Stats 2020'!$M$24:$M$1048576,"<="&Graphs!$B78,'Stats 2020'!O$24:O$1048576),NA()) -> 215 | D78: =IF($B78<=TODAY(),MAX($C78,$E78,$G78,$H78)+11+16.5,NA()) -> 242.5 | E78: =IF($B78<=TODAY(),SUMIF('Stats 2020'!$M$24:$M$1048576,"<="&Graphs!$B78,'Stats 2020'!Q$24:Q$1048576),NA()) -> 193 | F78: =IF($B78<=TODAY(),MAX($C78,$E78,$G78,$H78)+11+16.5,NA()) -> 242.5 | G78: =IF($B78<=TODAY(),SUMIF('Stats 2020'!$M$24:$M$1048576,"<="&Graphs!$B78,'Stats 2020'!S$24:S$1048576),NA()) -> 187.5 | H78: =IF($B78<=TODAY(),SUMIF('Stats 2020'!$M$24:$M$1048576,"<="&Graphs!$B78,'Stats 2020'!T$24:T$1048576),NA()) -> 123.75 | I78: =VLOOKUP($A78,$B$1:$H$59,MATCH(I$1,$B$1:$H$1,0),0) -> #N/A | J78: =VLOOKUP($A78,$B$1:$H$59,MATCH(J$1,$B$1:$H$1,0),0) -> #N/A | K78: =VLOOKUP($A78,$B$1:$H$59,MATCH(K$1,$B$1:$H$1,0),0) -> #N/A | L78: =VLOOKUP($A78,$B$1:$H$59,MATCH(L$1,$B$1:$H$1,0),0) -> #N/A | M78: =VLOOKUP($A78,$B$1:$H$59,MATCH(M$1,$B$1:$H$1,0),0) -> #N/A | N78: =VLOOKUP($A78,$B$1:$H$59,MATCH(N$1,$B$1:$H$1,0),0) -> #N/A | P78: =B79 -> 0 | Q78: =VLOOKUP($B79,'Stats 2020'!$D$25:$J$89,MATCH(Graphs!Q$1,'Stats 2020'!$D$18:$J$18,0),0) -> #N/A | R78: =VLOOKUP($B79,'Stats 2020'!$D$25:$J$89,MATCH(Graphs!R$1,'Stats 2020'!$D$18:$J$18,0),0) -> #N/A | S78: =VLOOKUP($B79,'Stats 2020'!$D$25:$J$89,MATCH(Graphs!S$1,'Stats 2020'!$D$18:$J$18,0),0) -> #N/A | T78: =VLOOKUP($B79,'Stats 2020'!$D$25:$J$89,MATCH(Graphs!T$1,'Stats 2020'!$D$18:$J$18,0),0) -> #N/A | U78: =VLOOKUP($B79,'Stats 2020'!$D$25:$J$89,MATCH(Graphs!U$1,'Stats 2020'!$D$18:$J$18,0),0) -> #N/A | V78: =VLOOKUP($B79,'Stats 2020'!$D$25:$J$89,MATCH(Graphs!V$1,'Stats 2020'!$D$18:$J$18,0),0) -> #N/A | X78: =B78 -> 44386 | Y78: =SUM(Q$2:Q78)/COUNTA($P$2:$P78) -> #N/A | Z78: =SUM(R$2:R78)/COUNTA($P$2:$P78) -> #N/A | AA78: =SUM(S$2:S78)/COUNTA($P$2:$P78) -> #N/A | AB78: =SUM(T$2:T78)/COUNTA($P$2:$P78) -> #N/A | AC78: =SUM(U$2:U78)/COUNTA($P$2:$P78) -> #N/A | AD78: =SUM(V$2:V78)/COUNTA($P$2:$P78) -> #N/A | AE78: =AVERAGE(Y78:AD78) -> #N/A | AF78: =VLOOKUP($A78,$X$1:$AE$59,MATCH(AF$1,$X$1:$AE$1,0),0) -> #N/A | AG78: =VLOOKUP($A78,$X$1:$AE$59,MATCH(AG$1,$X$1:$AE$1,0),0) -> #N/A | AH78: =VLOOKUP($A78,$X$1:$AE$59,MATCH(AH$1,$X$1:$AE$1,0),0) -> #N/A | AI78: =VLOOKUP($A78,$X$1:$AE$59,MATCH(AI$1,$X$1:$AE$1,0),0) -> #N/A | AJ78: =VLOOKUP($A78,$X$1:$AE$59,MATCH(AJ$1,$X$1:$AE$1,0),0) -> #N/A | AK78: =VLOOKUP($A78,$X$1:$AE$59,MATCH(AK$1,$X$1:$AE$1,0),0) -> #N/A | AL78: =VLOOKUP($A78,$X$1:$AE$59,MATCH(AL$1,$X$1:$AE$1,0),0) -> #N/A

Sheet Stats 2026
C2: DF Statistics
C5: Participation: | M5: Debitors: | O5: TOTAL ASSETS | T5: =W16 -> 6838.25 | V5: Has proudly worn his own DF Shirt and PIN at QUO VADIS V1 (2020) | X5: Ämtli | Z5: Other titles
B7: Rank | C7: Name: | D7: Points: | E7: %: | F7: %m: | N7: Name: | O7: Amount: | P7: Paid: | Q7: Access to DF chlopfetä: | S7: Special Treatment:
B8: =RANK(G13,$G$8:$G$13,1) + COUNTIFS($G$8:$G$13,G13,$H$8:$H$13,">"&H13) -> 1 | C8: MSO | D8: =ROUND(HLOOKUP(C8,$E$18:$J$20,3,FALSE),0) -> 34 | E8: =D8/$C$20 -> 0.80952381 | F8: =1-E8 -> 0.19047619 | G8: =RANK(D10,$D$8:$D$13,0) -> 3 | H8: =RANK(E21,$E$21:$J$21,0) -> 4 | N8: YMI | O8: =R20 -> 282 | P8: 0 | S8: njet | V8: si, grande | X8: Kassier, DFQV-Mitorganisierer | Z8: Symposierer
B9: =RANK(G12,$G$8:$G$13,1) + COUNTIFS($G$8:$G$13,G12,$H$8:$H$13,">"&H12) -> 2 | C9: SJU | D9: =ROUND(HLOOKUP(C9,$E$18:$J$20,3,FALSE),0) -> 29 | E9: =D9/$C$20 -> 0.69047619 | F9: =1-E9 -> 0.30952381 | G9: =RANK(D13,$D$8:$D$13,0) -> 6 | H9: =RANK(F21,$E$21:$J$21,0) -> 3 | N9: CBO | O9: =P20 -> 382 | P9: 0 | S9: njet | V9: njet, vergesse im Estrich | X9: Massregler, DFQV-Mitorganisierer | Z9: Marketingchef
B10: =RANK(G8,$G$8:$G$13,1) + COUNTIFS($G$8:$G$13,G8,$H$8:$H$13,">"&H8) -> 3 | C10: JWU | D10: =ROUND(HLOOKUP(C10,$E$18:$J$20,3,FALSE),0) -> 23 | E10: =D10/$C$20 -> 0.54761905 | F10: =1-E10 -> 0.45238095 | G10: =RANK(D11,$D$8:$D$13,0) -> 5 | H10: =RANK(G21,$E$21:$J$21,0) -> 5 | N10: SJU | O10: =S20 -> 201.75 | P10: 0 | S10: njet | V10: si, grande | X10: Präsident, Iladigsversender | Z10: Loyalitätspokalhalter
B11: =RANK(G10,$G$8:$G$13,1) + COUNTIFS($G$8:$G$13,G10,$H$8:$H$13,">"&H10) -> 5 | C11: PKN | D11: =ROUND(HLOOKUP(C11,$E$18:$J$20,3,FALSE),0) -> 19 | E11: =D11/$C$20 -> 0.45238095 | F11: =1-E11 -> 0.54761905 | G11: =RANK(D12,$D$8:$D$13,0) -> 4 | H11: =RANK(H21,$E$21:$J$21,0) -> 5 | N11: PKN | O11: =Q20 -> 321 | P11: 0 | S11: njet | V11: si, grande | X11: Auditor | Z11: Brügler Ultralight
B12: =RANK(G11,$G$8:$G$13,1) + COUNTIFS($G$8:$G$13,G11,$H$8:$H$13,">"&H11) -> 4 | C12: YMI | D12: =ROUND(HLOOKUP(C12,$E$18:$J$20,3,FALSE),0) -> 22 | E12: =D12/$C$20 -> 0.52380952 | F12: =1-E12 -> 0.47619048 | G12: =RANK(D9,$D$8:$D$13,0) -> 2 | H12: =RANK(I21,$E$21:$J$21,0) -> 2 | N12: JWU | O12: =O20 -> 272.25 | P12: 0 | S12: njet | V12: njet, vergesse bi dä Erika | X12: Protokollfüehrer vo GVs und Chlopfete (nie Statistiker gsi, offiziell bestätigt) | Z12: Blöffer, Wiederiträtter
B13: =RANK(G9,$G$8:$G$13,1) + COUNTIFS($G$8:$G$13,G9,$H$8:$H$13,">"&H9) -> 6 | C13: CBO | D13: =ROUND(HLOOKUP(C13,$E$18:$J$20,3,FALSE),0) -> 15 | E13: =D13/$C$20 -> 0.35714286 | F13: =1-E13 -> 0.64285714 | G13: =RANK(D8,$D$8:$D$13,0) -> 1 | H13: =RANK(J21,$E$21:$J$21,0) -> 1 | N13: MST | O13: =T20 -> 141.25 | P13: 0 | S13: njet | V13: si, scho am Flughafe blöfft | X13: "Hauptstatistiker", Vizepräsident, "Vize-iladigsversender", Frauebeuftreite, Glichberechtigungsbeamte | Z13: Statistikskönig
Q15: Rückstellungen für Merchandise | S15: 1000 | V15: Available | W15: =O16+S16 -> 5838.25
N16: DEBITORS TOTAL: | O16: =SUM(O8:O13) -> 1600.25 | Q16: Investments TOTAL*: | S16: ='Stats 2025'!W16-'Stats 2025'!O16-120-S15 -> 4238 | T16: Wert 05.12.2025 | V16: Total | W16: =S16+S15+O16 -> 6838.25
E17: =RANK(E20,$E20:$J20) -> 3 | F17: =RANK(F20,$E20:$J20) -> 6 | G17: =RANK(G20,$E20:$J20) -> 5 | H17: =RANK(H20,$E20:$J20) -> 4 | I17: =RANK(I20,$E20:$J20) -> 2 | J17: =RANK(J20,$E20:$J20) -> 1
E18: JWU | F18: CBO | G18: PKN | H18: YMI | I18: SJU | J18: MSO | O18: #VALUE! | P18: CBO | Q18: PKN | R18: YMI | S18: SJU | T18: MST
